Workbook
Name CANTIDAD_EQUIPOS: 'CONSOLIDADO VTAS'!$B:$B
Name CLIENTE: 'CONSOLIDADO VTAS'!$C:$C
Name DIAS_VTO: 'CONSOLIDADO VTAS'!$T:$T
Name ESTADO_ENTREGA: 'CONSOLIDADO VTAS'!$G:$G
Name FC_SUCRO: 'CONSOLIDADO VTAS'!$E:$E
Name FECHA_ENTREGA: 'CONSOLIDADO VTAS'!$H:$H
Name FECHA_FC: 'CONSOLIDADO VTAS'!$D:$D
Name FECHA_RETIRO_VALORES: 'CONSOLIDADO VTAS'!$R:$R
Name FECHA_VTO_VALORES: 'CONSOLIDADO VTAS'!$S:$S
Name FORMA_PAGO: 'CONSOLIDADO VTAS'!$V:$V
Name IVA: 'CONSOLIDADO VTAS'!$L:$L
Name KGS: 'CONSOLIDADO VTAS'!$I:$I
Name MES: Tabla1[[#Headers],[MES]]
Name OC: 'CONSOLIDADO VTAS'!$X:$X
Name PENDIENTE_DE_COBRO: 'CONSOLIDADO VTAS'!$O:$O
Name PENDIENTE_DE_ENTREGA: 'CONSOLIDADO VTAS'!$N:$N
Name PLAZO_PAGO_DIAS: 'CONSOLIDADO VTAS'!$U:$U
Name PLAZO_VALORES: 'CONSOLIDADO VTAS'!$AR:$AR
Name PRECIO_POR_KILO: 'CONSOLIDADO VTAS'!$J:$J
Name PRODUCTO: 'CONSOLIDADO VTAS'!$F:$F
Name SEMANA_ACREDITACION_PAGO: 'CONSOLIDADO VTAS'!$W:$W
Name SUBTOTAL: 'CONSOLIDADO VTAS'!$K:$K
Name TASA_FINANCIACION_MENSUAL: 'CONSOLIDADO VTAS'!$AP:$AP
Name TOTAL: 'CONSOLIDADO VTAS'!$M:$M
Name VALORES_COBRADOS: 'CONSOLIDADO VTAS'!$Q:$Q
Name VALORES_EN_CARTERA: 'CONSOLIDADO VTAS'!$P:$P

Sheet KPI´S
A1: ZAFRA 25 KPI´S MES
C3: 46143 | D3: =+C3+31 -> 46174 | E3: =+D3+31 -> 46205 | F3: =+E3+31 -> 46236 | G3: =+F3+31 -> 46267 | H3: =+G3+31 -> 46298 | I3: =+H3+31 -> 46329 | J3: =+I3+31 -> 46360 | K3: =+J3+31 -> 46391 | ... N3: =+M3+31 -> 46484 | O3: TOTAL ACUM.
A5: TOTAL BOLSAS Z25 | B5: (Unidades 50Kg) | C5: =+ACUMULADOS!Z2 -> 70186.92 | D5: =+ACUMULADOS!Z4 -> 104239.6 | E5: =+ACUMULADOS!Z7 -> 70284 | F5: =+ACUMULADOS!Z10 -> 0 | G5: =+ACUMULADOS!Z13 -> 0 | H5: =+ACUMULADOS!Z16 -> 0 | I5: =+ACUMULADOS!Z19 -> 0 | J5: =+ACUMULADOS!Z22 -> 0 | K5: =+ACUMULADOS!Z25 -> 0 | L5: =+ACUMULADOS!Z28 -> 0 | M5: =+ACUMULADOS!Z31 -> 0 | N5: =+ACUMULADOS!Z34 -> 0 | O5: =SUM(C5:N5) -> 244710.52
A7: TOTAL TONELADAS | C7: =+C5*0.05 -> 3509.346 | D7: =+D5*0.05 -> 5211.98 | E7: =+E5*0.05 -> 3514.2 | F7: =+F5*0.05 -> 0 | G7: =+G5*0.05 -> 0 | H7: =+H5*0.05 -> 0 | I7: =+I5*0.05 -> 0 | J7: =+J5*0.05 -> 0 | ... N7: =+N5*0.05 -> 0 | O7: =SUM(C7:N7) -> 12235.526
A9: VENTA BRUTA INDUSTRIA | B9: ($ Millones) | C9: =+ACUMULADOS!M2/1000000 -> 2338.6576 | D9: =+ACUMULADOS!M4/1000000 -> 3022.2142 | E9: =+ACUMULADOS!M7/1000000 -> 2010.7204 | F9: =+ACUMULADOS!M10/1000000 -> 0 | G9: =ACUMULADOS!M13/1000000 -> 0 | H9: =+ACUMULADOS!M16/1000000 -> 0 | I9: =+ACUMULADOS!M19/1000000 -> 0 | J9: =+ACUMULADOS!M22/1000000 -> 0 | K9: =ACUMULADOS!M25/1000000 -> 0 | L9: =+ACUMULADOS!M28/1000000 -> 0 | M9: =+ACUMULADOS!M31/1000000 -> 0 | N9: =ACUMULADOS!M34/1000000 -> 0 | O9: =SUM(C9:N9) -> 7371.5922
B10: ($USD Miles) | C10: =+C9/C54*1000 -> 1656.2731 | D10: =+D9/D54*1000 -> 1989.7297 | E10: =+E9/E54*1000 -> 1300.3874 | F10: =+F9/F54*1000 -> 0 | G10: =+G9/G54*1000 -> 0 | H10: =+H9/H54*1000 -> 0 | I10: =+I9/I54*1000 -> 0 | J10: =+J9/J54*1000 -> 0 | ... N10: =+N9/N54*1000 -> 0 | O10: =SUM(C10:N10) -> 4946.3902
A12: PRECIO FOB CDO TUC BOLSA 50 KG | B12: (Bolsa 50kg) | C12: =+ACUMULADOS!AE3 -> 32106.914 | D12: =+ACUMULADOS!AE5 -> 29204.472 | E12: =+ACUMULADOS!AE8 -> #VALUE! | F12: =+ACUMULADOS!AE11 -> #VALUE! | G12: =+ACUMULADOS!AE14 -> #VALUE! | H12: =+ACUMULADOS!AE17 -> #VALUE! | I12: =+ACUMULADOS!AE20 -> #VALUE! | J12: =+ACUMULADOS!AE23 -> #VALUE! | K12: =+ACUMULADOS!AE26 -> #VALUE! | L12: =+ACUMULADOS!AE29 -> #VALUE! | M12: =+ACUMULADOS!AE32 -> #VALUE! | N12: =+ACUMULADOS!AE35 -> #VALUE! | O12: =AVERAGE(C12:N12) -> #VALUE!
A13: PRECIO FOB CDO TUC KG | B13: ($) IVA INC | C13: =+C12/50 -> 642.13829 | D13: =+D12/50 -> 584.08944 | E13: =+E12/50 -> #VALUE! | F13: =+F12/50 -> #VALUE! | G13: =+G12/50 -> #VALUE! | H13: =+H12/50 -> #VALUE! | I13: =+I12/50 -> #VALUE! | J13: =+J12/50 -> #VALUE! | ... O13: =+O12/50 -> #VALUE!
A14: PRECIO FOB CDO TUC KG | B14: ($USD) IVA INC | C14: =+C13/C54 -> 0.45477216 | D14: =+D13/D54 -> 0.38454591 | E14: =+E13/E54 -> #VALUE! | F14: =+F13/F54 -> #VALUE! | G14: =+G13/G54 -> #VALUE! | H14: =+H13/H54 -> #VALUE! | I14: =+I13/I54 -> #VALUE! | J14: =+J13/J54 -> #VALUE! | ... O14: =+O13/O54 -> #VALUE!
A16: PRECIO CACTU COMPARABLE | C16: =+ACUMULADOS!AJ3 -> 34174.432 | D16: =+ACUMULADOS!AJ5 -> 33811.815 | E16: =+ACUMULADOS!AJ8 -> 33759.479 | F16: =+ACUMULADOS!AJ11 -> #DIV/0! | G16: =+ACUMULADOS!AJ14 -> #DIV/0! | H16: =+ACUMULADOS!AJ17 -> #DIV/0! | I16: =+ACUMULADOS!AJ20 -> #DIV/0! | J16: =+ACUMULADOS!AJ23 -> #DIV/0! | K16: =+ACUMULADOS!AJ26 -> #DIV/0! | L16: =+ACUMULADOS!AJ29 -> #DIV/0! | M16: =+ACUMULADOS!AJ32 -> #DIV/0! | N16: =+ACUMULADOS!AJ35 -> #DIV/0! | O16: =AVERAGE(C16:N16) -> #DIV/0!
A17: GAP VS. CACTU | B17: % | C17: =+ACUMULADOS!AO3 -> -0.06634543 | D17: =+ACUMULADOS!AO5 -> -0.13797056 | E17: =+ACUMULADOS!AO8 -> #VALUE! | F17: =+ACUMULADOS!AO11 -> #VALUE! | G17: =+ACUMULADOS!AO14 -> #VALUE! | H17: =+ACUMULADOS!AO17 -> #VALUE! | I17: =+ACUMULADOS!AO20 -> #VALUE! | J17: =+ACUMULADOS!AO23 -> #VALUE! | K17: =+ACUMULADOS!AO26 -> #VALUE! | L17: =+ACUMULADOS!AO29 -> #VALUE! | M17: =+ACUMULADOS!AO32 -> #VALUE! | N17: =+ACUMULADOS!AO35 -> #VALUE! | O17: =AVERAGE(C17:N17) -> #VALUE!
A18: MARGEN IND VS CACTU | B18: ($ Millones) | C18: =+C17*C9 -> -155.15925 | D18: =+D17*D9 -> -416.97659 | E18: =+E17*E9 -> #VALUE! | F18: =+F17*F9 -> #VALUE! | G18: =+G17*G9 -> #VALUE! | H18: =+H17*H9 -> #VALUE! | I18: =+I17*I9 -> #VALUE! | J18: =+J17*J9 -> #VALUE! | ... N18: =+N17*N9 -> #VALUE! | O18: =SUM(C18:N18) -> #VALUE!
A20: PRECIO VENTA PROMEDIO
A21: KG A PLAZO EN CLIENTE | B21: ($) IVA INC | C21: =+C9*1000000/(C5*50) -> 666.40839 | D21: =+D9*1000000/(D5*50) -> 579.85913 | E21: =+E9*1000000/(E5*50) -> 572.17017 | F21: =+F9*1000000/(F5*50) -> #DIV/0! | G21: =+G9*1000000/(G5*50) -> #DIV/0! | H21: =+H9*1000000/(H5*50) -> #DIV/0! | I21: =+I9*1000000/(I5*50) -> #DIV/0! | J21: =+J9*1000000/(J5*50) -> #DIV/0! | ... N21: =+N9*1000000/(N5*50) -> #DIV/0! | O21: =+(O9*1000000)/(O7*1000) -> 602.47448
A22: PRECIO POR KG A PLAZO EN CLIENTE | B22: ($) SIN IVA | C22: =+C21/(1+C63) -> 586.62711 | D22: =+D21/(1+D63) -> 495.5468 | E22: =+E21/(1+E63) -> 521.57718 | F22: =+F21/(1+F63) -> #DIV/0! | G22: =+G21/(1+G63) -> #DIV/0! | H22: =+H21/(1+H63) -> #DIV/0! | I22: =+I21/(1+I63) -> #DIV/0! | J22: =+J21/(1+J63) -> #DIV/0! | ... N22: =+N21/(1+N63) -> #DIV/0! | O22: =+((O9*1000000)/(1+'CONSOLIDADO VTAS'!L881))/(KPI´S!O7*1000) -> 505.33715
A23: PRECIO POR TN A PLAZO EN CLIENTE | B23: (USD) SIN IVA | C23: =+C22/C54*1000 -> 415.45829 | D23: =+D22/D54*1000 -> 326.25225 | E23: =+E22/E54*1000 -> 337.3181 | F23: =+F22/F54*1000 -> #DIV/0! | G23: =+G22/G54*1000 -> #DIV/0! | H23: =+H22/H54*1000 -> #DIV/0! | I23: =+I22/I54*1000 -> #DIV/0! | J23: =+J22/J54*1000 -> #DIV/0! | ... N23: =+N22/N54*1000 -> #DIV/0! | O23: =+O10*1000/(1+'CONSOLIDADO VTAS'!L881)/KPI´S!O7 -> 339.08478
A24: PRECIO VENTA BRUTO BOLSA 50KG | B24: ($) IVA INC | C24: =+C9*1000000/C5 -> 33320.42 | D24: =+D9*1000000/D5 -> 28992.956 | E24: =+E9*1000000/E5 -> 28608.508 | F24: =+F9*1000000/F5 -> #DIV/0! | G24: =+G9*1000000/G5 -> #DIV/0! | H24: =+H9*1000000/H5 -> #DIV/0! | I24: =+I9*1000000/I5 -> #DIV/0! | J24: =+J9*1000000/J5 -> #DIV/0! | ... O24: =+O9*1000000/O5 -> 30123.724
A26: PRECIO BUE 30D
A27: PRECIO FOB BUE A PLAZO | B27: Bolsa 50 KG | C27: =+(C12-C57)*(1+C63) -> 33065.455 | D27: =+(D12-D57)*(1+D63) -> 30662.901 | E27: =+(E12-E57)*(1+E63) -> #VALUE! | F27: =+(F12-F57)*(1+F63) -> #VALUE! | G27: =+(G12-G57)*(1+G63) -> #VALUE! | H27: =+(H12-H57)*(1+H63) -> #VALUE! | I27: =+(I12-I57)*(1+I63) -> #VALUE! | J27: =+(J12-J57)*(1+J63) -> #VALUE! | ... N27: =+(N12-N57)*(1+N63) -> #VALUE!
A28: FINANCIACION A 30D | B28: Bolsa 50 KG | C28: =+C56*C12 -> 923.62357 | D28: =+D56*D12 -> 840.12864 | E28: =+E56*E12 -> #VALUE! | F28: =+F56*F12 -> #VALUE! | G28: =+G56*G12 -> #VALUE! | H28: =+H56*H12 -> #VALUE! | I28: =+I56*I12 -> #VALUE! | J28: =+J56*J12 -> #VALUE! | ... N28: =+N56*N12 -> #VALUE!
A29: PRECIO FOB BUE 30D | B29: Bolsa 50 KG | C29: =SUM(C27:C28) -> 33989.078 | D29: =SUM(D27:D28) -> 31503.029 | E29: =SUM(E27:E28) -> #VALUE! | F29: =SUM(F27:F28) -> #VALUE! | G29: =SUM(G27:G28) -> #VALUE! | H29: =SUM(H27:H28) -> #VALUE! | I29: =SUM(I27:I28) -> #VALUE! | J29: =SUM(J27:J28) -> #VALUE! | ... N29: =SUM(N27:N28) -> #VALUE! | O29: =AVERAGE(C29:I29) -> #VALUE!
A30: PRECIO FOB BUE 30D KG | B30: ($) IVA INC | C30: =+C29/50 -> 679.78157 | D30: =+D29/50 -> 630.06059 | E30: =+E29/50 -> #VALUE! | F30: =+F29/50 -> #VALUE! | G30: =+G29/50 -> #VALUE! | H30: =+H29/50 -> #VALUE! | I30: =+I29/50 -> #VALUE! | J30: =+J29/50 -> #VALUE! | ... N30: =+N29/50 -> #VALUE! | O30: =AVERAGE(C30:I30) -> #VALUE!
A31: LA CORONA FOB BUE 30D KG | B31: ($) SIN IVA | C31: =+C22+(C64/50)-(C57/50) -> 491.44711 | D31: =+D22+(D64/50)-(D57/50) -> 407.4468 | E31: =+E22+(E64/50)-(E57/50) -> 439.57718 | F31: =+F22+(F64/50)-(F57/50) -> #DIV/0! | G31: =+G22+(G64/50)-(G57/50) -> #DIV/0! | H31: =+H22+(H64/50)-(H57/50) -> #DIV/0! | I31: =+I22+(I64/50)-(I57/50) -> #DIV/0! | J31: =+J22+(J64/50)-(J57/50) -> #DIV/0! | ... N31: =+N22+(N64/50)-(N57/50) -> #DIV/0! | O31: =AVERAGE(C31:N31) -> #DIV/0!
A32: PRECIO LEDESMA COMPARABLE | B32: ($) SIN IVA | C32: =+'RESUMEN AVANCE MES'!D9 -> 850 | D32: =+'RESUMEN AVANCE MES'!D20 -> 900 | E32: =+'RESUMEN AVANCE MES'!D31 -> 900 | F32: =+'RESUMEN AVANCE MES'!D42 -> 0 | G32: =+'RESUMEN AVANCE MES'!D53 -> 0 | H32: =+'RESUMEN AVANCE MES'!D64 -> 0 | I32: =+'RESUMEN AVANCE MES'!D75 -> 0 | J32: =+'RESUMEN AVANCE MES'!D86 -> 0 | K32: =+'RESUMEN AVANCE MES'!D97 -> 0 | L32: =+'RESUMEN AVANCE MES'!D108 -> 0 | M32: =+'RESUMEN AVANCE MES'!D119 -> 0 | N32: 870 | O32: =AVERAGE(C32:N32) -> 293.33333
A33: GAP VS. LEDESMA | C33: =+C31/C32-1 -> -0.42182693 | D33: =+D31/D32-1 -> -0.54728134 | E33: =+E31/E32-1 -> -0.51158091 | F33: =+F31/F32-1 -> #DIV/0! | G33: =+G31/G32-1 -> #DIV/0! | H33: =+H31/H32-1 -> #DIV/0! | I33: =+I31/I32-1 -> #DIV/0! | J33: =+J31/J32-1 -> #DIV/0! | ... O33: =+O31/O32-1 -> #DIV/0!
A35: COMPARACION Z25 - Z24
A36: VARIACIÓN VOLUMEN BOLSAS TOTAL | B36: (%) | C36: =C5/'COMPARATIVO ANUAL'!I10-1 -> #DIV/0! | D36: =D5/'COMPARATIVO ANUAL'!I11-1 -> #DIV/0! | E36: =E5/'COMPARATIVO ANUAL'!I12-1 -> #DIV/0! | F36: =F5/'COMPARATIVO ANUAL'!I13-1 -> #DIV/0! | G36: =G5/'COMPARATIVO ANUAL'!I14-1 -> #DIV/0! | H36: =H5/'COMPARATIVO ANUAL'!I15-1 -> #DIV/0! | I36: =I5/'COMPARATIVO ANUAL'!I16-1 -> #DIV/0! | J36: =J5/'COMPARATIVO ANUAL'!I17-1 -> #DIV/0! | K36: =K5/'COMPARATIVO ANUAL'!I18-1 -> #DIV/0! | L36: =L5/'COMPARATIVO ANUAL'!I19-1 -> #DIV/0! | M36: =M5/'COMPARATIVO ANUAL'!I20-1 -> #DIV/0! | N36: =N5/'COMPARATIVO ANUAL'!I21-1 -> #DIV/0! | O36: =+O5/O37-1 -> #DIV/0!
A37: Total BOLSAS Z24 | B37: unidades | C37: =+'COMPARATIVO ANUAL'!I10 -> 0 | D37: =+'COMPARATIVO ANUAL'!I11 -> 0 | E37: =+'COMPARATIVO ANUAL'!I12 -> 0 | F37: =+'COMPARATIVO ANUAL'!I13 -> 0 | G37: =+'COMPARATIVO ANUAL'!I14 -> 0 | H37: =+'COMPARATIVO ANUAL'!I15 -> 0 | I37: =+'COMPARATIVO ANUAL'!I16 -> 0 | J37: =+'COMPARATIVO ANUAL'!I17 -> 0 | K37: =+'COMPARATIVO ANUAL'!I18 -> 0 | L37: =+'COMPARATIVO ANUAL'!I19 -> 0 | M37: =+'COMPARATIVO ANUAL'!I20 -> 0 | N37: =+'COMPARATIVO ANUAL'!I21 -> 0 | O37: =SUM(C37:N37) -> 0
A38: VARIACION PRECIO POR KG SIN IVA
A39: Variacion % en $ | B39: % ($) | C39: =+C22/C42-1 -> 0.29011874 | D39: =+D22/D42-1 -> -0.0064829735 | E39: =+E22/E42-1 -> 0.052449725 | F39: =+F22/F42-1 -> #DIV/0! | G39: =+G22/G42-1 -> #DIV/0! | H39: =+H22/H42-1 -> #DIV/0! | I39: =+I22/I42-1 -> #DIV/0! | J39: =+J22/J42-1 -> #DIV/0! | ... N39: =+N22/N42-1 -> #DIV/0! | O39: =AVERAGE(C39:N39) -> #DIV/0!
A40: Variacion % en USD | B40: % (USD) | C40: =+((C22/C54)/(C42/C61))-1 -> 0.048476576 | D40: =+((D22/D54)/(D42/D61))-1 -> -0.22727548 | E40: =+((E22/E54)/(E42/E61))-1 -> -0.13760382 | F40: =+((F22/F54)/(F42/F61))-1 -> #DIV/0! | G40: =+((G22/G54)/(G42/G61))-1 -> #DIV/0! | H40: =+((H22/H54)/(H42/H61))-1 -> #DIV/0! | I40: =+((I22/I54)/(I42/I61))-1 -> #DIV/0! | J40: =+((J22/J54)/(J42/J61))-1 -> #DIV/0! | ... O40: =+((O22/O54)/(O42/O61))-1 -> -0.22204767
A42: Precio x KG Z24 | B42: ($) SIN IVA | C42: =+'COMPARATIVO ANUAL'!F10 -> 454.70784 | D42: =+'COMPARATIVO ANUAL'!F11 -> 498.78038 | E42: =+'COMPARATIVO ANUAL'!F12 -> 495.58394 | F42: =+'COMPARATIVO ANUAL'!F13 -> 443.34077 | G42: =+'COMPARATIVO ANUAL'!F14 -> 421.68591 | H42: =+'COMPARATIVO ANUAL'!F15 -> 453.84908 | I42: =+'COMPARATIVO ANUAL'!F16 -> 482.29339 | J42: =+'COMPARATIVO ANUAL'!F17 -> 518.40928 | K42: =+'COMPARATIVO ANUAL'!F18 -> 617.7272 | L42: =+'COMPARATIVO ANUAL'!F19 -> 642.76507 | M42: =+'COMPARATIVO ANUAL'!F20 -> 670.58014 | N42: =+'COMPARATIVO ANUAL'!F21 -> 684.09182 | O42: =AVERAGE(C42:N42) -> 531.98457
A43: Precio x TN Z24 | B43: (USD) SIN IVA | C43: =+C42/C61*1000 -> 396.24947 | D43: =+D42/D61*1000 -> 422.2103 | E43: =+E42/E61*1000 -> 391.14054 | F43: =+F42/F61*1000 -> 333.45488 | G43: =+G42/G61*1000 -> 301.22623 | H43: =+H42/H61*1000 -> 316.92869 | I43: =+I42/I61*1000 -> 337.97715 | J43: =+J42/J61*1000 -> 358.05759 | ... O43: =+O42/O61*1000 -> 392.39169
A44: VARIACIÓN PRECIO FOB CONTADO TUC X BOLSA
B45: % ($) | C45: =+C12/C47-1 -> #DIV/0! | D45: =+D12/D47-1 -> #DIV/0! | E45: =+E12/E47-1 -> #VALUE! | F45: =+F12/F47-1 -> #VALUE! | G45: =+G12/G47-1 -> #VALUE! | H45: =+H12/H47-1 -> #VALUE! | I45: =+I12/I47-1 -> #VALUE! | J45: =+J12/J47-1 -> #VALUE! | ... N45: =+N12/N47-1 -> #VALUE! | O45: =AVERAGE(C45:N45) -> #DIV/0!
B46: % (USD) | C46: =+(C12/C54)/(C47/C61)-1 -> #DIV/0! | D46: =+(D12/D54)/(D47/D61)-1 -> #DIV/0! | E46: =+(E12/E54)/(E47/E61)-1 -> #VALUE! | F46: =+(F12/F54)/(F47/F61)-1 -> #VALUE! | G46: =+(G12/G54)/(G47/G61)-1 -> #VALUE! | H46: =+(H12/H54)/(H47/H61)-1 -> #VALUE! | I46: =+(I12/I54)/(I47/I61)-1 -> #VALUE! | J46: =+(J12/J54)/(J47/J61)-1 -> #VALUE! | ... O46: =+(O12/O54)/(O47/O61)-1 -> #VALUE!
A47: Precio FOB CONTADO Z24 | B47: Bolsa 50 KG | C47: =+'COMPARATIVO ANUAL'!L10 -> 0 | D47: =+'COMPARATIVO ANUAL'!L11 -> 0 | E47: =+'COMPARATIVO ANUAL'!L12 -> 0 | F47: =+'COMPARATIVO ANUAL'!L13 -> 0 | G47: =+'COMPARATIVO ANUAL'!L14 -> 0 | H47: =+'COMPARATIVO ANUAL'!L15 -> 0 | I47: =+'COMPARATIVO ANUAL'!L16 -> 0 | J47: =+'COMPARATIVO ANUAL'!I17 -> 0 | K47: =+'COMPARATIVO ANUAL'!L18 -> 0 | L47: =+'COMPARATIVO ANUAL'!L19 -> 0 | M47: =+'COMPARATIVO ANUAL'!L20 -> 0 | N47: =+'COMPARATIVO ANUAL'!L21 -> 0 | O47: =AVERAGE(C47:N47) -> 0
A53: REFERENCIAS | C53: 46143 | D53: =+C53+31 -> 46174 | E53: =+D53+31 -> 46205 | F53: =+E53+31 -> 46236 | G53: =+F53+31 -> 46267 | H53: =+G53+31 -> 46298 | I53: =+H53+31 -> 46329 | J53: =+I53+31 -> 46360 | K53: =+J53+31 -> 46391 | ... N53: =+M53+31 -> 46484 | O53: Promedio
A54: TIPO DE CAMBIO USD | B54: BNA of compra | C54: 1412 | D54: 1518.9069 | E54: 1546.2472 | F54: 1574.0797 | G54: 1602.4131 | H54: 1631.2565 | I54: 1660.6192 | J54: 1685.5284 | K54: 1790 | L54: 1799 | M54: 1810 | N54: 1835 | O54: =AVERAGE(C54:N54) -> 1655.4209
A55: TASA FINANC ANUAL | B55: % | C55: 0.35 | D55: 0.35 | E55: 0.35 | F55: 0.35 | G55: 0.35 | H55: 0.35 | I55: 0.35 | J55: 0.35 | K55: 0.35 | L55: 0.35 | M55: 0.35 | N55: 0.35
A56: COSTO FIN X BOLSA PLAZO 30 | B56: 30 | C56: =+($B$56/365)*C55 -> 0.028767123 | D56: =+($B$56/365)*D55 -> 0.028767123 | E56: =+($B$56/365)*E55 -> 0.028767123 | F56: =+($B$56/365)*F55 -> 0.028767123 | G56: =+($B$56/365)*G55 -> 0.028767123 | H56: =+($B$56/365)*H55 -> 0.028767123 | I56: =+($B$56/365)*I55 -> 0.028767123 | J56: =+($B$56/365)*J55 -> 0.028767123 | ... N56: =+($B$56/365)*N55 -> 0.028767123
A57: FLETE EQ BOLSA A BUE | B57: SIN IVA | C57: =--60000/20 -> 3000 | D57: =--60000/20 -> 3000 | E57: =--60000/20 -> 3000 | F57: =--60000/20 -> 3000 | G57: =--60000/20 -> 3000 | H57: =--60000/20 -> 3000 | I57: =--60000/20 -> 3000 | J57: =--60000/20 -> 3000 | ... N57: =--60000/20 -> 3000
C60: 45778 | D60: =+C60+31 -> 45809 | E60: =+D60+31 -> 45840 | F60: =+E60+31 -> 45871 | G60: =+F60+31 -> 45902 | H60: =+G60+31 -> 45933 | I60: =+H60+31 -> 45964 | J60: =+I60+31 -> 45995 | K60: =+J60+31 -> 46026 | ... N60: =+M60+31 -> 46119
A61: TIPO DE CAMBIO USD | C61: 1147.5292 | D61: 1181.3553 | E61: 1267.0227 | F61: 1329.5375 | G61: 1399.8977 | H61: 1432.0227 | I61: 1427 | J61: 1447.8377 | K61: 1449.3347 | L61: 1409.6571 | M61: 1396.3387 | N61: 1381.4523 | O61: =AVERAGE(C61:N61) -> 1355.7488
A62: Apreciacion TC variacion mensual | C62: =+C54/C61-1 -> 0.23046978 | D62: =+D54/D61-1 -> 0.2857325 | E62: =+E54/E61-1 -> 0.22037847 | F62: =+F54/F61-1 -> 0.18393026 | G62: =+G54/G61-1 -> 0.14466443 | H62: =+H54/H61-1 -> 0.13912757 | I62: =+I54/I61-1 -> 0.1637135 | J62: =+J54/J61-1 -> 0.16416947 | ... N62: =+N54/N61-1 -> 0.32831224
A63: incidencia IVA según mix de venta | C63: 0.136 | D63: 0.17014 | E63: 0.097 | F63: 0.1629 | G63: 0.175 | H63: 0.197 | I63: 0.19 | J63: 0.1504 | K63: 0.1429 | L63: 0.168 | M63: 0.051 | N63: 0 | O63: 0.171
A64: incidencia FLETE según mix de venta | C64: -1759 | D64: -1405 | E64: -1100 | F64: -1469 | G64: -1238 | H64: -1335 | I64: -1780 | J64: -1750 | K64: -3116 | L64: -2760 | M64: -3110 | N64: -5850

Sheet RESUMEN AVANCE MES
B1: RESUMEN AVANCE ZAFRA 2026 POR MES
B3: MAYO
B4: BOLSAS | C4: =+ACUMULADOS!Z2 -> 70186.92 | D4: 50000 | E4: OBJETIVO MES
B5: PESOS $ | C5: =+ACUMULADOS!M2 -> 2.3386576e+09
B6: PRECIO FOB CDO | C6: =+ACUMULADOS!AE3 -> 32106.914 | D6: =+ACUMULADOS!AJ3 -> 34174.432 | E6: CACTU COMPARABLE
B7: GAP VS. CACTU | C7: =+ACUMULADOS!AL3 -> -0.060498957
B8: GAP VS LEDESMA BUE30DFF | C8: =+(((C6/1.21/50)+(2700/50/1.21)+(C6*0.048/50/1.21))/D9)-1 -> -0.29318335
B9: PRECIO PROMEDIO KG (SIN IVA) | C9: =+ACUMULADOS!J3 -> 579.27325 | D9: =+'COMPARATIVO PCIOS REFERENCIA'!F8 -> 850 | E9: LEDESMA COMPARABLE
B10: PRECIO PROMEDIO TN USD (SIN IVA) | C10: =+C9/C12*1000 -> 410.25018
B11: VARIACION PRECIO KG ZAFRA 26 VS 25 | C11: =+C9/D11-1 -> 0.27394603 | D11: =+'COMPARATIVO ANUAL'!F10 -> 454.70784 | E11: PRECIO MAY 25
B12: TIPO DE CAMBIO PROMEDIO | C12: =+KPI´S!C54 -> 1412
B14: JUNIO
B15: BOLSAS | C15: =+ACUMULADOS!Z4 -> 104239.6 | D15: 60000 | E15: OBJETIVO MES
B16: PESOS $ | C16: =+ACUMULADOS!M4 -> 3.0222142e+09
B17: PRECIO FOB CDO | C17: =+ACUMULADOS!AE5 -> 29204.472 | D17: =+ACUMULADOS!AJ5 -> 33811.815 | E17: CACTU COMPARABLE
B18: GAP VS. CACTU | C18: =+ACUMULADOS!AL5 -> -0.1362643
B19: GAP VS LEDESMA BUE30DFF | C19: =+(((C17/1.21/50)+(2700/50/1.21)+(C17*0.048/50/1.21))/D20)-1 -> -0.3883143
B20: PRECIO PROMEDIO KG (SIN IVA) | C20: =+ACUMULADOS!J5 -> 483.75911 | D20: =+'COMPARATIVO PCIOS REFERENCIA'!F9 -> 900 | E20: LEDESMA COMPARABLE
B21: PRECIO PROMEDIO TN USD (SIN IVA) | C21: =+C20/C23*1000 -> 318.49161
B22: VARIACION PRECIO KG ZAFRA 26 VS 25 | C22: =+C20/D22-1 -> -0.030116002 | D22: =+'COMPARATIVO ANUAL'!F11 -> 498.78038 | E22: PRECIO JUN 25
B23: TIPO DE CAMBIO PROMEDIO | C23: =+KPI´S!D54 -> 1518.9069
B25: JULIO
B26: BOLSAS | C26: =+ACUMULADOS!Z7 -> 70284 | D26: 60000 | E26: OBJETIVO MES
B27: PESOS $ | C27: =+ACUMULADOS!M7 -> 2.0107204e+09
B28: PRECIO FOB CDO | C28: =+ACUMULADOS!AE8 -> #VALUE! | D28: =+ACUMULADOS!AJ8 -> 33759.479 | E28: CACTU COMPARABLE
B29: GAP VS. CACTU | C29: =+ACUMULADOS!AO8 -> #VALUE!
B30: GAP VS LEDESMA BUE30DFF | C30: =+(((C28/1.21/50)+(+(2525*1.21)/50/1.21)+(C28*0.048/50/1.21))/D31)-1 -> #VALUE!
B31: PRECIO PROMEDIO KG (SIN IVA) | C31: =+ACUMULADOS!J8 -> 472.89726 | D31: =+'COMPARATIVO PCIOS REFERENCIA'!F10 -> 900 | E31: LEDESMA COMPARABLE
B32: PRECIO PROMEDIO TN USD (SIN IVA) | C32: =+C31/C34*1000 -> 305.83548
B33: VARIACION PRECIO KG ZAFRA 26 VS 25 | C33: =+C31/D33-1 -> -0.045777672 | D33: =+'COMPARATIVO ANUAL'!F12 -> 495.58394 | E33: PRECIO JUL 25
B34: TIPO DE CAMBIO PROMEDIO | C34: =+KPI´S!E54 -> 1546.2472
B36: AGOSTO
B37: BOLSAS | C37: =+ACUMULADOS!Z10 -> 0 | D37: 50000 | E37: OBJETIVO MES
B38: PESOS $ | C38: =+ACUMULADOS!M10 -> 0
B39: PRECIO FOB CDO | C39: =+ACUMULADOS!AE8 -> #VALUE! | D39: =+ACUMULADOS!AJ11 -> #DIV/0! | E39: CACTU COMPARABLE
B40: GAP VS. CACTU | C40: =+ACUMULADOS!AL11 -> #DIV/0!
B41: GAP VS LEDESMA BUE30DFF | C41: =+(((C39/1.21/50)+((2525*1.21)/50/1.21)+(C39*0.048/50/1.21))/D42)-1 -> #VALUE!
B42: PRECIO PROMEDIO KG (SIN IVA) | C42: =+ACUMULADOS!J11 -> #DIV/0! | D42: =+'COMPARATIVO PCIOS REFERENCIA'!F11 -> 0 | E42: LEDESMA COMPARABLE
B43: PRECIO PROMEDIO TN USD (SIN IVA) | C43: =+C42/C45*1000 -> #DIV/0!
B44: VARIACION PRECIO KG ZAFRA 26 VS 25 | C44: =+C42/D44-1 -> #DIV/0! | D44: =+'COMPARATIVO ANUAL'!F13 -> 443.34077 | E44: PRECIO AGO 25
B45: TIPO DE CAMBIO PROMEDIO | C45: =+KPI´S!F54 -> 1574.0797
B47: SEPTIEMBRE
B48: BOLSAS | C48: =+ACUMULADOS!Z13 -> 0 | D48: 50000 | E48: OBJETIVO MES
B49: PESOS $ | C49: =+ACUMULADOS!M13 -> 0
B50: PRECIO FOB CDO | C50: =+ACUMULADOS!AE14 -> #VALUE! | D50: =+ACUMULADOS!AJ14 -> #DIV/0! | E50: CACTU COMPARABLE
B51: GAP VS. CACTU | C51: =+ACUMULADOS!AL14 -> #DIV/0!
B52: GAP VS LEDESMA BUE30DFF | C52: =+(((C50/1.21/50)+((2525*1.21)/50/1.21)+(C50*0.048/50/1.21))/D53)-1 -> #VALUE!
B53: PRECIO PROMEDIO KG (SIN IVA) | C53: =+ACUMULADOS!J14 -> #DIV/0! | D53: =+'COMPARATIVO PCIOS REFERENCIA'!F12 -> 0 | E53: LEDESMA COMPARABLE
B54: PRECIO PROMEDIO TN USD (SIN IVA) | C54: =+C53/C56*1000 -> #DIV/0!
B55: VARIACION PRECIO KG ZAFRA 26 VS 25 | C55: =+C53/D55-1 -> #DIV/0! | D55: =+'COMPARATIVO ANUAL'!F14 -> 421.68591 | E55: PRECIO SEP 25
B56: TIPO DE CAMBIO PROMEDIO | C56: =+KPI´S!G54 -> 1602.4131
B58: OCTUBRE
B59: BOLSAS | C59: =+ACUMULADOS!Z16 -> 0 | D59: 50000 | E59: OBJETIVO MES
B60: PESOS $ | C60: =+ACUMULADOS!M16 -> 0
B61: PRECIO FOB CDO | C61: =+ACUMULADOS!AE17 -> #VALUE! | D61: =+ACUMULADOS!AJ17 -> #DIV/0! | E61: CACTU COMPARABLE
B62: GAP VS. CACTU | C62: =+ACUMULADOS!AL17 -> #DIV/0!
B63: GAP VS LEDESMA BUE30DFF | C63: =+(((C61/1.21/50)+((2525*1.21)/50/1.21)+(C61*0.048/50/1.21))/D64)-1 -> #VALUE!
B64: PRECIO PROMEDIO KG (SIN IVA) | C64: =+ACUMULADOS!J17 -> #DIV/0! | D64: =+'COMPARATIVO PCIOS REFERENCIA'!F13 -> 0 | E64: LEDESMA COMPARABLE
B65: PRECIO PROMEDIO TN USD (SIN IVA) | C65: =+C64/C67*1000 -> #DIV/0!
B66: VARIACION PRECIO KG ZAFRA 26 VS 25 | C66: =+C64/D66-1 -> #DIV/0! | D66: =+'COMPARATIVO ANUAL'!F15 -> 453.84908 | E66: PRECIO OCT 25
B67: TIPO DE CAMBIO PROMEDIO | C67: =+KPI´S!H54 -> 1631.2565
B69: NOVIEMBRE
B70: BOLSAS | C70: =+ACUMULADOS!Z19 -> 0 | D70: 20000 | E70: OBJETIVO MES
B71: PESOS $ | C71: =+ACUMULADOS!M19 -> 0
B72: PRECIO FOB CDO | C72: =+ACUMULADOS!AE20 -> #VALUE! | D72: =+ACUMULADOS!AJ20 -> #DIV/0! | E72: CACTU COMPARABLE
B73: GAP VS. CACTU | C73: =+ACUMULADOS!AL20 -> #DIV/0!
B74: GAP VS LEDESMA BUE30DFF | C74: =+(((C72/1.21/50)+((2525*1.21)/50/1.21)+(C72*0.048/50/1.21))/D75)-1 -> #VALUE!
B75: PRECIO PROMEDIO KG (SIN IVA) | C75: =+ACUMULADOS!J20 -> #DIV/0! | D75: =+'COMPARATIVO PCIOS REFERENCIA'!F14 -> 0 | E75: LEDESMA COMPARABLE
B76: PRECIO PROMEDIO TN USD (SIN IVA) | C76: =+C75/C78*1000 -> #DIV/0!
B77: VARIACION PRECIO KG ZAFRA 26 VS 25 | C77: =+C75/D77-1 -> #DIV/0! | D77: =+'COMPARATIVO ANUAL'!F16 -> 482.29339 | E77: PRECIO NOV 25
B78: TIPO DE CAMBIO PROMEDIO | C78: =+KPI´S!I54 -> 1660.6192
B80: DICIEMBRE
B81: BOLSAS | C81: =+ACUMULADOS!Z22 -> 0 | D81: 20000 | E81: OBJETIVO MES
B82: PESOS $ | C82: =+ACUMULADOS!M22 -> 0
B83: PRECIO FOB CDO | C83: =+ACUMULADOS!AE23 -> #VALUE! | D83: =+ACUMULADOS!AJ23 -> #DIV/0! | E83: CACTU COMPARABLE
B84: GAP VS. CACTU | C84: =+ACUMULADOS!AL23 -> #DIV/0!
B85: GAP VS LEDESMA BUE30DFF | C85: =+(((C83/1.21/50)+((2525*1.21)/50/1.21)+(C83*0.048/50/1.21))/D86)-1 -> #VALUE!
B86: PRECIO PROMEDIO KG (SIN IVA) | C86: =+ACUMULADOS!J23 -> #DIV/0! | D86: =+'COMPARATIVO PCIOS REFERENCIA'!F15 -> 0 | E86: LEDESMA COMPARABLE
B87: PRECIO PROMEDIO TN USD (SIN IVA) | C87: =+C86/C89*1000 -> #DIV/0!
B88: VARIACION PRECIO KG ZAFRA 26 VS 25 | C88: =+C86/D88-1 -> #DIV/0! | D88: =+'COMPARATIVO ANUAL'!F17 -> 518.40928 | E88: PRECIO DIC 25
B89: TIPO DE CAMBIO PROMEDIO | C89: =+KPI´S!J54 -> 1685.5284
B91: ENERO
B92: BOLSAS | C92: =+ACUMULADOS!Z25 -> 0 | D92: 20000 | E92: OBJETIVO MES
B93: PESOS $ | C93: =+ACUMULADOS!M25 -> 0
B94: PRECIO FOB CDO | C94: =+ACUMULADOS!AE26 -> #VALUE! | D94: =+ACUMULADOS!AJ26 -> #DIV/0! | E94: CACTU COMPARABLE
B95: GAP VS. CACTU | C95: =+ACUMULADOS!AL26 -> #DIV/0!
B96: GAP VS LEDESMA BUE30DFF | C96: =+(((C94/1.21/50)+((2650*1.21)/50/1.21)+(C94*0.048/50/1.21))/D97)-1 -> #VALUE!
B97: PRECIO PROMEDIO KG (SIN IVA) | C97: =+ACUMULADOS!J26 -> #DIV/0! | D97: =+'COMPARATIVO PCIOS REFERENCIA'!F16 -> 0 | E97: LEDESMA COMPARABLE
B98: PRECIO PROMEDIO TN USD (SIN IVA) | C98: =+C97/C100*1000 -> #DIV/0!
B99: VARIACION PRECIO KG ZAFRA 26 VS 25 | C99: =+C97/D99-1 -> #DIV/0! | D99: =+'COMPARATIVO ANUAL'!F18 -> 617.7272 | E99: PRECIO ENE 26
B100: TIPO DE CAMBIO PROMEDIO | C100: =+KPI´S!K54 -> 1790
B102: FEBRERO
B103: BOLSAS | C103: =+ACUMULADOS!Z28 -> 0 | D103: 20000 | E103: OBJETIVO MES
B104: PESOS $ | C104: =+ACUMULADOS!M28 -> 0
B105: PRECIO FOB CDO | C105: =+ACUMULADOS!AE29 -> #VALUE! | D105: =+ACUMULADOS!AJ29 -> #DIV/0! | E105: CACTU COMPARABLE
B106: GAP VS. CACTU | C106: =+ACUMULADOS!AL29 -> #DIV/0!
B107: GAP VS LEDESMA BUE30DFF | C107: =+(((C105/1.21/50)+((2650*1.21)/50/1.21)+(C105*0.048/50/1.21))/D108)-1 -> #VALUE!
B108: PRECIO PROMEDIO KG (SIN IVA) | C108: =+ACUMULADOS!J29 -> #DIV/0! | D108: =+'COMPARATIVO PCIOS REFERENCIA'!F17 -> 0 | E108: LEDESMA COMPARABLE
B109: PRECIO PROMEDIO TN USD (SIN IVA) | C109: =+C108/C111*1000 -> #DIV/0!
B110: VARIACION PRECIO KG ZAFRA 26 VS 25 | C110: =+C108/D110-1 -> #DIV/0! | D110: =+'COMPARATIVO ANUAL'!F19 -> 642.76507 | E110: PRECIO FEB 26
...

Sheet CONSOLIDADO VTAS
U2: =TODAY() -> 46181
A3: MES | B3: CANTIDAD EQUIPOS | C3: CLIENTE | D3: FECHA FC | E3: FC SUCRO | F3: PRODUCTO | G3: ESTADO ENTREGA | H3: FECHA Entrega | I3: KGS | J3: PRECIO $/ KG A PLAZO EN CLIENTE ( SIN IVA) | K3: SUBTOTAL | L3: IVA | M3: VENTA TOTAL $ (IVA INC) | N3: PENDIENTE DE ENTREGA | O3: PENDIENTE DE COBRO | P3: VALORES EN CARTERA | Q3: VALORES COBRADOS | R3: FECHA RETIRO VALORES | S3: FECHA VTO VALORES | T3: Dias Vto | U3: PLAZO ENTREGA VALORES | V3: Banco | W3: SEMANA ACREDITACION PAGO | X3: OC | Y3: FECHA OC | Z3: Q Bolsas Equivalentes 50kg | AA3: PRECIO $ BOLSA 50 KG (IVA INC) | AB3: COSTO FLETE $ BOLSA 50 KG (IVA INC) | AC3: PRECIO $ BOLSA50 KG FOB TUCUMAN A PLAZO (IVA INC) | AD3: GASTOS FINANCIEROS $ BOLSA 50 KG (IVA INC) | AE3: PRECIO $ BOLSA 50KG FOB CDO TUC (IVA INC) | AF3: ENVASE | AG3: LOCALIDAD | AH3: PAIS / PROVINCIA | AI3: TIPO OPERACIÓN | AJ3: PRECIO REF $ BOLSA 50 KG CACTU (IVA INC) | AK3: DIF $ PRECIO NETO INDUSTRIA vs Neto TUCUMAN (IVA INC) | AL3: DIF % PRECIO NETO INDUSTRIA vs Neto TUCUMAN (IVA INC) | AM3: TOTAL GANANCIA $ POR OPERACIÓN VS. CACTU (IVA INC) | AN3: VENTA EQUIVALENTE $ CACTU (IVA INC) | AO3: VENTA EQU $ LA CORONA FOB TUC (IVA INC) | AP3: TASA FINANCIACION MENSUAL | AQ3: COSTO FLETE $ POR BOLSA 5O KG (SIN IVA) | AR3: PLAZO PAGO (DIAS) | AS3: REMITO | AT3: CONTROL | AU3: TIPO DE CAMBIO | AV3: VENTA TOTAL USD A PLAZO EN CLIENTE (SIN IVA) | AW3: % IVA | AX3: VENTA TOTAL USD A PLAZO EN CLIENTE (IVA INC) | AY3: PRECIO POR TN USD EN CLIENTE A PLAZO (SIN IVA) | AZ3: COSTO USD FLETE /TN (SIN IVA) | BA3: COSTO FINANCIERO USD POR BOLSA 50KG (IVA INC) | BB3: PRECIO USD TON FOB CORONA | BC3: TIER | BD3: COMENTARIOS2
A4: 46143 | B4: 1 | C4: LEDESMA SAAI | D4: =+Tabla1[[#This Row],[FECHA Entrega]] -> 46168.793 | E4: 700000869 | F4: AZÚCAR CRUDO | G4: ENTREGADO | H4: 46168.793 | I4: =564*50 -> 28200 | J4: =0.315*Tabla1[[#This Row],[TIPO DE CAMBIO]] -> 455.58481 | K4: =+J4*I4 -> 12847492 | L4: =IF(Tabla1[[#This Row],[TIPO OPERACIÓN]]="INDUSTRIA",Tabla1[[#This Row],[SUBTOTAL]]*0.21,IF(Tabla1[[#This Row],[TIPO OPERACIÓN]]="GDES CUENTAS",Tabla1[[#This Row],[SUBTOTAL]]*0.21,IF(Tabla1[[#This Row],[TIPO OPERACIÓN]]="TUC CTADO 2","",IF(Tabla1[[#This Row],[TIPO OPERACIÓN]]="EXPO CHILE","",IF(Tabla1[[#This Row],[TIPO OPERACIÓN]]="TUC CTADO 1",Tabla1[[#This Row],[SUBTOTAL]]*0.21,""))))) -> 2697973.3 | M4: =SUM(K4:L4) -> 15545465 | O4: 0 | P4: 0 | Q4: =+Tabla1[[#This Row],[VENTA TOTAL $ (IVA INC) ]]-Tabla1[[#This Row],[PENDIENTE DE COBRO]] -> 15545465 | R4: =+Tabla1[[#This Row],[FECHA FC]]+Tabla1[[#This Row],[PLAZO ENTREGA VALORES]] -> 46051 | S4: =+Tabla1[[#This Row],[FECHA FC]]+Tabla1[[#This Row],[PLAZO PAGO (DIAS)]] -> 46168.793 | T4: =+S4-$U$2 -> -12.206944 | U4: =+Tabla1[[#This Row],[FECHA OC]]-Tabla1[[#This Row],[FECHA Entrega]] -> -117.79306 | W4: =+Tabla1[[#This Row],[FECHA VTO VALORES]]+7 -> 46175.793 | Y4: 46051 | Z4: =Tabla1[[#This Row],[KGS]]/50 -> 564 | AA4: =IFERROR((IF(Tabla1[[#This Row],[TIPO OPERACIÓN]]="INDUSTRIA",Tabla1[[#This Row],[PRECIO $/ KG A PLAZO EN CLIENTE ( SIN IVA)]]*50*1.21,IF(Tabla1[[#This Row],[TIPO OPERACIÓN]]="TUC CTADO 2",Tabla1[[#This Row],[PRECIO $/ KG A PLAZO EN CLIENTE ( SIN IVA)]]*50,IF(Tabla1[[#This Row],[TIPO OPERACIÓN]]="EXPO CHILE",Tabla1[[#This Row],[PRECIO $/ KG A PLAZO EN CLIENTE ( SIN IVA)]]*50*1,IF(Tabla1[[#This Row],[TIPO OPERACIÓN]]="GDES CUENTAS",Tabla1[[#This Row],[PRECIO $/ KG A PLAZO EN CLIENTE ( SIN IVA)]]*50*1.21,IF(Tabla1[[#This Row],[TIPO OPERACIÓN]]="TUC CTADO 1",Tabla1[[#This Row],[PRECIO $/ KG A PLAZO EN CLIENTE ( SIN IVA)]]*50*1.21,"")))))),"") -> 27562.881 | AB4: =-Tabla1[[#This Row],[COSTO FLETE $ POR BOLSA 5O KG (SIN IVA)]]*1.21-Tabla1[[#This Row],[PRECIO $/ KG A PLAZO EN CLIENTE ( SIN IVA)]]*0.003*1.21*50 -> -0.40864392 | AC4: =SUM(Tabla1[[#This Row],[PRECIO $ BOLSA 50 KG (IVA INC) ]]+Tabla1[[#This Row],[COSTO FLETE $ BOLSA 50 KG (IVA INC)]]) -> 27562.473 | AD4: =-Tabla1[[#This Row],[PRECIO $ BOLSA 50 KG (IVA INC) ]]*(Tabla1[[#This Row],[TASA FINANCIACION MENSUAL]]/365)*Tabla1[[#This Row],[PLAZO ENTREGA VALORES]] -> 257.95826 | AE4: =SUM(Tabla1[[#This Row],[PRECIO $ BOLSA50 KG FOB TUCUMAN A PLAZO (IVA INC)]]+Tabla1[[#This Row],[GASTOS FINANCIEROS $ BOLSA 50 KG (IVA INC)]]) -> 27820.431 | AF4: GRANEL | AG4: RETIRA DE INGENIO | AH4: TUCUMAN | AI4: GDES CUENTAS | AJ4: =IFERROR(IF(Tabla1[[#This Row],[TIPO OPERACIÓN]]="INDUSTRIA",VLOOKUP(Tabla1[[#This Row],[FECHA OC]],'PRECIO CACTU'!A:B,2,FALSE),IF(Tabla1[[#This Row],[TIPO OPERACIÓN]]="GDES CUENTAS",VLOOKUP(Tabla1[[#This Row],[FECHA OC]],'PRECIO CACTU'!A:B,2,FALSE),IF(Tabla1[[#This Row],[TIPO OPERACIÓN]]="EXPO CHILE",VLOOKUP(Tabla1[[#This Row],[FECHA OC]],'PRECIO CACTU'!A:B,2,FALSE)/1.21,IF(Tabla1[[#This Row],[TIPO OPERACIÓN]]="TUC CTADO 2",VLOOKUP(Tabla1[[#This Row],[FECHA OC]],'PRECIO CACTU'!A:B,2,FALSE)/1.21,IF(Tabla1[[#This Row],[TIPO OPERACIÓN]]="TUC CTADO 1",VLOOKUP(Tabla1[[#This Row],[FECHA OC]],'PRECIO CACTU'!A:B,2,FALSE),""))))),"") -> 32515 | AK4: =SUM(Tabla1[[#This Row],[PRECIO $ BOLSA 50KG FOB CDO TUC (IVA INC)]]-Tabla1[[#This Row],[PRECIO REF $ BOLSA 50 KG CACTU (IVA INC)]]) -> -4694.5691 | AL4: =IFERROR(Tabla1[[#This Row],[PRECIO $ BOLSA 50KG FOB CDO TUC (IVA INC)]]/Tabla1[[#This Row],[PRECIO REF $ BOLSA 50 KG CACTU (IVA INC)]]-1,"") -> -0.14438164 | AM4: =+Tabla1[[#This Row],[DIF $ PRECIO NETO INDUSTRIA vs Neto TUCUMAN (IVA INC)]]*Tabla1[[#This Row],[Q Bolsas Equivalentes 50kg]] -> -2647737 | AN4: =Tabla1[[#This Row],[PRECIO REF $ BOLSA 50 KG CACTU (IVA INC)]]*Tabla1[[#This Row],[Q Bolsas Equivalentes 50kg]] -> 18338460 | AO4: =+Tabla1[[#This Row],[PRECIO $ BOLSA 50KG FOB CDO TUC (IVA INC)]]*Tabla1[[#This Row],[Q Bolsas Equivalentes 50kg]] -> 15690723 | AP4: 0.029 | AQ4: -68 | AT4: =+Tabla1[[#This Row],[VENTA TOTAL $ (IVA INC) ]]-(SUM(Tabla1[[#This Row],[PENDIENTE DE ENTREGA]:[VALORES COBRADOS]])) -> 0 | AU4: =VLOOKUP(Tabla1[[#This Row],[FECHA OC]],'TIPO DE CAMBIO'!A:B,2,TRUE) -> 1446.301 | AV4: =+Tabla1[[#This Row],[SUBTOTAL]]/Tabla1[[#This Row],[TIPO DE CAMBIO]] -> 8883 | AX4: =IFERROR(Tabla1[[#This Row],[VENTA TOTAL USD A PLAZO EN CLIENTE (SIN IVA)]]*(1+Tabla1[[#This Row],[% IVA ]]),"") -> 8883 | AY4: =+Tabla1[[#This Row],[VENTA TOTAL USD A PLAZO EN CLIENTE (SIN IVA)]]/Tabla1[[#This Row],[KGS]]*1000 -> 315 | AZ4: 0 | BA4: =+Tabla1[[#This Row],[GASTOS FINANCIEROS $ BOLSA 50 KG (IVA INC)]]*20/Tabla1[[#This Row],[TIPO DE CAMBIO]] -> 3.5671449 | BB4: =+Tabla1[[#This Row],[PRECIO POR TN USD EN CLIENTE A PLAZO (SIN IVA)]]+Tabla1[[#This Row],[COSTO USD FLETE /TN (SIN IVA)]]+Tabla1[[#This Row],[COSTO FINANCIERO USD POR BOLSA 50KG (IVA INC)]] -> 318.56714 | BC4: 5
A5: 46143 | B5: 1 | C5: LEDESMA SAAI | D5: =+Tabla1[[#This Row],[FECHA Entrega]] -> 46168.938 | E5: 700000869 | F5: AZÚCAR CRUDO | G5: ENTREGADO | H5: 46168.938 | I5: =600*50 -> 30000 | J5: =0.315*Tabla1[[#This Row],[TIPO DE CAMBIO]] -> 455.58481 | K5: =+J5*I5 -> 13667544 | L5: =IF(Tabla1[[#This Row],[TIPO OPERACIÓN]]="INDUSTRIA",Tabla1[[#This Row],[SUBTOTAL]]*0.21,IF(Tabla1[[#This Row],[TIPO OPERACIÓN]]="GDES CUENTAS",Tabla1[[#This Row],[SUBTOTAL]]*0.21,IF(Tabla1[[#This Row],[TIPO OPERACIÓN]]="TUC CTADO 2","",IF(Tabla1[[#This Row],[TIPO OPERACIÓN]]="EXPO CHILE","",IF(Tabla1[[#This Row],[TIPO OPERACIÓN]]="TUC CTADO 1",Tabla1[[#This Row],[SUBTOTAL]]*0.21,""))))) -> 2870184.3 | M5: =SUM(K5:L5) -> 16537729 | O5: 0 | P5: 0 | Q5: =+Tabla1[[#This Row],[VENTA TOTAL $ (IVA INC) ]]-Tabla1[[#This Row],[PENDIENTE DE COBRO]] -> 16537729 | R5: =+Tabla1[[#This Row],[FECHA FC]]+Tabla1[[#This Row],[PLAZO ENTREGA VALORES]] -> 46051 | S5: =+Tabla1[[#This Row],[FECHA FC]]+Tabla1[[#This Row],[PLAZO PAGO (DIAS)]] -> 46168.938 | T5: =+S5-$U$2 -> -12.061806 | U5: =+Tabla1[[#This Row],[FECHA OC]]-Tabla1[[#This Row],[FECHA Entrega]] -> -117.93819 | W5: =+Tabla1[[#This Row],[FECHA VTO VALORES]]+7 -> 46175.938 | Y5: 46051 | Z5: =Tabla1[[#This Row],[KGS]]/50 -> 600 | AA5: =IFERROR((IF(Tabla1[[#This Row],[TIPO OPERACIÓN]]="INDUSTRIA",Tabla1[[#This Row],[PRECIO $/ KG A PLAZO EN CLIENTE ( SIN IVA)]]*50*1.21,IF(Tabla1[[#This Row],[TIPO OPERACIÓN]]="TUC CTADO 2",Tabla1[[#This Row],[PRECIO $/ KG A PLAZO EN CLIENTE ( SIN IVA)]]*50,IF(Tabla1[[#This Row],[TIPO OPERACIÓN]]="EXPO CHILE",Tabla1[[#This Row],[PRECIO $/ KG A PLAZO EN CLIENTE ( SIN IVA)]]*50*1,IF(Tabla1[[#This Row],[TIPO OPERACIÓN]]="GDES CUENTAS",Tabla1[[#This Row],[PRECIO $/ KG A PLAZO EN CLIENTE ( SIN IVA)]]*50*1.21,IF(Tabla1[[#This Row],[TIPO OPERACIÓN]]="TUC CTADO 1",Tabla1[[#This Row],[PRECIO $/ KG A PLAZO EN CLIENTE ( SIN IVA)]]*50*1.21,"")))))),"") -> 27562.881 | AB5: =-Tabla1[[#This Row],[COSTO FLETE $ POR BOLSA 5O KG (SIN IVA)]]*1.21-Tabla1[[#This Row],[PRECIO $/ KG A PLAZO EN CLIENTE ( SIN IVA)]]*0.003*1.21*50 -> -0.40864392 | AC5: =SUM(Tabla1[[#This Row],[PRECIO $ BOLSA 50 KG (IVA INC) ]]+Tabla1[[#This Row],[COSTO FLETE $ BOLSA 50 KG (IVA INC)]]) -> 27562.473 | AD5: =-Tabla1[[#This Row],[PRECIO $ BOLSA 50 KG (IVA INC) ]]*(Tabla1[[#This Row],[TASA FINANCIACION MENSUAL]]/365)*Tabla1[[#This Row],[PLAZO ENTREGA VALORES]] -> 258.2761 | AE5: =SUM(Tabla1[[#This Row],[PRECIO $ BOLSA50 KG FOB TUCUMAN A PLAZO (IVA INC)]]+Tabla1[[#This Row],[GASTOS FINANCIEROS $ BOLSA 50 KG (IVA INC)]]) -> 27820.749 | AF5: GRANEL | AG5: RETIRA DE INGENIO | AH5: TUCUMAN | AI5: GDES CUENTAS | AJ5: =IFERROR(IF(Tabla1[[#This Row],[TIPO OPERACIÓN]]="INDUSTRIA",VLOOKUP(Tabla1[[#This Row],[FECHA OC]],'PRECIO CACTU'!A:B,2,FALSE),IF(Tabla1[[#This Row],[TIPO OPERACIÓN]]="GDES CUENTAS",VLOOKUP(Tabla1[[#This Row],[FECHA OC]],'PRECIO CACTU'!A:B,2,FALSE),IF(Tabla1[[#This Row],[TIPO OPERACIÓN]]="EXPO CHILE",VLOOKUP(Tabla1[[#This Row],[FECHA OC]],'PRECIO CACTU'!A:B,2,FALSE)/1.21,IF(Tabla1[[#This Row],[TIPO OPERACIÓN]]="TUC CTADO 2",VLOOKUP(Tabla1[[#This Row],[FECHA OC]],'PRECIO CACTU'!A:B,2,FALSE)/1.21,IF(Tabla1[[#This Row],[TIPO OPERACIÓN]]="TUC CTADO 1",VLOOKUP(Tabla1[[#This Row],[FECHA OC]],'PRECIO CACTU'!A:B,2,FALSE),""))))),"") -> 32515 | AK5: =SUM(Tabla1[[#This Row],[PRECIO $ BOLSA 50KG FOB CDO TUC (IVA INC)]]-Tabla1[[#This Row],[PRECIO REF $ BOLSA 50 KG CACTU (IVA INC)]]) -> -4694.2512 | AL5: =IFERROR(Tabla1[[#This Row],[PRECIO $ BOLSA 50KG FOB CDO TUC (IVA INC)]]/Tabla1[[#This Row],[PRECIO REF $ BOLSA 50 KG CACTU (IVA INC)]]-1,"") -> -0.14437187 | AM5: =+Tabla1[[#This Row],[DIF $ PRECIO NETO INDUSTRIA vs Neto TUCUMAN (IVA INC)]]*Tabla1[[#This Row],[Q Bolsas Equivalentes 50kg]] -> -2816550.7 | AN5: =Tabla1[[#This Row],[PRECIO REF $ BOLSA 50 KG CACTU (IVA INC)]]*Tabla1[[#This Row],[Q Bolsas Equivalentes 50kg]] -> 19509000 | AO5: =+Tabla1[[#This Row],[PRECIO $ BOLSA 50KG FOB CDO TUC (IVA INC)]]*Tabla1[[#This Row],[Q Bolsas Equivalentes 50kg]] -> 16692449 | AP5: 0.029 | AQ5: -68 | AT5: =+Tabla1[[#This Row],[VENTA TOTAL $ (IVA INC) ]]-(SUM(Tabla1[[#This Row],[PENDIENTE DE ENTREGA]:[VALORES COBRADOS]])) -> 0 | AU5: =VLOOKUP(Tabla1[[#This Row],[FECHA OC]],'TIPO DE CAMBIO'!A:B,2,TRUE) -> 1446.301 | AV5: =+Tabla1[[#This Row],[SUBTOTAL]]/Tabla1[[#This Row],[TIPO DE CAMBIO]] -> 9450 | AX5: =IFERROR(Tabla1[[#This Row],[VENTA TOTAL USD A PLAZO EN CLIENTE (SIN IVA)]]*(1+Tabla1[[#This Row],[% IVA ]]),"") -> 9450 | AY5: =+Tabla1[[#This Row],[VENTA TOTAL USD A PLAZO EN CLIENTE (SIN IVA)]]/Tabla1[[#This Row],[KGS]]*1000 -> 315 | AZ5: 0 | BA5: =+Tabla1[[#This Row],[GASTOS FINANCIEROS $ BOLSA 50 KG (IVA INC)]]*20/Tabla1[[#This Row],[TIPO DE CAMBIO]] -> 3.5715401 | BB5: =+Tabla1[[#This Row],[PRECIO POR TN USD EN CLIENTE A PLAZO (SIN IVA)]]+Tabla1[[#This Row],[COSTO USD FLETE /TN (SIN IVA)]]+Tabla1[[#This Row],[COSTO FINANCIERO USD POR BOLSA 50KG (IVA INC)]] -> 318.57154 | BC5: 5
A6: 46143 | B6: 1 | C6: LEDESMA SAAI | D6: =+Tabla1[[#This Row],[FECHA Entrega]] -> 46168.951 | E6: 700000869 | F6: AZÚCAR CRUDO | G6: ENTREGADO | H6: 46168.951 | I6: =579*50 -> 28950 | J6: =0.315*Tabla1[[#This Row],[TIPO DE CAMBIO]] -> 455.58481 | K6: =+J6*I6 -> 13189180 | L6: =IF(Tabla1[[#This Row],[TIPO OPERACIÓN]]="INDUSTRIA",Tabla1[[#This Row],[SUBTOTAL]]*0.21,IF(Tabla1[[#This Row],[TIPO OPERACIÓN]]="GDES CUENTAS",Tabla1[[#This Row],[SUBTOTAL]]*0.21,IF(Tabla1[[#This Row],[TIPO OPERACIÓN]]="TUC CTADO 2","",IF(Tabla1[[#This Row],[TIPO OPERACIÓN]]="EXPO CHILE","",IF(Tabla1[[#This Row],[TIPO OPERACIÓN]]="TUC CTADO 1",Tabla1[[#This Row],[SUBTOTAL]]*0.21,""))))) -> 2769727.9 | M6: =SUM(K6:L6) -> 15958908 | O6: 0 | P6: 0 | Q6: =+Tabla1[[#This Row],[VENTA TOTAL $ (IVA INC) ]]-Tabla1[[#This Row],[PENDIENTE DE COBRO]] -> 15958908 | R6: =+Tabla1[[#This Row],[FECHA FC]]+Tabla1[[#This Row],[PLAZO ENTREGA VALORES]] -> 46051 | S6: =+Tabla1[[#This Row],[FECHA FC]]+Tabla1[[#This Row],[PLAZO PAGO (DIAS)]] -> 46168.951 | T6: =+S6-$U$2 -> -12.049306 | U6: =+Tabla1[[#This Row],[FECHA OC]]-Tabla1[[#This Row],[FECHA Entrega]] -> -117.95069 | W6: =+Tabla1[[#This Row],[FECHA VTO VALORES]]+7 -> 46175.951 | Y6: 46051 | Z6: =Tabla1[[#This Row],[KGS]]/50 -> 579 | AA6: =IFERROR((IF(Tabla1[[#This Row],[TIPO OPERACIÓN]]="INDUSTRIA",Tabla1[[#This Row],[PRECIO $/ KG A PLAZO EN CLIENTE ( SIN IVA)]]*50*1.21,IF(Tabla1[[#This Row],[TIPO OPERACIÓN]]="TUC CTADO 2",Tabla1[[#This Row],[PRECIO $/ KG A PLAZO EN CLIENTE ( SIN IVA)]]*50,IF(Tabla1[[#This Row],[TIPO OPERACIÓN]]="EXPO CHILE",Tabla1[[#This Row],[PRECIO $/ KG A PLAZO EN CLIENTE ( SIN IVA)]]*50*1,IF(Tabla1[[#This Row],[TIPO OPERACIÓN]]="GDES CUENTAS",Tabla1[[#This Row],[PRECIO $/ KG A PLAZO EN CLIENTE ( SIN IVA)]]*50*1.21,IF(Tabla1[[#This Row],[TIPO OPERACIÓN]]="TUC CTADO 1",Tabla1[[#This Row],[PRECIO $/ KG A PLAZO EN CLIENTE ( SIN IVA)]]*50*1.21,"")))))),"") -> 27562.881 | AB6: =-Tabla1[[#This Row],[COSTO FLETE $ POR BOLSA 5O KG (SIN IVA)]]*1.21-Tabla1[[#This Row],[PRECIO $/ KG A PLAZO EN CLIENTE ( SIN IVA)]]*0.003*1.21*50 -> -0.40864392 | AC6: =SUM(Tabla1[[#This Row],[PRECIO $ BOLSA 50 KG (IVA INC) ]]+Tabla1[[#This Row],[COSTO FLETE $ BOLSA 50 KG (IVA INC)]]) -> 27562.473 | AD6: =-Tabla1[[#This Row],[PRECIO $ BOLSA 50 KG (IVA INC) ]]*(Tabla1[[#This Row],[TASA FINANCIACION MENSUAL]]/365)*Tabla1[[#This Row],[PLAZO ENTREGA VALORES]] -> 258.30348 | AE6: =SUM(Tabla1[[#This Row],[PRECIO $ BOLSA50 KG FOB TUCUMAN A PLAZO (IVA INC)]]+Tabla1[[#This Row],[GASTOS FINANCIEROS $ BOLSA 50 KG (IVA INC)]]) -> 27820.776 | AF6: GRANEL | AG6: RETIRA DE INGENIO | AH6: TUCUMAN | AI6: GDES CUENTAS | AJ6: =IFERROR(IF(Tabla1[[#This Row],[TIPO OPERACIÓN]]="INDUSTRIA",VLOOKUP(Tabla1[[#This Row],[FECHA OC]],'PRECIO CACTU'!A:B,2,FALSE),IF(Tabla1[[#This Row],[TIPO OPERACIÓN]]="GDES CUENTAS",VLOOKUP(Tabla1[[#This Row],[FECHA OC]],'PRECIO CACTU'!A:B,2,FALSE),IF(Tabla1[[#This Row],[TIPO OPERACIÓN]]="EXPO CHILE",VLOOKUP(Tabla1[[#This Row],[FECHA OC]],'PRECIO CACTU'!A:B,2,FALSE)/1.21,IF(Tabla1[[#This Row],[TIPO OPERACIÓN]]="TUC CTADO 2",VLOOKUP(Tabla1[[#This Row],[FECHA OC]],'PRECIO CACTU'!A:B,2,FALSE)/1.21,IF(Tabla1[[#This Row],[TIPO OPERACIÓN]]="TUC CTADO 1",VLOOKUP(Tabla1[[#This Row],[FECHA OC]],'PRECIO CACTU'!A:B,2,FALSE),""))))),"") -> 32515 | AK6: =SUM(Tabla1[[#This Row],[PRECIO $ BOLSA 50KG FOB CDO TUC (IVA INC)]]-Tabla1[[#This Row],[PRECIO REF $ BOLSA 50 KG CACTU (IVA INC)]]) -> -4694.2239 | AL6: =IFERROR(Tabla1[[#This Row],[PRECIO $ BOLSA 50KG FOB CDO TUC (IVA INC)]]/Tabla1[[#This Row],[PRECIO REF $ BOLSA 50 KG CACTU (IVA INC)]]-1,"") -> -0.14437102 | AM6: =+Tabla1[[#This Row],[DIF $ PRECIO NETO INDUSTRIA vs Neto TUCUMAN (IVA INC)]]*Tabla1[[#This Row],[Q Bolsas Equivalentes 50kg]] -> -2717955.6 | AN6: =Tabla1[[#This Row],[PRECIO REF $ BOLSA 50 KG CACTU (IVA INC)]]*Tabla1[[#This Row],[Q Bolsas Equivalentes 50kg]] -> 18826185 | AO6: =+Tabla1[[#This Row],[PRECIO $ BOLSA 50KG FOB CDO TUC (IVA INC)]]*Tabla1[[#This Row],[Q Bolsas Equivalentes 50kg]] -> 16108229 | AP6: 0.029 | AQ6: -68 | AS6: 0008-00005536 | AT6: =+Tabla1[[#This Row],[VENTA TOTAL $ (IVA INC) ]]-(SUM(Tabla1[[#This Row],[PENDIENTE DE ENTREGA]:[VALORES COBRADOS]])) -> 0 | AU6: =VLOOKUP(Tabla1[[#This Row],[FECHA OC]],'TIPO DE CAMBIO'!A:B,2,TRUE) -> 1446.301 | AV6: =+Tabla1[[#This Row],[SUBTOTAL]]/Tabla1[[#This Row],[TIPO DE CAMBIO]] -> 9119.25 | AX6: =IFERROR(Tabla1[[#This Row],[VENTA TOTAL USD A PLAZO EN CLIENTE (SIN IVA)]]*(1+Tabla1[[#This Row],[% IVA ]]),"") -> 9119.25 | AY6: =+Tabla1[[#This Row],[VENTA TOTAL USD A PLAZO EN CLIENTE (SIN IVA)]]/Tabla1[[#This Row],[KGS]]*1000 -> 315 | AZ6: 0 | BA6: =+Tabla1[[#This Row],[GASTOS FINANCIEROS $ BOLSA 50 KG (IVA INC)]]*20/Tabla1[[#This Row],[TIPO DE CAMBIO]] -> 3.5719187 | BB6: =+Tabla1[[#This Row],[PRECIO POR TN USD EN CLIENTE A PLAZO (SIN IVA)]]+Tabla1[[#This Row],[COSTO USD FLETE /TN (SIN IVA)]]+Tabla1[[#This Row],[COSTO FINANCIERO USD POR BOLSA 50KG (IVA INC)]] -> 318.57192 | BC6: 5
A7: 46143 | B7: 1 | C7: LEDESMA SAAI | D7: =+Tabla1[[#This Row],[FECHA Entrega]] -> 46170.651 | E7: 700000869 | F7: AZÚCAR CRUDO | G7: ENTREGADO | H7: 46170.651 | I7: =588*50 -> 29400 | J7: =0.315*Tabla1[[#This Row],[TIPO DE CAMBIO]] -> 455.58481 | K7: =+J7*I7 -> 13394194 | L7: =IF(Tabla1[[#This Row],[TIPO OPERACIÓN]]="INDUSTRIA",Tabla1[[#This Row],[SUBTOTAL]]*0.21,IF(Tabla1[[#This Row],[TIPO OPERACIÓN]]="GDES CUENTAS",Tabla1[[#This Row],[SUBTOTAL]]*0.21,IF(Tabla1[[#This Row],[TIPO OPERACIÓN]]="TUC CTADO 2","",IF(Tabla1[[#This Row],[TIPO OPERACIÓN]]="EXPO CHILE","",IF(Tabla1[[#This Row],[TIPO OPERACIÓN]]="TUC CTADO 1",Tabla1[[#This Row],[SUBTOTAL]]*0.21,""))))) -> 2812780.6 | M7: =SUM(K7:L7) -> 16206974 | O7: 0 | P7: 0 | Q7: =+Tabla1[[#This Row],[VENTA TOTAL $ (IVA INC) ]]-Tabla1[[#This Row],[PENDIENTE DE COBRO]] -> 16206974 | R7: =+Tabla1[[#This Row],[FECHA FC]]+Tabla1[[#This Row],[PLAZO ENTREGA VALORES]] -> 46051 | S7: =+Tabla1[[#This Row],[FECHA FC]]+Tabla1[[#This Row],[PLAZO PAGO (DIAS)]] -> 46170.651 | T7: =+S7-$U$2 -> -10.348611 | U7: =+Tabla1[[#This Row],[FECHA OC]]-Tabla1[[#This Row],[FECHA Entrega]] -> -119.65139 | W7: =+Tabla1[[#This Row],[FECHA VTO VALORES]]+7 -> 46177.651 | Y7: 46051 | Z7: =Tabla1[[#This Row],[KGS]]/50 -> 588 | AA7: =IFERROR((IF(Tabla1[[#This Row],[TIPO OPERACIÓN]]="INDUSTRIA",Tabla1[[#This Row],[PRECIO $/ KG A PLAZO EN CLIENTE ( SIN IVA)]]*50*1.21,IF(Tabla1[[#This Row],[TIPO OPERACIÓN]]="TUC CTADO 2",Tabla1[[#This Row],[PRECIO $/ KG A PLAZO EN CLIENTE ( SIN IVA)]]*50,IF(Tabla1[[#This Row],[TIPO OPERACIÓN]]="EXPO CHILE",Tabla1[[#This Row],[PRECIO $/ KG A PLAZO EN CLIENTE ( SIN IVA)]]*50*1,IF(Tabla1[[#This Row],[TIPO OPERACIÓN]]="GDES CUENTAS",Tabla1[[#This Row],[PRECIO $/ KG A PLAZO EN CLIENTE ( SIN IVA)]]*50*1.21,IF(Tabla1[[#This Row],[TIPO OPERACIÓN]]="TUC CTADO 1",Tabla1[[#This Row],[PRECIO $/ KG A PLAZO EN CLIENTE ( SIN IVA)]]*50*1.21,"")))))),"") -> 27562.881 | AB7: =-Tabla1[[#This Row],[COSTO FLETE $ POR BOLSA 5O KG (SIN IVA)]]*1.21-Tabla1[[#This Row],[PRECIO $/ KG A PLAZO EN CLIENTE ( SIN IVA)]]*0.003*1.21*50 -> -0.40864392 | AC7: =SUM(Tabla1[[#This Row],[PRECIO $ BOLSA 50 KG (IVA INC) ]]+Tabla1[[#This Row],[COSTO FLETE $ BOLSA 50 KG (IVA INC)]]) -> 27562.473 | AD7: =-Tabla1[[#This Row],[PRECIO $ BOLSA 50 KG (IVA INC) ]]*(Tabla1[[#This Row],[TASA FINANCIACION MENSUAL]]/365)*Tabla1[[#This Row],[PLAZO ENTREGA VALORES]] -> 262.02787 | AE7: =SUM(Tabla1[[#This Row],[PRECIO $ BOLSA50 KG FOB TUCUMAN A PLAZO (IVA INC)]]+Tabla1[[#This Row],[GASTOS FINANCIEROS $ BOLSA 50 KG (IVA INC)]]) -> 27824.501 | AF7: GRANEL | AG7: RETIRA DE INGENIO | AH7: TUCUMAN | AI7: GDES CUENTAS | AJ7: =IFERROR(IF(Tabla1[[#This Row],[TIPO OPERACIÓN]]="INDUSTRIA",VLOOKUP(Tabla1[[#This Row],[FECHA OC]],'PRECIO CACTU'!A:B,2,FALSE),IF(Tabla1[[#This Row],[TIPO OPERACIÓN]]="GDES CUENTAS",VLOOKUP(Tabla1[[#This Row],[FECHA OC]],'PRECIO CACTU'!A:B,2,FALSE),IF(Tabla1[[#This Row],[TIPO OPERACIÓN]]="EXPO CHILE",VLOOKUP(Tabla1[[#This Row],[FECHA OC]],'PRECIO CACTU'!A:B,2,FALSE)/1.21,IF(Tabla1[[#This Row],[TIPO OPERACIÓN]]="TUC CTADO 2",VLOOKUP(Tabla1[[#This Row],[FECHA OC]],'PRECIO CACTU'!A:B,2,FALSE)/1.21,IF(Tabla1[[#This Row],[TIPO OPERACIÓN]]="TUC CTADO 1",VLOOKUP(Tabla1[[#This Row],[FECHA OC]],'PRECIO CACTU'!A:B,2,FALSE),""))))),"") -> 32515 | AK7: =SUM(Tabla1[[#This Row],[PRECIO $ BOLSA 50KG FOB CDO TUC (IVA INC)]]-Tabla1[[#This Row],[PRECIO REF $ BOLSA 50 KG CACTU (IVA INC)]]) -> -4690.4995 | AL7: =IFERROR(Tabla1[[#This Row],[PRECIO $ BOLSA 50KG FOB CDO TUC (IVA INC)]]/Tabla1[[#This Row],[PRECIO REF $ BOLSA 50 KG CACTU (IVA INC)]]-1,"") -> -0.14425648 | AM7: =+Tabla1[[#This Row],[DIF $ PRECIO NETO INDUSTRIA vs Neto TUCUMAN (IVA INC)]]*Tabla1[[#This Row],[Q Bolsas Equivalentes 50kg]] -> -2758013.7 | AN7: =Tabla1[[#This Row],[PRECIO REF $ BOLSA 50 KG CACTU (IVA INC)]]*Tabla1[[#This Row],[Q Bolsas Equivalentes 50kg]] -> 19118820 | AO7: =+Tabla1[[#This Row],[PRECIO $ BOLSA 50KG FOB CDO TUC (IVA INC)]]*Tabla1[[#This Row],[Q Bolsas Equivalentes 50kg]] -> 16360806 | AP7: 0.029 | AQ7: -68 | AS7: 0008-00005540 | AT7: =+Tabla1[[#This Row],[VENTA TOTAL $ (IVA INC) ]]-(SUM(Tabla1[[#This Row],[PENDIENTE DE ENTREGA]:[VALORES COBRADOS]])) -> 0 | AU7: =VLOOKUP(Tabla1[[#This Row],[FECHA OC]],'TIPO DE CAMBIO'!A:B,2,TRUE) -> 1446.301 | AV7: =+Tabla1[[#This Row],[SUBTOTAL]]/Tabla1[[#This Row],[TIPO DE CAMBIO]] -> 9261 | AX7: =IFERROR(Tabla1[[#This Row],[VENTA TOTAL USD A PLAZO EN CLIENTE (SIN IVA)]]*(1+Tabla1[[#This Row],[% IVA ]]),"") -> 9261 | AY7: =+Tabla1[[#This Row],[VENTA TOTAL USD A PLAZO EN CLIENTE (SIN IVA)]]/Tabla1[[#This Row],[KGS]]*1000 -> 315 | AZ7: 0 | BA7: =+Tabla1[[#This Row],[GASTOS FINANCIEROS $ BOLSA 50 KG (IVA INC)]]*20/Tabla1[[#This Row],[TIPO DE CAMBIO]] -> 3.623421 | BB7: =+Tabla1[[#This Row],[PRECIO POR TN USD EN CLIENTE A PLAZO (SIN IVA)]]+Tabla1[[#This Row],[COSTO USD FLETE /TN (SIN IVA)]]+Tabla1[[#This Row],[COSTO FINANCIERO USD POR BOLSA 50KG (IVA INC)]] -> 318.62342 | BC7: 5
A8: 46143 | B8: 1 | C8: LEDESMA SAAI | D8: =+Tabla1[[#This Row],[FECHA Entrega]] -> 46170.655 | E8: 700000869 | F8: AZÚCAR CRUDO | G8: ENTREGADO | H8: 46170.655 | I8: =581*50 -> 29050 | J8: =0.315*Tabla1[[#This Row],[TIPO DE CAMBIO]] -> 455.58481 | K8: =+J8*I8 -> 13234739 | L8: =IF(Tabla1[[#This Row],[TIPO OPERACIÓN]]="INDUSTRIA",Tabla1[[#This Row],[SUBTOTAL]]*0.21,IF(Tabla1[[#This Row],[TIPO OPERACIÓN]]="GDES CUENTAS",Tabla1[[#This Row],[SUBTOTAL]]*0.21,IF(Tabla1[[#This Row],[TIPO OPERACIÓN]]="TUC CTADO 2","",IF(Tabla1[[#This Row],[TIPO OPERACIÓN]]="EXPO CHILE","",IF(Tabla1[[#This Row],[TIPO OPERACIÓN]]="TUC CTADO 1",Tabla1[[#This Row],[SUBTOTAL]]*0.21,""))))) -> 2779295.2 | M8: =SUM(K8:L8) -> 16014034 | O8: 0 | P8: 0 | Q8: =+Tabla1[[#This Row],[VENTA TOTAL $ (IVA INC) ]]-Tabla1[[#This Row],[PENDIENTE DE COBRO]] -> 16014034 | R8: =+Tabla1[[#This Row],[FECHA FC]]+Tabla1[[#This Row],[PLAZO ENTREGA VALORES]] -> 46051 | S8: =+Tabla1[[#This Row],[FECHA FC]]+Tabla1[[#This Row],[PLAZO PAGO (DIAS)]] -> 46170.655 | T8: =+S8-$U$2 -> -10.345139 | U8: =+Tabla1[[#This Row],[FECHA OC]]-Tabla1[[#This Row],[FECHA Entrega]] -> -119.65486 | W8: =+Tabla1[[#This Row],[FECHA VTO VALORES]]+7 -> 46177.655 | Y8: 46051 | Z8: =Tabla1[[#This Row],[KGS]]/50 -> 581 | AA8: =IFERROR((IF(Tabla1[[#This Row],[TIPO OPERACIÓN]]="INDUSTRIA",Tabla1[[#This Row],[PRECIO $/ KG A PLAZO EN CLIENTE ( SIN IVA)]]*50*1.21,IF(Tabla1[[#This Row],[TIPO OPERACIÓN]]="TUC CTADO 2",Tabla1[[#This Row],[PRECIO $/ KG A PLAZO EN CLIENTE ( SIN IVA)]]*50,IF(Tabla1[[#This Row],[TIPO OPERACIÓN]]="EXPO CHILE",Tabla1[[#This Row],[PRECIO $/ KG A PLAZO EN CLIENTE ( SIN IVA)]]*50*1,IF(Tabla1[[#This Row],[TIPO OPERACIÓN]]="GDES CUENTAS",Tabla1[[#This Row],[PRECIO $/ KG A PLAZO EN CLIENTE ( SIN IVA)]]*50*1.21,IF(Tabla1[[#This Row],[TIPO OPERACIÓN]]="TUC CTADO 1",Tabla1[[#This Row],[PRECIO $/ KG A PLAZO EN CLIENTE ( SIN IVA)]]*50*1.21,"")))))),"") -> 27562.881 | AB8: =-Tabla1[[#This Row],[COSTO FLETE $ POR BOLSA 5O KG (SIN IVA)]]*1.21-Tabla1[[#This Row],[PRECIO $/ KG A PLAZO EN CLIENTE ( SIN IVA)]]*0.003*1.21*50 -> -0.40864392 | AC8: =SUM(Tabla1[[#This Row],[PRECIO $ BOLSA 50 KG (IVA INC) ]]+Tabla1[[#This Row],[COSTO FLETE $ BOLSA 50 KG (IVA INC)]]) -> 27562.473 | AD8: =-Tabla1[[#This Row],[PRECIO $ BOLSA 50 KG (IVA INC) ]]*(Tabla1[[#This Row],[TASA FINANCIACION MENSUAL]]/365)*Tabla1[[#This Row],[PLAZO ENTREGA VALORES]] -> 262.03548 | AE8: =SUM(Tabla1[[#This Row],[PRECIO $ BOLSA50 KG FOB TUCUMAN A PLAZO (IVA INC)]]+Tabla1[[#This Row],[GASTOS FINANCIEROS $ BOLSA 50 KG (IVA INC)]]) -> 27824.508 | AF8: GRANEL | AG8: RETIRA DE INGENIO | AH8: TUCUMAN | AI8: GDES CUENTAS | AJ8: =IFERROR(IF(Tabla1[[#This Row],[TIPO OPERACIÓN]]="INDUSTRIA",VLOOKUP(Tabla1[[#This Row],[FECHA OC]],'PRECIO CACTU'!A:B,2,FALSE),IF(Tabla1[[#This Row],[TIPO OPERACIÓN]]="GDES CUENTAS",VLOOKUP(Tabla1[[#This Row],[FECHA OC]],'PRECIO CACTU'!A:B,2,FALSE),IF(Tabla1[[#This Row],[TIPO OPERACIÓN]]="EXPO CHILE",VLOOKUP(Tabla1[[#This Row],[FECHA OC]],'PRECIO CACTU'!A:B,2,FALSE)/1.21,IF(Tabla1[[#This Row],[TIPO OPERACIÓN]]="TUC CTADO 2",VLOOKUP(Tabla1[[#This Row],[FECHA OC]],'PRECIO CACTU'!A:B,2,FALSE)/1.21,IF(Tabla1[[#This Row],[TIPO OPERACIÓN]]="TUC CTADO 1",VLOOKUP(Tabla1[[#This Row],[FECHA OC]],'PRECIO CACTU'!A:B,2,FALSE),""))))),"") -> 32515 | AK8: =SUM(Tabla1[[#This Row],[PRECIO $ BOLSA 50KG FOB CDO TUC (IVA INC)]]-Tabla1[[#This Row],[PRECIO REF $ BOLSA 50 KG CACTU (IVA INC)]]) -> -4690.4919 | AL8: =IFERROR(Tabla1[[#This Row],[PRECIO $ BOLSA 50KG FOB CDO TUC (IVA INC)]]/Tabla1[[#This Row],[PRECIO REF $ BOLSA 50 KG CACTU (IVA INC)]]-1,"") -> -0.14425625 | AM8: =+Tabla1[[#This Row],[DIF $ PRECIO NETO INDUSTRIA vs Neto TUCUMAN (IVA INC)]]*Tabla1[[#This Row],[Q Bolsas Equivalentes 50kg]] -> -2725175.8 | AN8: =Tabla1[[#This Row],[PRECIO REF $ BOLSA 50 KG CACTU (IVA INC)]]*Tabla1[[#This Row],[Q Bolsas Equivalentes 50kg]] -> 18891215 | AO8: =+Tabla1[[#This Row],[PRECIO $ BOLSA 50KG FOB CDO TUC (IVA INC)]]*Tabla1[[#This Row],[Q Bolsas Equivalentes 50kg]] -> 16166039 | AP8: 0.029 | AQ8: -68 | AS8: 0008-00005542 | AT8: =+Tabla1[[#This Row],[VENTA TOTAL $ (IVA INC) ]]-(SUM(Tabla1[[#This Row],[PENDIENTE DE ENTREGA]:[VALORES COBRADOS]])) -> 0 | AU8: =VLOOKUP(Tabla1[[#This Row],[FECHA OC]],'TIPO DE CAMBIO'!A:B,2,TRUE) -> 1446.301 | AV8: =+Tabla1[[#This Row],[SUBTOTAL]]/Tabla1[[#This Row],[TIPO DE CAMBIO]] -> 9150.75 | AX8: =IFERROR(Tabla1[[#This Row],[VENTA TOTAL USD A PLAZO EN CLIENTE (SIN IVA)]]*(1+Tabla1[[#This Row],[% IVA ]]),"") -> 9150.75 | AY8: =+Tabla1[[#This Row],[VENTA TOTAL USD A PLAZO EN CLIENTE (SIN IVA)]]/Tabla1[[#This Row],[KGS]]*1000 -> 315 | AZ8: 0 | BA8: =+Tabla1[[#This Row],[GASTOS FINANCIEROS $ BOLSA 50 KG (IVA INC)]]*20/Tabla1[[#This Row],[TIPO DE CAMBIO]] -> 3.6235262 | BB8: =+Tabla1[[#This Row],[PRECIO POR TN USD EN CLIENTE A PLAZO (SIN IVA)]]+Tabla1[[#This Row],[COSTO USD FLETE /TN (SIN IVA)]]+Tabla1[[#This Row],[COSTO FINANCIERO USD POR BOLSA 50KG (IVA INC)]] -> 318.62353 | BC8: 5
A9: 46143 | B9: 1 | C9: LEDESMA SAAI | D9: =+Tabla1[[#This Row],[FECHA Entrega]] -> 46170.758 | E9: 700000869 | F9: AZÚCAR CRUDO | G9: ENTREGADO | H9: 46170.758 | I9: =586*50 -> 29300 | J9: =0.315*Tabla1[[#This Row],[TIPO DE CAMBIO]] -> 455.58481 | K9: =+J9*I9 -> 13348635 | L9: =IF(Tabla1[[#This Row],[TIPO OPERACIÓN]]="INDUSTRIA",Tabla1[[#This Row],[SUBTOTAL]]*0.21,IF(Tabla1[[#This Row],[TIPO OPERACIÓN]]="GDES CUENTAS",Tabla1[[#This Row],[SUBTOTAL]]*0.21,IF(Tabla1[[#This Row],[TIPO OPERACIÓN]]="TUC CTADO 2","",IF(Tabla1[[#This Row],[TIPO OPERACIÓN]]="EXPO CHILE","",IF(Tabla1[[#This Row],[TIPO OPERACIÓN]]="TUC CTADO 1",Tabla1[[#This Row],[SUBTOTAL]]*0.21,""))))) -> 2803213.4 | M9: =SUM(K9:L9) -> 16151848 | O9: 0 | P9: 0 | Q9: =+Tabla1[[#This Row],[VENTA TOTAL $ (IVA INC) ]]-Tabla1[[#This Row],[PENDIENTE DE COBRO]] -> 16151848 | R9: =+Tabla1[[#This Row],[FECHA FC]]+Tabla1[[#This Row],[PLAZO ENTREGA VALORES]] -> 46051 | S9: =+Tabla1[[#This Row],[FECHA FC]]+Tabla1[[#This Row],[PLAZO PAGO (DIAS)]] -> 46170.758 | T9: =+S9-$U$2 -> -10.242361 | U9: =+Tabla1[[#This Row],[FECHA OC]]-Tabla1[[#This Row],[FECHA Entrega]] -> -119.75764 | W9: =+Tabla1[[#This Row],[FECHA VTO VALORES]]+7 -> 46177.758 | Y9: 46051 | Z9: =Tabla1[[#This Row],[KGS]]/50 -> 586 | AA9: =IFERROR((IF(Tabla1[[#This Row],[TIPO OPERACIÓN]]="INDUSTRIA",Tabla1[[#This Row],[PRECIO $/ KG A PLAZO EN CLIENTE ( SIN IVA)]]*50*1.21,IF(Tabla1[[#This Row],[TIPO OPERACIÓN]]="TUC CTADO 2",Tabla1[[#This Row],[PRECIO $/ KG A PLAZO EN CLIENTE ( SIN IVA)]]*50,IF(Tabla1[[#This Row],[TIPO OPERACIÓN]]="EXPO CHILE",Tabla1[[#This Row],[PRECIO $/ KG A PLAZO EN CLIENTE ( SIN IVA)]]*50*1,IF(Tabla1[[#This Row],[TIPO OPERACIÓN]]="GDES CUENTAS",Tabla1[[#This Row],[PRECIO $/ KG A PLAZO EN CLIENTE ( SIN IVA)]]*50*1.21,IF(Tabla1[[#This Row],[TIPO OPERACIÓN]]="TUC CTADO 1",Tabla1[[#This Row],[PRECIO $/ KG A PLAZO EN CLIENTE ( SIN IVA)]]*50*1.21,"")))))),"") -> 27562.881 | AB9: =-Tabla1[[#This Row],[COSTO FLETE $ POR BOLSA 5O KG (SIN IVA)]]*1.21-Tabla1[[#This Row],[PRECIO $/ KG A PLAZO EN CLIENTE ( SIN IVA)]]*0.003*1.21*50 -> -0.40864392 | AC9: =SUM(Tabla1[[#This Row],[PRECIO $ BOLSA 50 KG (IVA INC) ]]+Tabla1[[#This Row],[COSTO FLETE $ BOLSA 50 KG (IVA INC)]]) -> 27562.473 | AD9: =-Tabla1[[#This Row],[PRECIO $ BOLSA 50 KG (IVA INC) ]]*(Tabla1[[#This Row],[TASA FINANCIACION MENSUAL]]/365)*Tabla1[[#This Row],[PLAZO ENTREGA VALORES]] -> 262.26055 | AE9: =SUM(Tabla1[[#This Row],[PRECIO $ BOLSA50 KG FOB TUCUMAN A PLAZO (IVA INC)]]+Tabla1[[#This Row],[GASTOS FINANCIEROS $ BOLSA 50 KG (IVA INC)]]) -> 27824.733 | AF9: GRANEL | AG9: RETIRA DE INGENIO | AH9: TUCUMAN | AI9: GDES CUENTAS | AJ9: =IFERROR(IF(Tabla1[[#This Row],[TIPO OPERACIÓN]]="INDUSTRIA",VLOOKUP(Tabla1[[#This Row],[FECHA OC]],'PRECIO CACTU'!A:B,2,FALSE),IF(Tabla1[[#This Row],[TIPO OPERACIÓN]]="GDES CUENTAS",VLOOKUP(Tabla1[[#This Row],[FECHA OC]],'PRECIO CACTU'!A:B,2,FALSE),IF(Tabla1[[#This Row],[TIPO OPERACIÓN]]="EXPO CHILE",VLOOKUP(Tabla1[[#This Row],[FECHA OC]],'PRECIO CACTU'!A:B,2,FALSE)/1.21,IF(Tabla1[[#This Row],[TIPO OPERACIÓN]]="TUC CTADO 2",VLOOKUP(Tabla1[[#This Row],[FECHA OC]],'PRECIO CACTU'!A:B,2,FALSE)/1.21,IF(Tabla1[[#This Row],[TIPO OPERACIÓN]]="TUC CTADO 1",VLOOKUP(Tabla1[[#This Row],[FECHA OC]],'PRECIO CACTU'!A:B,2,FALSE),""))))),"") -> 32515 | AK9: =SUM(Tabla1[[#This Row],[PRECIO $ BOLSA 50KG FOB CDO TUC (IVA INC)]]-Tabla1[[#This Row],[PRECIO REF $ BOLSA 50 KG CACTU (IVA INC)]]) -> -4690.2668 | AL9: =IFERROR(Tabla1[[#This Row],[PRECIO $ BOLSA 50KG FOB CDO TUC (IVA INC)]]/Tabla1[[#This Row],[PRECIO REF $ BOLSA 50 KG CACTU (IVA INC)]]-1,"") -> -0.14424932 | AM9: =+Tabla1[[#This Row],[DIF $ PRECIO NETO INDUSTRIA vs Neto TUCUMAN (IVA INC)]]*Tabla1[[#This Row],[Q Bolsas Equivalentes 50kg]] -> -2748496.3 | AN9: =Tabla1[[#This Row],[PRECIO REF $ BOLSA 50 KG CACTU (IVA INC)]]*Tabla1[[#This Row],[Q Bolsas Equivalentes 50kg]] -> 19053790 | AO9: =+Tabla1[[#This Row],[PRECIO $ BOLSA 50KG FOB CDO TUC (IVA INC)]]*Tabla1[[#This Row],[Q Bolsas Equivalentes 50kg]] -> 16305294 | AP9: 0.029 | AQ9: -68 | AS9: 0008-00005544 | AT9: =+Tabla1[[#This Row],[VENTA TOTAL $ (IVA INC) ]]-(SUM(Tabla1[[#This Row],[PENDIENTE DE ENTREGA]:[VALORES COBRADOS]])) -> 0 | AU9: =VLOOKUP(Tabla1[[#This Row],[FECHA OC]],'TIPO DE CAMBIO'!A:B,2,TRUE) -> 1446.301 | AV9: =+Tabla1[[#This Row],[SUBTOTAL]]/Tabla1[[#This Row],[TIPO DE CAMBIO]] -> 9229.5 | AX9: =IFERROR(Tabla1[[#This Row],[VENTA TOTAL USD A PLAZO EN CLIENTE (SIN IVA)]]*(1+Tabla1[[#This Row],[% IVA ]]),"") -> 9229.5 | AY9: =+Tabla1[[#This Row],[VENTA TOTAL USD A PLAZO EN CLIENTE (SIN IVA)]]/Tabla1[[#This Row],[KGS]]*1000 -> 315 | AZ9: 0 | BA9: =+Tabla1[[#This Row],[GASTOS FINANCIEROS $ BOLSA 50 KG (IVA INC)]]*20/Tabla1[[#This Row],[TIPO DE CAMBIO]] -> 3.6266386 | BB9: =+Tabla1[[#This Row],[PRECIO POR TN USD EN CLIENTE A PLAZO (SIN IVA)]]+Tabla1[[#This Row],[COSTO USD FLETE /TN (SIN IVA)]]+Tabla1[[#This Row],[COSTO FINANCIERO USD POR BOLSA 50KG (IVA INC)]] -> 318.62664 | BC9: 5
A10: 46143 | B10: 1 | C10: LEDESMA SAAI | D10: =+Tabla1[[#This Row],[FECHA Entrega]] -> 46170.808 | E10: 700000869 | F10: AZÚCAR CRUDO | G10: ENTREGADO | H10: 46170.808 | I10: =728*50 -> 36400 | J10: =0.315*Tabla1[[#This Row],[TIPO DE CAMBIO]] -> 455.58481 | K10: =+J10*I10 -> 16583287 | L10: =IF(Tabla1[[#This Row],[TIPO OPERACIÓN]]="INDUSTRIA",Tabla1[[#This Row],[SUBTOTAL]]*0.21,IF(Tabla1[[#This Row],[TIPO OPERACIÓN]]="GDES CUENTAS",Tabla1[[#This Row],[SUBTOTAL]]*0.21,IF(Tabla1[[#This Row],[TIPO OPERACIÓN]]="TUC CTADO 2","",IF(Tabla1[[#This Row],[TIPO OPERACIÓN]]="EXPO CHILE","",IF(Tabla1[[#This Row],[TIPO OPERACIÓN]]="TUC CTADO 1",Tabla1[[#This Row],[SUBTOTAL]]*0.21,""))))) -> 3482490.3 | M10: =SUM(K10:L10) -> 20065778 | O10: 0 | P10: 0 | Q10: =+Tabla1[[#This Row],[VENTA TOTAL $ (IVA INC) ]]-Tabla1[[#This Row],[PENDIENTE DE COBRO]] -> 20065778 | R10: =+Tabla1[[#This Row],[FECHA FC]]+Tabla1[[#This Row],[PLAZO ENTREGA VALORES]] -> 46051 | S10: =+Tabla1[[#This Row],[FECHA FC]]+Tabla1[[#This Row],[PLAZO PAGO (DIAS)]] -> 46170.808 | T10: =+S10-$U$2 -> -10.191667 | U10: =+Tabla1[[#This Row],[FECHA OC]]-Tabla1[[#This Row],[FECHA Entrega]] -> -119.80833 | W10: =+Tabla1[[#This Row],[FECHA VTO VALORES]]+7 -> 46177.808 | Y10: 46051 | Z10: =Tabla1[[#This Row],[KGS]]/50 -> 728 | AA10: =IFERROR((IF(Tabla1[[#This Row],[TIPO OPERACIÓN]]="INDUSTRIA",Tabla1[[#This Row],[PRECIO $/ KG A PLAZO EN CLIENTE ( SIN IVA)]]*50*1.21,IF(Tabla1[[#This Row],[TIPO OPERACIÓN]]="TUC CTADO 2",Tabla1[[#This Row],[PRECIO $/ KG A PLAZO EN CLIENTE ( SIN IVA)]]*50,IF(Tabla1[[#This Row],[TIPO OPERACIÓN]]="EXPO CHILE",Tabla1[[#This Row],[PRECIO $/ KG A PLAZO EN CLIENTE ( SIN IVA)]]*50*1,IF(Tabla1[[#This Row],[TIPO OPERACIÓN]]="GDES CUENTAS",Tabla1[[#This Row],[PRECIO $/ KG A PLAZO EN CLIENTE ( SIN IVA)]]*50*1.21,IF(Tabla1[[#This Row],[TIPO OPERACIÓN]]="TUC CTADO 1",Tabla1[[#This Row],[PRECIO $/ KG A PLAZO EN CLIENTE ( SIN IVA)]]*50*1.21,"")))))),"") -> 27562.881 | AB10: =-Tabla1[[#This Row],[COSTO FLETE $ POR BOLSA 5O KG (SIN IVA)]]*1.21-Tabla1[[#This Row],[PRECIO $/ KG A PLAZO EN CLIENTE ( SIN IVA)]]*0.003*1.21*50 -> -0.40864392 | AC10: =SUM(Tabla1[[#This Row],[PRECIO $ BOLSA 50 KG (IVA INC) ]]+Tabla1[[#This Row],[COSTO FLETE $ BOLSA 50 KG (IVA INC)]]) -> 27562.473 | AD10: =-Tabla1[[#This Row],[PRECIO $ BOLSA 50 KG (IVA INC) ]]*(Tabla1[[#This Row],[TASA FINANCIACION MENSUAL]]/365)*Tabla1[[#This Row],[PLAZO ENTREGA VALORES]] -> 262.37157 | AE10: =SUM(Tabla1[[#This Row],[PRECIO $ BOLSA50 KG FOB TUCUMAN A PLAZO (IVA INC)]]+Tabla1[[#This Row],[GASTOS FINANCIEROS $ BOLSA 50 KG (IVA INC)]]) -> 27824.844 | AF10: GRANEL | AG10: RETIRA DE INGENIO | AH10: TUCUMAN | AI10: GDES CUENTAS | AJ10: =IFERROR(IF(Tabla1[[#This Row],[TIPO OPERACIÓN]]="INDUSTRIA",VLOOKUP(Tabla1[[#This Row],[FECHA OC]],'PRECIO CACTU'!A:B,2,FALSE),IF(Tabla1[[#This Row],[TIPO OPERACIÓN]]="GDES CUENTAS",VLOOKUP(Tabla1[[#This Row],[FECHA OC]],'PRECIO CACTU'!A:B,2,FALSE),IF(Tabla1[[#This Row],[TIPO OPERACIÓN]]="EXPO CHILE",VLOOKUP(Tabla1[[#This Row],[FECHA OC]],'PRECIO CACTU'!A:B,2,FALSE)/1.21,IF(Tabla1[[#This Row],[TIPO OPERACIÓN]]="TUC CTADO 2",VLOOKUP(Tabla1[[#This Row],[FECHA OC]],'PRECIO CACTU'!A:B,2,FALSE)/1.21,IF(Tabla1[[#This Row],[TIPO OPERACIÓN]]="TUC CTADO 1",VLOOKUP(Tabla1[[#This Row],[FECHA OC]],'PRECIO CACTU'!A:B,2,FALSE),""))))),"") -> 32515 | AK10: =SUM(Tabla1[[#This Row],[PRECIO $ BOLSA 50KG FOB CDO TUC (IVA INC)]]-Tabla1[[#This Row],[PRECIO REF $ BOLSA 50 KG CACTU (IVA INC)]]) -> -4690.1558 | AL10: =IFERROR(Tabla1[[#This Row],[PRECIO $ BOLSA 50KG FOB CDO TUC (IVA INC)]]/Tabla1[[#This Row],[PRECIO REF $ BOLSA 50 KG CACTU (IVA INC)]]-1,"") -> -0.14424591 | AM10: =+Tabla1[[#This Row],[DIF $ PRECIO NETO INDUSTRIA vs Neto TUCUMAN (IVA INC)]]*Tabla1[[#This Row],[Q Bolsas Equivalentes 50kg]] -> -3414433.4 | AN10: =Tabla1[[#This Row],[PRECIO REF $ BOLSA 50 KG CACTU (IVA INC)]]*Tabla1[[#This Row],[Q Bolsas Equivalentes 50kg]] -> 23670920 | AO10: =+Tabla1[[#This Row],[PRECIO $ BOLSA 50KG FOB CDO TUC (IVA INC)]]*Tabla1[[#This Row],[Q Bolsas Equivalentes 50kg]] -> 20256487 | AP10: 0.029 | AQ10: -68 | AS10: 0008-00005546 | AT10: =+Tabla1[[#This Row],[VENTA TOTAL $ (IVA INC) ]]-(SUM(Tabla1[[#This Row],[PENDIENTE DE ENTREGA]:[VALORES COBRADOS]])) -> 0 | AU10: =VLOOKUP(Tabla1[[#This Row],[FECHA OC]],'TIPO DE CAMBIO'!A:B,2,TRUE) -> 1446.301 | AV10: =+Tabla1[[#This Row],[SUBTOTAL]]/Tabla1[[#This Row],[TIPO DE CAMBIO]] -> 11466 | AX10: =IFERROR(Tabla1[[#This Row],[VENTA TOTAL USD A PLAZO EN CLIENTE (SIN IVA)]]*(1+Tabla1[[#This Row],[% IVA ]]),"") -> 11466 | AY10: =+Tabla1[[#This Row],[VENTA TOTAL USD A PLAZO EN CLIENTE (SIN IVA)]]/Tabla1[[#This Row],[KGS]]*1000 -> 315 | AZ10: 0 | BA10: =+Tabla1[[#This Row],[GASTOS FINANCIEROS $ BOLSA 50 KG (IVA INC)]]*20/Tabla1[[#This Row],[TIPO DE CAMBIO]] -> 3.6281738 | BB10: =+Tabla1[[#This Row],[PRECIO POR TN USD EN CLIENTE A PLAZO (SIN IVA)]]+Tabla1[[#This Row],[COSTO USD FLETE /TN (SIN IVA)]]+Tabla1[[#This Row],[COSTO FINANCIERO USD POR BOLSA 50KG (IVA INC)]] -> 318.62817 | BC10: 5
A11: 46143 | B11: 1 | C11: LEDESMA SAAI | D11: =+Tabla1[[#This Row],[FECHA Entrega]] -> 46172.361 | E11: 700000869 | F11: AZÚCAR CRUDO | G11: ENTREGADO | H11: 46172.361 | I11: =732*50 -> 36600 | J11: =0.315*Tabla1[[#This Row],[TIPO DE CAMBIO]] -> 455.58481 | K11: =+J11*I11 -> 16674404 | L11: =IF(Tabla1[[#This Row],[TIPO OPERACIÓN]]="INDUSTRIA",Tabla1[[#This Row],[SUBTOTAL]]*0.21,IF(Tabla1[[#This Row],[TIPO OPERACIÓN]]="GDES CUENTAS",Tabla1[[#This Row],[SUBTOTAL]]*0.21,IF(Tabla1[[#This Row],[TIPO OPERACIÓN]]="TUC CTADO 2","",IF(Tabla1[[#This Row],[TIPO OPERACIÓN]]="EXPO CHILE","",IF(Tabla1[[#This Row],[TIPO OPERACIÓN]]="TUC CTADO 1",Tabla1[[#This Row],[SUBTOTAL]]*0.21,""))))) -> 3501624.9 | M11: =SUM(K11:L11) -> 20176029 | O11: 0 | P11: 0 | Q11: =+Tabla1[[#This Row],[VENTA TOTAL $ (IVA INC) ]]-Tabla1[[#This Row],[PENDIENTE DE COBRO]] -> 20176029 | R11: =+Tabla1[[#This Row],[FECHA FC]]+Tabla1[[#This Row],[PLAZO ENTREGA VALORES]] -> 46051 | S11: =+Tabla1[[#This Row],[FECHA FC]]+Tabla1[[#This Row],[PLAZO PAGO (DIAS)]] -> 46172.361 | T11: =+S11-$U$2 -> -8.6388889 | U11: =+Tabla1[[#This Row],[FECHA OC]]-Tabla1[[#This Row],[FECHA Entrega]] -> -121.36111 | W11: =+Tabla1[[#This Row],[FECHA VTO VALORES]]+7 -> 46179.361 | Y11: 46051 | Z11: =Tabla1[[#This Row],[KGS]]/50 -> 732 | AA11: =IFERROR((IF(Tabla1[[#This Row],[TIPO OPERACIÓN]]="INDUSTRIA",Tabla1[[#This Row],[PRECIO $/ KG A PLAZO EN CLIENTE ( SIN IVA)]]*50*1.21,IF(Tabla1[[#This Row],[TIPO OPERACIÓN]]="TUC CTADO 2",Tabla1[[#This Row],[PRECIO $/ KG A PLAZO EN CLIENTE ( SIN IVA)]]*50,IF(Tabla1[[#This Row],[TIPO OPERACIÓN]]="EXPO CHILE",Tabla1[[#This Row],[PRECIO $/ KG A PLAZO EN CLIENTE ( SIN IVA)]]*50*1,IF(Tabla1[[#This Row],[TIPO OPERACIÓN]]="GDES CUENTAS",Tabla1[[#This Row],[PRECIO $/ KG A PLAZO EN CLIENTE ( SIN IVA)]]*50*1.21,IF(Tabla1[[#This Row],[TIPO OPERACIÓN]]="TUC CTADO 1",Tabla1[[#This Row],[PRECIO $/ KG A PLAZO EN CLIENTE ( SIN IVA)]]*50*1.21,"")))))),"") -> 27562.881 | AB11: =-Tabla1[[#This Row],[COSTO FLETE $ POR BOLSA 5O KG (SIN IVA)]]*1.21-Tabla1[[#This Row],[PRECIO $/ KG A PLAZO EN CLIENTE ( SIN IVA)]]*0.003*1.21*50 -> -0.40864392 | AC11: =SUM(Tabla1[[#This Row],[PRECIO $ BOLSA 50 KG (IVA INC) ]]+Tabla1[[#This Row],[COSTO FLETE $ BOLSA 50 KG (IVA INC)]]) -> 27562.473 | AD11: =-Tabla1[[#This Row],[PRECIO $ BOLSA 50 KG (IVA INC) ]]*(Tabla1[[#This Row],[TASA FINANCIACION MENSUAL]]/365)*Tabla1[[#This Row],[PLAZO ENTREGA VALORES]] -> 265.77204 | AE11: =SUM(Tabla1[[#This Row],[PRECIO $ BOLSA50 KG FOB TUCUMAN A PLAZO (IVA INC)]]+Tabla1[[#This Row],[GASTOS FINANCIEROS $ BOLSA 50 KG (IVA INC)]]) -> 27828.245 | AF11: GRANEL | AG11: RETIRA DE INGENIO | AH11: TUCUMAN | AI11: GDES CUENTAS | AJ11: =IFERROR(IF(Tabla1[[#This Row],[TIPO OPERACIÓN]]="INDUSTRIA",VLOOKUP(Tabla1[[#This Row],[FECHA OC]],'PRECIO CACTU'!A:B,2,FALSE),IF(Tabla1[[#This Row],[TIPO OPERACIÓN]]="GDES CUENTAS",VLOOKUP(Tabla1[[#This Row],[FECHA OC]],'PRECIO CACTU'!A:B,2,FALSE),IF(Tabla1[[#This Row],[TIPO OPERACIÓN]]="EXPO CHILE",VLOOKUP(Tabla1[[#This Row],[FECHA OC]],'PRECIO CACTU'!A:B,2,FALSE)/1.21,IF(Tabla1[[#This Row],[TIPO OPERACIÓN]]="TUC CTADO 2",VLOOKUP(Tabla1[[#This Row],[FECHA OC]],'PRECIO CACTU'!A:B,2,FALSE)/1.21,IF(Tabla1[[#This Row],[TIPO OPERACIÓN]]="TUC CTADO 1",VLOOKUP(Tabla1[[#This Row],[FECHA OC]],'PRECIO CACTU'!A:B,2,FALSE),""))))),"") -> 32515 | AK11: =SUM(Tabla1[[#This Row],[PRECIO $ BOLSA 50KG FOB CDO TUC (IVA INC)]]-Tabla1[[#This Row],[PRECIO REF $ BOLSA 50 KG CACTU (IVA INC)]]) -> -4686.7553 | AL11: =IFERROR(Tabla1[[#This Row],[PRECIO $ BOLSA 50KG FOB CDO TUC (IVA INC)]]/Tabla1[[#This Row],[PRECIO REF $ BOLSA 50 KG CACTU (IVA INC)]]-1,"") -> -0.14414133 | AM11: =+Tabla1[[#This Row],[DIF $ PRECIO NETO INDUSTRIA vs Neto TUCUMAN (IVA INC)]]*Tabla1[[#This Row],[Q Bolsas Equivalentes 50kg]] -> -3430704.9 | AN11: =Tabla1[[#This Row],[PRECIO REF $ BOLSA 50 KG CACTU (IVA INC)]]*Tabla1[[#This Row],[Q Bolsas Equivalentes 50kg]] -> 23800980 | AO11: =+Tabla1[[#This Row],[PRECIO $ BOLSA 50KG FOB CDO TUC (IVA INC)]]*Tabla1[[#This Row],[Q Bolsas Equivalentes 50kg]] -> 20370275 | AP11: 0.029 | AQ11: -68 | AS11: 0008-00005549 | AT11: =+Tabla1[[#This Row],[VENTA TOTAL $ (IVA INC) ]]-(SUM(Tabla1[[#This Row],[PENDIENTE DE ENTREGA]:[VALORES COBRADOS]])) -> 0 | AU11: =VLOOKUP(Tabla1[[#This Row],[FECHA OC]],'TIPO DE CAMBIO'!A:B,2,TRUE) -> 1446.301 | AV11: =+Tabla1[[#This Row],[SUBTOTAL]]/Tabla1[[#This Row],[TIPO DE CAMBIO]] -> 11529 | AX11: =IFERROR(Tabla1[[#This Row],[VENTA TOTAL USD A PLAZO EN CLIENTE (SIN IVA)]]*(1+Tabla1[[#This Row],[% IVA ]]),"") -> 11529 | AY11: =+Tabla1[[#This Row],[VENTA TOTAL USD A PLAZO EN CLIENTE (SIN IVA)]]/Tabla1[[#This Row],[KGS]]*1000 -> 315 | AZ11: 0 | BA11: =+Tabla1[[#This Row],[GASTOS FINANCIEROS $ BOLSA 50 KG (IVA INC)]]*20/Tabla1[[#This Row],[TIPO DE CAMBIO]] -> 3.6751968 | BB11: =+Tabla1[[#This Row],[PRECIO POR TN USD EN CLIENTE A PLAZO (SIN IVA)]]+Tabla1[[#This Row],[COSTO USD FLETE /TN (SIN IVA)]]+Tabla1[[#This Row],[COSTO FINANCIERO USD POR BOLSA 50KG (IVA INC)]] -> 318.6752 | BC11: 5
A12: 46143 | B12: 1 | C12: LEDESMA SAAI | D12: =+Tabla1[[#This Row],[FECHA Entrega]] -> 46172.394 | E12: 700000869 | F12: AZÚCAR CRUDO | G12: ENTREGADO | H12: 46172.394 | I12: =588*50 -> 29400 | J12: =0.315*Tabla1[[#This Row],[TIPO DE CAMBIO]] -> 455.58481 | K12: =+J12*I12 -> 13394194 | L12: =IF(Tabla1[[#This Row],[TIPO OPERACIÓN]]="INDUSTRIA",Tabla1[[#This Row],[SUBTOTAL]]*0.21,IF(Tabla1[[#This Row],[TIPO OPERACIÓN]]="GDES CUENTAS",Tabla1[[#This Row],[SUBTOTAL]]*0.21,IF(Tabla1[[#This Row],[TIPO OPERACIÓN]]="TUC CTADO 2","",IF(Tabla1[[#This Row],[TIPO OPERACIÓN]]="EXPO CHILE","",IF(Tabla1[[#This Row],[TIPO OPERACIÓN]]="TUC CTADO 1",Tabla1[[#This Row],[SUBTOTAL]]*0.21,""))))) -> 2812780.6 | M12: =SUM(K12:L12) -> 16206974 | O12: 0 | P12: 0 | Q12: =+Tabla1[[#This Row],[VENTA TOTAL $ (IVA INC) ]]-Tabla1[[#This Row],[PENDIENTE DE COBRO]] -> 16206974 | R12: =+Tabla1[[#This Row],[FECHA FC]]+Tabla1[[#This Row],[PLAZO ENTREGA VALORES]] -> 46051 | S12: =+Tabla1[[#This Row],[FECHA FC]]+Tabla1[[#This Row],[PLAZO PAGO (DIAS)]] -> 46172.394 | T12: =+S12-$U$2 -> -8.60625 | U12: =+Tabla1[[#This Row],[FECHA OC]]-Tabla1[[#This Row],[FECHA Entrega]] -> -121.39375 | W12: =+Tabla1[[#This Row],[FECHA VTO VALORES]]+7 -> 46179.394 | Y12: 46051 | Z12: =Tabla1[[#This Row],[KGS]]/50 -> 588 | AA12: =IFERROR((IF(Tabla1[[#This Row],[TIPO OPERACIÓN]]="INDUSTRIA",Tabla1[[#This Row],[PRECIO $/ KG A PLAZO EN CLIENTE ( SIN IVA)]]*50*1.21,IF(Tabla1[[#This Row],[TIPO OPERACIÓN]]="TUC CTADO 2",Tabla1[[#This Row],[PRECIO $/ KG A PLAZO EN CLIENTE ( SIN IVA)]]*50,IF(Tabla1[[#This Row],[TIPO OPERACIÓN]]="EXPO CHILE",Tabla1[[#This Row],[PRECIO $/ KG A PLAZO EN CLIENTE ( SIN IVA)]]*50*1,IF(Tabla1[[#This Row],[TIPO OPERACIÓN]]="GDES CUENTAS",Tabla1[[#This Row],[PRECIO $/ KG A PLAZO EN CLIENTE ( SIN IVA)]]*50*1.21,IF(Tabla1[[#This Row],[TIPO OPERACIÓN]]="TUC CTADO 1",Tabla1[[#This Row],[PRECIO $/ KG A PLAZO EN CLIENTE ( SIN IVA)]]*50*1.21,"")))))),"") -> 27562.881 | AB12: =-Tabla1[[#This Row],[COSTO FLETE $ POR BOLSA 5O KG (SIN IVA)]]*1.21-Tabla1[[#This Row],[PRECIO $/ KG A PLAZO EN CLIENTE ( SIN IVA)]]*0.003*1.21*50 -> -0.40864392 | AC12: =SUM(Tabla1[[#This Row],[PRECIO $ BOLSA 50 KG (IVA INC) ]]+Tabla1[[#This Row],[COSTO FLETE $ BOLSA 50 KG (IVA INC)]]) -> 27562.473 | AD12: =-Tabla1[[#This Row],[PRECIO $ BOLSA 50 KG (IVA INC) ]]*(Tabla1[[#This Row],[TASA FINANCIACION MENSUAL]]/365)*Tabla1[[#This Row],[PLAZO ENTREGA VALORES]] -> 265.84352 | AE12: =SUM(Tabla1[[#This Row],[PRECIO $ BOLSA50 KG FOB TUCUMAN A PLAZO (IVA INC)]]+Tabla1[[#This Row],[GASTOS FINANCIEROS $ BOLSA 50 KG (IVA INC)]]) -> 27828.316 | AF12: GRANEL | AG12: RETIRA DE INGENIO | AH12: TUCUMAN | AI12: GDES CUENTAS | AJ12: =IFERROR(IF(Tabla1[[#This Row],[TIPO OPERACIÓN]]="INDUSTRIA",VLOOKUP(Tabla1[[#This Row],[FECHA OC]],'PRECIO CACTU'!A:B,2,FALSE),IF(Tabla1[[#This Row],[TIPO OPERACIÓN]]="GDES CUENTAS",VLOOKUP(Tabla1[[#This Row],[FECHA OC]],'PRECIO CACTU'!A:B,2,FALSE),IF(Tabla1[[#This Row],[TIPO OPERACIÓN]]="EXPO CHILE",VLOOKUP(Tabla1[[#This Row],[FECHA OC]],'PRECIO CACTU'!A:B,2,FALSE)/1.21,IF(Tabla1[[#This Row],[TIPO OPERACIÓN]]="TUC CTADO 2",VLOOKUP(Tabla1[[#This Row],[FECHA OC]],'PRECIO CACTU'!A:B,2,FALSE)/1.21,IF(Tabla1[[#This Row],[TIPO OPERACIÓN]]="TUC CTADO 1",VLOOKUP(Tabla1[[#This Row],[FECHA OC]],'PRECIO CACTU'!A:B,2,FALSE),""))))),"") -> 32515 | AK12: =SUM(Tabla1[[#This Row],[PRECIO $ BOLSA 50KG FOB CDO TUC (IVA INC)]]-Tabla1[[#This Row],[PRECIO REF $ BOLSA 50 KG CACTU (IVA INC)]]) -> -4686.6838 | AL12: =IFERROR(Tabla1[[#This Row],[PRECIO $ BOLSA 50KG FOB CDO TUC (IVA INC)]]/Tabla1[[#This Row],[PRECIO REF $ BOLSA 50 KG CACTU (IVA INC)]]-1,"") -> -0.14413913 | AM12: =+Tabla1[[#This Row],[DIF $ PRECIO NETO INDUSTRIA vs Neto TUCUMAN (IVA INC)]]*Tabla1[[#This Row],[Q Bolsas Equivalentes 50kg]] -> -2755770.1 | AN12: =Tabla1[[#This Row],[PRECIO REF $ BOLSA 50 KG CACTU (IVA INC)]]*Tabla1[[#This Row],[Q Bolsas Equivalentes 50kg]] -> 19118820 | AO12: =+Tabla1[[#This Row],[PRECIO $ BOLSA 50KG FOB CDO TUC (IVA INC)]]*Tabla1[[#This Row],[Q Bolsas Equivalentes 50kg]] -> 16363050 | AP12: 0.029 | AQ12: -68 | AS12: 0008-00005550 | AT12: =+Tabla1[[#This Row],[VENTA TOTAL $ (IVA INC) ]]-(SUM(Tabla1[[#This Row],[PENDIENTE DE ENTREGA]:[VALORES COBRADOS]])) -> 0 | AU12: =VLOOKUP(Tabla1[[#This Row],[FECHA OC]],'TIPO DE CAMBIO'!A:B,2,TRUE) -> 1446.301 | AV12: =+Tabla1[[#This Row],[SUBTOTAL]]/Tabla1[[#This Row],[TIPO DE CAMBIO]] -> 9261 | AX12: =IFERROR(Tabla1[[#This Row],[VENTA TOTAL USD A PLAZO EN CLIENTE (SIN IVA)]]*(1+Tabla1[[#This Row],[% IVA ]]),"") -> 9261 | AY12: =+Tabla1[[#This Row],[VENTA TOTAL USD A PLAZO EN CLIENTE (SIN IVA)]]/Tabla1[[#This Row],[KGS]]*1000 -> 315 | AZ12: 0 | BA12: =+Tabla1[[#This Row],[GASTOS FINANCIEROS $ BOLSA 50 KG (IVA INC)]]*20/Tabla1[[#This Row],[TIPO DE CAMBIO]] -> 3.6761852 | BB12: =+Tabla1[[#This Row],[PRECIO POR TN USD EN CLIENTE A PLAZO (SIN IVA)]]+Tabla1[[#This Row],[COSTO USD FLETE /TN (SIN IVA)]]+Tabla1[[#This Row],[COSTO FINANCIERO USD POR BOLSA 50KG (IVA INC)]] -> 318.67619 | BC12: 5
A13: 46143 | B13: 1 | C13: LEDESMA SAAI | D13: =+Tabla1[[#This Row],[FECHA Entrega]] -> 46173.388 | E13: 700000869 | F13: AZÚCAR CRUDO | G13: ENTREGADO | H13: 46173.388 | I13: =575*50 -> 28750 | J13: =0.315*Tabla1[[#This Row],[TIPO DE CAMBIO]] -> 455.58481 | K13: =+J13*I13 -> 13098063 | L13: =IF(Tabla1[[#This Row],[TIPO OPERACIÓN]]="INDUSTRIA",Tabla1[[#This Row],[SUBTOTAL]]*0.21,IF(Tabla1[[#This Row],[TIPO OPERACIÓN]]="GDES CUENTAS",Tabla1[[#This Row],[SUBTOTAL]]*0.21,IF(Tabla1[[#This Row],[TIPO OPERACIÓN]]="TUC CTADO 2","",IF(Tabla1[[#This Row],[TIPO OPERACIÓN]]="EXPO CHILE","",IF(Tabla1[[#This Row],[TIPO OPERACIÓN]]="TUC CTADO 1",Tabla1[[#This Row],[SUBTOTAL]]*0.21,""))))) -> 2750593.3 | M13: =SUM(K13:L13) -> 15848657 | O13: 0 | P13: 0 | Q13: =+Tabla1[[#This Row],[VENTA TOTAL $ (IVA INC) ]]-Tabla1[[#This Row],[PENDIENTE DE COBRO]] -> 15848657 | R13: =+Tabla1[[#This Row],[FECHA FC]]+Tabla1[[#This Row],[PLAZO ENTREGA VALORES]] -> 46051 | S13: =+Tabla1[[#This Row],[FECHA FC]]+Tabla1[[#This Row],[PLAZO PAGO (DIAS)]] -> 46173.388 | T13: =+S13-$U$2 -> -7.6118056 | U13: =+Tabla1[[#This Row],[FECHA OC]]-Tabla1[[#This Row],[FECHA Entrega]] -> -122.38819 | W13: =+Tabla1[[#This Row],[FECHA VTO VALORES]]+7 -> 46180.388 | Y13: 46051 | Z13: =Tabla1[[#This Row],[KGS]]/50 -> 575 | AA13: =IFERROR((IF(Tabla1[[#This Row],[TIPO OPERACIÓN]]="INDUSTRIA",Tabla1[[#This Row],[PRECIO $/ KG A PLAZO EN CLIENTE ( SIN IVA)]]*50*1.21,IF(Tabla1[[#This Row],[TIPO OPERACIÓN]]="TUC CTADO 2",Tabla1[[#This Row],[PRECIO $/ KG A PLAZO EN CLIENTE ( SIN IVA)]]*50,IF(Tabla1[[#This Row],[TIPO OPERACIÓN]]="EXPO CHILE",Tabla1[[#This Row],[PRECIO $/ KG A PLAZO EN CLIENTE ( SIN IVA)]]*50*1,IF(Tabla1[[#This Row],[TIPO OPERACIÓN]]="GDES CUENTAS",Tabla1[[#This Row],[PRECIO $/ KG A PLAZO EN CLIENTE ( SIN IVA)]]*50*1.21,IF(Tabla1[[#This Row],[TIPO OPERACIÓN]]="TUC CTADO 1",Tabla1[[#This Row],[PRECIO $/ KG A PLAZO EN CLIENTE ( SIN IVA)]]*50*1.21,"")))))),"") -> 27562.881 | AB13: =-Tabla1[[#This Row],[COSTO FLETE $ POR BOLSA 5O KG (SIN IVA)]]*1.21-Tabla1[[#This Row],[PRECIO $/ KG A PLAZO EN CLIENTE ( SIN IVA)]]*0.003*1.21*50 -> -0.40864392 | AC13: =SUM(Tabla1[[#This Row],[PRECIO $ BOLSA 50 KG (IVA INC) ]]+Tabla1[[#This Row],[COSTO FLETE $ BOLSA 50 KG (IVA INC)]]) -> 27562.473 | AD13: =-Tabla1[[#This Row],[PRECIO $ BOLSA 50 KG (IVA INC) ]]*(Tabla1[[#This Row],[TASA FINANCIACION MENSUAL]]/365)*Tabla1[[#This Row],[PLAZO ENTREGA VALORES]] -> 268.02128 | AE13: =SUM(Tabla1[[#This Row],[PRECIO $ BOLSA50 KG FOB TUCUMAN A PLAZO (IVA INC)]]+Tabla1[[#This Row],[GASTOS FINANCIEROS $ BOLSA 50 KG (IVA INC)]]) -> 27830.494 | AF13: GRANEL | AG13: RETIRA DE INGENIO | AH13: TUCUMAN | AI13: GDES CUENTAS | AJ13: =IFERROR(IF(Tabla1[[#This Row],[TIPO OPERACIÓN]]="INDUSTRIA",VLOOKUP(Tabla1[[#This Row],[FECHA OC]],'PRECIO CACTU'!A:B,2,FALSE),IF(Tabla1[[#This Row],[TIPO OPERACIÓN]]="GDES CUENTAS",VLOOKUP(Tabla1[[#This Row],[FECHA OC]],'PRECIO CACTU'!A:B,2,FALSE),IF(Tabla1[[#This Row],[TIPO OPERACIÓN]]="EXPO CHILE",VLOOKUP(Tabla1[[#This Row],[FECHA OC]],'PRECIO CACTU'!A:B,2,FALSE)/1.21,IF(Tabla1[[#This Row],[TIPO OPERACIÓN]]="TUC CTADO 2",VLOOKUP(Tabla1[[#This Row],[FECHA OC]],'PRECIO CACTU'!A:B,2,FALSE)/1.21,IF(Tabla1[[#This Row],[TIPO OPERACIÓN]]="TUC CTADO 1",VLOOKUP(Tabla1[[#This Row],[FECHA OC]],'PRECIO CACTU'!A:B,2,FALSE),""))))),"") -> 32515 | AK13: =SUM(Tabla1[[#This Row],[PRECIO $ BOLSA 50KG FOB CDO TUC (IVA INC)]]-Tabla1[[#This Row],[PRECIO REF $ BOLSA 50 KG CACTU (IVA INC)]]) -> -4684.5061 | AL13: =IFERROR(Tabla1[[#This Row],[PRECIO $ BOLSA 50KG FOB CDO TUC (IVA INC)]]/Tabla1[[#This Row],[PRECIO REF $ BOLSA 50 KG CACTU (IVA INC)]]-1,"") -> -0.14407215 | AM13: =+Tabla1[[#This Row],[DIF $ PRECIO NETO INDUSTRIA vs Neto TUCUMAN (IVA INC)]]*Tabla1[[#This Row],[Q Bolsas Equivalentes 50kg]] -> -2693591 | AN13: =Tabla1[[#This Row],[PRECIO REF $ BOLSA 50 KG CACTU (IVA INC)]]*Tabla1[[#This Row],[Q Bolsas Equivalentes 50kg]] -> 18696125 | AO13: =+Tabla1[[#This Row],[PRECIO $ BOLSA 50KG FOB CDO TUC (IVA INC)]]*Tabla1[[#This Row],[Q Bolsas Equivalentes 50kg]] -> 16002534 | AP13: 0.029 | AQ13: -68 | AS13: 0008-00005551 | AT13: =+Tabla1[[#This Row],[VENTA TOTAL $ (IVA INC) ]]-(SUM(Tabla1[[#This Row],[PENDIENTE DE ENTREGA]:[VALORES COBRADOS]])) -> 0 | AU13: =VLOOKUP(Tabla1[[#This Row],[FECHA OC]],'TIPO DE CAMBIO'!A:B,2,TRUE) -> 1446.301 | AV13: =+Tabla1[[#This Row],[SUBTOTAL]]/Tabla1[[#This Row],[TIPO DE CAMBIO]] -> 9056.25 | AX13: =IFERROR(Tabla1[[#This Row],[VENTA TOTAL USD A PLAZO EN CLIENTE (SIN IVA)]]*(1+Tabla1[[#This Row],[% IVA ]]),"") -> 9056.25 | AY13: =+Tabla1[[#This Row],[VENTA TOTAL USD A PLAZO EN CLIENTE (SIN IVA)]]/Tabla1[[#This Row],[KGS]]*1000 -> 315 | AZ13: 0 | BA13: =+Tabla1[[#This Row],[GASTOS FINANCIEROS $ BOLSA 50 KG (IVA INC)]]*20/Tabla1[[#This Row],[TIPO DE CAMBIO]] -> 3.7063001 | BB13: =+Tabla1[[#This Row],[PRECIO POR TN USD EN CLIENTE A PLAZO (SIN IVA)]]+Tabla1[[#This Row],[COSTO USD FLETE /TN (SIN IVA)]]+Tabla1[[#This Row],[COSTO FINANCIERO USD POR BOLSA 50KG (IVA INC)]] -> 318.7063 | BC13: 5
A14: 46143 | B14: 1 | C14: LEDESMA SAAI | D14: =+Tabla1[[#This Row],[FECHA Entrega]] -> 46173.847 | E14: 700000869 | F14: AZÚCAR CRUDO | G14: ENTREGADO | H14: 46173.847 | I14: =707*50 -> 35350 | J14: =0.315*Tabla1[[#This Row],[TIPO DE CAMBIO]] -> 455.58481 | K14: =+J14*I14 -> 16104923 | L14: =IF(Tabla1[[#This Row],[TIPO OPERACIÓN]]="INDUSTRIA",Tabla1[[#This Row],[SUBTOTAL]]*0.21,IF(Tabla1[[#This Row],[TIPO OPERACIÓN]]="GDES CUENTAS",Tabla1[[#This Row],[SUBTOTAL]]*0.21,IF(Tabla1[[#This Row],[TIPO OPERACIÓN]]="TUC CTADO 2","",IF(Tabla1[[#This Row],[TIPO OPERACIÓN]]="EXPO CHILE","",IF(Tabla1[[#This Row],[TIPO OPERACIÓN]]="TUC CTADO 1",Tabla1[[#This Row],[SUBTOTAL]]*0.21,""))))) -> 3382033.9 | M14: =SUM(K14:L14) -> 19486957 | O14: 0 | P14: 0 | Q14: =+Tabla1[[#This Row],[VENTA TOTAL $ (IVA INC) ]]-Tabla1[[#This Row],[PENDIENTE DE COBRO]] -> 19486957 | R14: =+Tabla1[[#This Row],[FECHA FC]]+Tabla1[[#This Row],[PLAZO ENTREGA VALORES]] -> 46051 | S14: =+Tabla1[[#This Row],[FECHA FC]]+Tabla1[[#This Row],[PLAZO PAGO (DIAS)]] -> 46173.847 | T14: =+S14-$U$2 -> -7.1534722 | U14: =+Tabla1[[#This Row],[FECHA OC]]-Tabla1[[#This Row],[FECHA Entrega]] -> -122.84653 | W14: =+Tabla1[[#This Row],[FECHA VTO VALORES]]+7 -> 46180.847 | Y14: 46051 | Z14: =Tabla1[[#This Row],[KGS]]/50 -> 707 | AA14: =IFERROR((IF(Tabla1[[#This Row],[TIPO OPERACIÓN]]="INDUSTRIA",Tabla1[[#This Row],[PRECIO $/ KG A PLAZO EN CLIENTE ( SIN IVA)]]*50*1.21,IF(Tabla1[[#This Row],[TIPO OPERACIÓN]]="TUC CTADO 2",Tabla1[[#This Row],[PRECIO $/ KG A PLAZO EN CLIENTE ( SIN IVA)]]*50,IF(Tabla1[[#This Row],[TIPO OPERACIÓN]]="EXPO CHILE",Tabla1[[#This Row],[PRECIO $/ KG A PLAZO EN CLIENTE ( SIN IVA)]]*50*1,IF(Tabla1[[#This Row],[TIPO OPERACIÓN]]="GDES CUENTAS",Tabla1[[#This Row],[PRECIO $/ KG A PLAZO EN CLIENTE ( SIN IVA)]]*50*1.21,IF(Tabla1[[#This Row],[TIPO OPERACIÓN]]="TUC CTADO 1",Tabla1[[#This Row],[PRECIO $/ KG A PLAZO EN CLIENTE ( SIN IVA)]]*50*1.21,"")))))),"") -> 27562.881 | AB14: =-Tabla1[[#This Row],[COSTO FLETE $ POR BOLSA 5O KG (SIN IVA)]]*1.21-Tabla1[[#This Row],[PRECIO $/ KG A PLAZO EN CLIENTE ( SIN IVA)]]*0.003*1.21*50 -> -0.40864392 | AC14: =SUM(Tabla1[[#This Row],[PRECIO $ BOLSA 50 KG (IVA INC) ]]+Tabla1[[#This Row],[COSTO FLETE $ BOLSA 50 KG (IVA INC)]]) -> 27562.473 | AD14: =-Tabla1[[#This Row],[PRECIO $ BOLSA 50 KG (IVA INC) ]]*(Tabla1[[#This Row],[TASA FINANCIACION MENSUAL]]/365)*Tabla1[[#This Row],[PLAZO ENTREGA VALORES]] -> 269.025 | AE14: =SUM(Tabla1[[#This Row],[PRECIO $ BOLSA50 KG FOB TUCUMAN A PLAZO (IVA INC)]]+Tabla1[[#This Row],[GASTOS FINANCIEROS $ BOLSA 50 KG (IVA INC)]]) -> 27831.498 | AF14: GRANEL | AG14: RETIRA DE INGENIO | AH14: TUCUMAN | AI14: GDES CUENTAS | AJ14: =IFERROR(IF(Tabla1[[#This Row],[TIPO OPERACIÓN]]="INDUSTRIA",VLOOKUP(Tabla1[[#This Row],[FECHA OC]],'PRECIO CACTU'!A:B,2,FALSE),IF(Tabla1[[#This Row],[TIPO OPERACIÓN]]="GDES CUENTAS",VLOOKUP(Tabla1[[#This Row],[FECHA OC]],'PRECIO CACTU'!A:B,2,FALSE),IF(Tabla1[[#This Row],[TIPO OPERACIÓN]]="EXPO CHILE",VLOOKUP(Tabla1[[#This Row],[FECHA OC]],'PRECIO CACTU'!A:B,2,FALSE)/1.21,IF(Tabla1[[#This Row],[TIPO OPERACIÓN]]="TUC CTADO 2",VLOOKUP(Tabla1[[#This Row],[FECHA OC]],'PRECIO CACTU'!A:B,2,FALSE)/1.21,IF(Tabla1[[#This Row],[TIPO OPERACIÓN]]="TUC CTADO 1",VLOOKUP(Tabla1[[#This Row],[FECHA OC]],'PRECIO CACTU'!A:B,2,FALSE),""))))),"") -> 32515 | AK14: =SUM(Tabla1[[#This Row],[PRECIO $ BOLSA 50KG FOB CDO TUC (IVA INC)]]-Tabla1[[#This Row],[PRECIO REF $ BOLSA 50 KG CACTU (IVA INC)]]) -> -4683.5023 | AL14: =IFERROR(Tabla1[[#This Row],[PRECIO $ BOLSA 50KG FOB CDO TUC (IVA INC)]]/Tabla1[[#This Row],[PRECIO REF $ BOLSA 50 KG CACTU (IVA INC)]]-1,"") -> -0.14404128 | AM14: =+Tabla1[[#This Row],[DIF $ PRECIO NETO INDUSTRIA vs Neto TUCUMAN (IVA INC)]]*Tabla1[[#This Row],[Q Bolsas Equivalentes 50kg]] -> -3311236.2 | AN14: =Tabla1[[#This Row],[PRECIO REF $ BOLSA 50 KG CACTU (IVA INC)]]*Tabla1[[#This Row],[Q Bolsas Equivalentes 50kg]] -> 22988105 | AO14: =+Tabla1[[#This Row],[PRECIO $ BOLSA 50KG FOB CDO TUC (IVA INC)]]*Tabla1[[#This Row],[Q Bolsas Equivalentes 50kg]] -> 19676869 | AP14: 0.029 | AQ14: -68 | AS14: 0008-00005561 | AT14: =+Tabla1[[#This Row],[VENTA TOTAL $ (IVA INC) ]]-(SUM(Tabla1[[#This Row],[PENDIENTE DE ENTREGA]:[VALORES COBRADOS]])) -> 0 | AU14: =VLOOKUP(Tabla1[[#This Row],[FECHA OC]],'TIPO DE CAMBIO'!A:B,2,TRUE) -> 1446.301 | AV14: =+Tabla1[[#This Row],[SUBTOTAL]]/Tabla1[[#This Row],[TIPO DE CAMBIO]] -> 11135.25 | AX14: =IFERROR(Tabla1[[#This Row],[VENTA TOTAL USD A PLAZO EN CLIENTE (SIN IVA)]]*(1+Tabla1[[#This Row],[% IVA ]]),"") -> 11135.25 | AY14: =+Tabla1[[#This Row],[VENTA TOTAL USD A PLAZO EN CLIENTE (SIN IVA)]]/Tabla1[[#This Row],[KGS]]*1000 -> 315 | AZ14: 0 | BA14: =+Tabla1[[#This Row],[GASTOS FINANCIEROS $ BOLSA 50 KG (IVA INC)]]*20/Tabla1[[#This Row],[TIPO DE CAMBIO]] -> 3.7201799 | BB14: =+Tabla1[[#This Row],[PRECIO POR TN USD EN CLIENTE A PLAZO (SIN IVA)]]+Tabla1[[#This Row],[COSTO USD FLETE /TN (SIN IVA)]]+Tabla1[[#This Row],[COSTO FINANCIERO USD POR BOLSA 50KG (IVA INC)]] -> 318.72018 | BC14: 5
A15: 46143 | B15: 1 | C15: LEDESMA SAAI | D15: =+Tabla1[[#This Row],[FECHA Entrega]] -> 46173.91 | E15: 700000869 | F15: AZÚCAR CRUDO | G15: ENTREGADO | H15: 46173.91 | I15: =591*50 -> 29550 | J15: =0.315*Tabla1[[#This Row],[TIPO DE CAMBIO]] -> 455.58481 | K15: =+J15*I15 -> 13462531 | L15: =IF(Tabla1[[#This Row],[TIPO OPERACIÓN]]="INDUSTRIA",Tabla1[[#This Row],[SUBTOTAL]]*0.21,IF(Tabla1[[#This Row],[TIPO OPERACIÓN]]="GDES CUENTAS",Tabla1[[#This Row],[SUBTOTAL]]*0.21,IF(Tabla1[[#This Row],[TIPO OPERACIÓN]]="TUC CTADO 2","",IF(Tabla1[[#This Row],[TIPO OPERACIÓN]]="EXPO CHILE","",IF(Tabla1[[#This Row],[TIPO OPERACIÓN]]="TUC CTADO 1",Tabla1[[#This Row],[SUBTOTAL]]*0.21,""))))) -> 2827131.6 | M15: =SUM(K15:L15) -> 16289663 | O15: 0 | P15: 0 | Q15: =+Tabla1[[#This Row],[VENTA TOTAL $ (IVA INC) ]]-Tabla1[[#This Row],[PENDIENTE DE COBRO]] -> 16289663 | R15: =+Tabla1[[#This Row],[FECHA FC]]+Tabla1[[#This Row],[PLAZO ENTREGA VALORES]] -> 46051 | S15: =+Tabla1[[#This Row],[FECHA FC]]+Tabla1[[#This Row],[PLAZO PAGO (DIAS)]] -> 46173.91 | T15: =+S15-$U$2 -> -7.0902778 | U15: =+Tabla1[[#This Row],[FECHA OC]]-Tabla1[[#This Row],[FECHA Entrega]] -> -122.90972 | W15: =+Tabla1[[#This Row],[FECHA VTO VALORES]]+7 -> 46180.91 | Y15: 46051 | Z15: =Tabla1[[#This Row],[KGS]]/50 -> 591 | AA15: =IFERROR((IF(Tabla1[[#This Row],[TIPO OPERACIÓN]]="INDUSTRIA",Tabla1[[#This Row],[PRECIO $/ KG A PLAZO EN CLIENTE ( SIN IVA)]]*50*1.21,IF(Tabla1[[#This Row],[TIPO OPERACIÓN]]="TUC CTADO 2",Tabla1[[#This Row],[PRECIO $/ KG A PLAZO EN CLIENTE ( SIN IVA)]]*50,IF(Tabla1[[#This Row],[TIPO OPERACIÓN]]="EXPO CHILE",Tabla1[[#This Row],[PRECIO $/ KG A PLAZO EN CLIENTE ( SIN IVA)]]*50*1,IF(Tabla1[[#This Row],[TIPO OPERACIÓN]]="GDES CUENTAS",Tabla1[[#This Row],[PRECIO $/ KG A PLAZO EN CLIENTE ( SIN IVA)]]*50*1.21,IF(Tabla1[[#This Row],[TIPO OPERACIÓN]]="TUC CTADO 1",Tabla1[[#This Row],[PRECIO $/ KG A PLAZO EN CLIENTE ( SIN IVA)]]*50*1.21,"")))))),"") -> 27562.881 | AB15: =-Tabla1[[#This Row],[COSTO FLETE $ POR BOLSA 5O KG (SIN IVA)]]*1.21-Tabla1[[#This Row],[PRECIO $/ KG A PLAZO EN CLIENTE ( SIN IVA)]]*0.003*1.21*50 -> -0.40864392 | AC15: =SUM(Tabla1[[#This Row],[PRECIO $ BOLSA 50 KG (IVA INC) ]]+Tabla1[[#This Row],[COSTO FLETE $ BOLSA 50 KG (IVA INC)]]) -> 27562.473 | AD15: =-Tabla1[[#This Row],[PRECIO $ BOLSA 50 KG (IVA INC) ]]*(Tabla1[[#This Row],[TASA FINANCIACION MENSUAL]]/365)*Tabla1[[#This Row],[PLAZO ENTREGA VALORES]] -> 269.16339 | AE15: =SUM(Tabla1[[#This Row],[PRECIO $ BOLSA50 KG FOB TUCUMAN A PLAZO (IVA INC)]]+Tabla1[[#This Row],[GASTOS FINANCIEROS $ BOLSA 50 KG (IVA INC)]]) -> 27831.636 | AF15: GRANEL | AG15: RETIRA DE INGENIO | AH15: TUCUMAN | AI15: GDES CUENTAS | AJ15: =IFERROR(IF(Tabla1[[#This Row],[TIPO OPERACIÓN]]="INDUSTRIA",VLOOKUP(Tabla1[[#This Row],[FECHA OC]],'PRECIO CACTU'!A:B,2,FALSE),IF(Tabla1[[#This Row],[TIPO OPERACIÓN]]="GDES CUENTAS",VLOOKUP(Tabla1[[#This Row],[FECHA OC]],'PRECIO CACTU'!A:B,2,FALSE),IF(Tabla1[[#This Row],[TIPO OPERACIÓN]]="EXPO CHILE",VLOOKUP(Tabla1[[#This Row],[FECHA OC]],'PRECIO CACTU'!A:B,2,FALSE)/1.21,IF(Tabla1[[#This Row],[TIPO OPERACIÓN]]="TUC CTADO 2",VLOOKUP(Tabla1[[#This Row],[FECHA OC]],'PRECIO CACTU'!A:B,2,FALSE)/1.21,IF(Tabla1[[#This Row],[TIPO OPERACIÓN]]="TUC CTADO 1",VLOOKUP(Tabla1[[#This Row],[FECHA OC]],'PRECIO CACTU'!A:B,2,FALSE),""))))),"") -> 32515 | AK15: =SUM(Tabla1[[#This Row],[PRECIO $ BOLSA 50KG FOB CDO TUC (IVA INC)]]-Tabla1[[#This Row],[PRECIO REF $ BOLSA 50 KG CACTU (IVA INC)]]) -> -4683.3639 | AL15: =IFERROR(Tabla1[[#This Row],[PRECIO $ BOLSA 50KG FOB CDO TUC (IVA INC)]]/Tabla1[[#This Row],[PRECIO REF $ BOLSA 50 KG CACTU (IVA INC)]]-1,"") -> -0.14403703 | AM15: =+Tabla1[[#This Row],[DIF $ PRECIO NETO INDUSTRIA vs Neto TUCUMAN (IVA INC)]]*Tabla1[[#This Row],[Q Bolsas Equivalentes 50kg]] -> -2767868.1 | AN15: =Tabla1[[#This Row],[PRECIO REF $ BOLSA 50 KG CACTU (IVA INC)]]*Tabla1[[#This Row],[Q Bolsas Equivalentes 50kg]] -> 19216365 | AO15: =+Tabla1[[#This Row],[PRECIO $ BOLSA 50KG FOB CDO TUC (IVA INC)]]*Tabla1[[#This Row],[Q Bolsas Equivalentes 50kg]] -> 16448497 | AP15: 0.029 | AQ15: -68 | AS15: 0008-00005562 | AT15: =+Tabla1[[#This Row],[VENTA TOTAL $ (IVA INC) ]]-(SUM(Tabla1[[#This Row],[PENDIENTE DE ENTREGA]:[VALORES COBRADOS]])) -> 0 | AU15: =VLOOKUP(Tabla1[[#This Row],[FECHA OC]],'TIPO DE CAMBIO'!A:B,2,TRUE) -> 1446.301 | AV15: =+Tabla1[[#This Row],[SUBTOTAL]]/Tabla1[[#This Row],[TIPO DE CAMBIO]] -> 9308.25 | AX15: =IFERROR(Tabla1[[#This Row],[VENTA TOTAL USD A PLAZO EN CLIENTE (SIN IVA)]]*(1+Tabla1[[#This Row],[% IVA ]]),"") -> 9308.25 | AY15: =+Tabla1[[#This Row],[VENTA TOTAL USD A PLAZO EN CLIENTE (SIN IVA)]]/Tabla1[[#This Row],[KGS]]*1000 -> 315 | AZ15: 0 | BA15: =+Tabla1[[#This Row],[GASTOS FINANCIEROS $ BOLSA 50 KG (IVA INC)]]*20/Tabla1[[#This Row],[TIPO DE CAMBIO]] -> 3.7220936 | BB15: =+Tabla1[[#This Row],[PRECIO POR TN USD EN CLIENTE A PLAZO (SIN IVA)]]+Tabla1[[#This Row],[COSTO USD FLETE /TN (SIN IVA)]]+Tabla1[[#This Row],[COSTO FINANCIERO USD POR BOLSA 50KG (IVA INC)]] -> 318.72209 | BC15: 5
A16: 46143 | B16: 1 | C16: LEDESMA SAAI | D16: =+Tabla1[[#This Row],[FECHA Entrega]] -> 46173.927 | E16: 700000869 | F16: AZÚCAR CRUDO | G16: ENTREGADO | H16: 46173.927 | I16: =597*50 -> 29850 | J16: =0.315*Tabla1[[#This Row],[TIPO DE CAMBIO]] -> 455.58481 | K16: =+J16*I16 -> 13599207 | L16: =IF(Tabla1[[#This Row],[TIPO OPERACIÓN]]="INDUSTRIA",Tabla1[[#This Row],[SUBTOTAL]]*0.21,IF(Tabla1[[#This Row],[TIPO OPERACIÓN]]="GDES CUENTAS",Tabla1[[#This Row],[SUBTOTAL]]*0.21,IF(Tabla1[[#This Row],[TIPO OPERACIÓN]]="TUC CTADO 2","",IF(Tabla1[[#This Row],[TIPO OPERACIÓN]]="EXPO CHILE","",IF(Tabla1[[#This Row],[TIPO OPERACIÓN]]="TUC CTADO 1",Tabla1[[#This Row],[SUBTOTAL]]*0.21,""))))) -> 2855833.4 | M16: =SUM(K16:L16) -> 16455040 | O16: 0 | P16: 0 | Q16: =+Tabla1[[#This Row],[VENTA TOTAL $ (IVA INC) ]]-Tabla1[[#This Row],[PENDIENTE DE COBRO]] -> 16455040 | R16: =+Tabla1[[#This Row],[FECHA FC]]+Tabla1[[#This Row],[PLAZO ENTREGA VALORES]] -> 46051 | S16: =+Tabla1[[#This Row],[FECHA FC]]+Tabla1[[#This Row],[PLAZO PAGO (DIAS)]] -> 46173.927 | T16: =+S16-$U$2 -> -7.0729167 | U16: =+Tabla1[[#This Row],[FECHA OC]]-Tabla1[[#This Row],[FECHA Entrega]] -> -122.92708 | W16: =+Tabla1[[#This Row],[FECHA VTO VALORES]]+7 -> 46180.927 | Y16: 46051 | Z16: =Tabla1[[#This Row],[KGS]]/50 -> 597 | AA16: =IFERROR((IF(Tabla1[[#This Row],[TIPO OPERACIÓN]]="INDUSTRIA",Tabla1[[#This Row],[PRECIO $/ KG A PLAZO EN CLIENTE ( SIN IVA)]]*50*1.21,IF(Tabla1[[#This Row],[TIPO OPERACIÓN]]="TUC CTADO 2",Tabla1[[#This Row],[PRECIO $/ KG A PLAZO EN CLIENTE ( SIN IVA)]]*50,IF(Tabla1[[#This Row],[TIPO OPERACIÓN]]="EXPO CHILE",Tabla1[[#This Row],[PRECIO $/ KG A PLAZO EN CLIENTE ( SIN IVA)]]*50*1,IF(Tabla1[[#This Row],[TIPO OPERACIÓN]]="GDES CUENTAS",Tabla1[[#This Row],[PRECIO $/ KG A PLAZO EN CLIENTE ( SIN IVA)]]*50*1.21,IF(Tabla1[[#This Row],[TIPO OPERACIÓN]]="TUC CTADO 1",Tabla1[[#This Row],[PRECIO $/ KG A PLAZO EN CLIENTE ( SIN IVA)]]*50*1.21,"")))))),"") -> 27562.881 | AB16: =-Tabla1[[#This Row],[COSTO FLETE $ POR BOLSA 5O KG (SIN IVA)]]*1.21-Tabla1[[#This Row],[PRECIO $/ KG A PLAZO EN CLIENTE ( SIN IVA)]]*0.003*1.21*50 -> -0.40864392 | AC16: =SUM(Tabla1[[#This Row],[PRECIO $ BOLSA 50 KG (IVA INC) ]]+Tabla1[[#This Row],[COSTO FLETE $ BOLSA 50 KG (IVA INC)]]) -> 27562.473 | AD16: =-Tabla1[[#This Row],[PRECIO $ BOLSA 50 KG (IVA INC) ]]*(Tabla1[[#This Row],[TASA FINANCIACION MENSUAL]]/365)*Tabla1[[#This Row],[PLAZO ENTREGA VALORES]] -> 269.20141 | AE16: =SUM(Tabla1[[#This Row],[PRECIO $ BOLSA50 KG FOB TUCUMAN A PLAZO (IVA INC)]]+Tabla1[[#This Row],[GASTOS FINANCIEROS $ BOLSA 50 KG (IVA INC)]]) -> 27831.674 | AF16: GRANEL | AG16: RETIRA DE INGENIO | AH16: TUCUMAN | AI16: GDES CUENTAS | AJ16: =IFERROR(IF(Tabla1[[#This Row],[TIPO OPERACIÓN]]="INDUSTRIA",VLOOKUP(Tabla1[[#This Row],[FECHA OC]],'PRECIO CACTU'!A:B,2,FALSE),IF(Tabla1[[#This Row],[TIPO OPERACIÓN]]="GDES CUENTAS",VLOOKUP(Tabla1[[#This Row],[FECHA OC]],'PRECIO CACTU'!A:B,2,FALSE),IF(Tabla1[[#This Row],[TIPO OPERACIÓN]]="EXPO CHILE",VLOOKUP(Tabla1[[#This Row],[FECHA OC]],'PRECIO CACTU'!A:B,2,FALSE)/1.21,IF(Tabla1[[#This Row],[TIPO OPERACIÓN]]="TUC CTADO 2",VLOOKUP(Tabla1[[#This Row],[FECHA OC]],'PRECIO CACTU'!A:B,2,FALSE)/1.21,IF(Tabla1[[#This Row],[TIPO OPERACIÓN]]="TUC CTADO 1",VLOOKUP(Tabla1[[#This Row],[FECHA OC]],'PRECIO CACTU'!A:B,2,FALSE),""))))),"") -> 32515 | AK16: =SUM(Tabla1[[#This Row],[PRECIO $ BOLSA 50KG FOB CDO TUC (IVA INC)]]-Tabla1[[#This Row],[PRECIO REF $ BOLSA 50 KG CACTU (IVA INC)]]) -> -4683.3259 | AL16: =IFERROR(Tabla1[[#This Row],[PRECIO $ BOLSA 50KG FOB CDO TUC (IVA INC)]]/Tabla1[[#This Row],[PRECIO REF $ BOLSA 50 KG CACTU (IVA INC)]]-1,"") -> -0.14403586 | AM16: =+Tabla1[[#This Row],[DIF $ PRECIO NETO INDUSTRIA vs Neto TUCUMAN (IVA INC)]]*Tabla1[[#This Row],[Q Bolsas Equivalentes 50kg]] -> -2795945.6 | AN16: =Tabla1[[#This Row],[PRECIO REF $ BOLSA 50 KG CACTU (IVA INC)]]*Tabla1[[#This Row],[Q Bolsas Equivalentes 50kg]] -> 19411455 | AO16: =+Tabla1[[#This Row],[PRECIO $ BOLSA 50KG FOB CDO TUC (IVA INC)]]*Tabla1[[#This Row],[Q Bolsas Equivalentes 50kg]] -> 16615509 | AP16: 0.029 | AQ16: -68 | AS16: 0008-00005563 | AT16: =+Tabla1[[#This Row],[VENTA TOTAL $ (IVA INC) ]]-(SUM(Tabla1[[#This Row],[PENDIENTE DE ENTREGA]:[VALORES COBRADOS]])) -> 0 | AU16: =VLOOKUP(Tabla1[[#This Row],[FECHA OC]],'TIPO DE CAMBIO'!A:B,2,TRUE) -> 1446.301 | AV16: =+Tabla1[[#This Row],[SUBTOTAL]]/Tabla1[[#This Row],[TIPO DE CAMBIO]] -> 9402.75 | AX16: =IFERROR(Tabla1[[#This Row],[VENTA TOTAL USD A PLAZO EN CLIENTE (SIN IVA)]]*(1+Tabla1[[#This Row],[% IVA ]]),"") -> 9402.75 | AY16: =+Tabla1[[#This Row],[VENTA TOTAL USD A PLAZO EN CLIENTE (SIN IVA)]]/Tabla1[[#This Row],[KGS]]*1000 -> 315 | AZ16: 0 | BA16: =+Tabla1[[#This Row],[GASTOS FINANCIEROS $ BOLSA 50 KG (IVA INC)]]*20/Tabla1[[#This Row],[TIPO DE CAMBIO]] -> 3.7226194 | BB16: =+Tabla1[[#This Row],[PRECIO POR TN USD EN CLIENTE A PLAZO (SIN IVA)]]+Tabla1[[#This Row],[COSTO USD FLETE /TN (SIN IVA)]]+Tabla1[[#This Row],[COSTO FINANCIERO USD POR BOLSA 50KG (IVA INC)]] -> 318.72262 | BC16: 5
A17: 46143 | B17: 1 | C17: LEDESMA SAAI | D17: =+Tabla1[[#This Row],[FECHA Entrega]] -> 46175.831 | E17: 700000869 | F17: AZÚCAR CRUDO | G17: ENTREGADO | H17: 46175.831 | I17: =719*50 -> 35950 | J17: =0.315*Tabla1[[#This Row],[TIPO DE CAMBIO]] -> 455.58481 | K17: =+J17*I17 -> 16378274 | L17: =IF(Tabla1[[#This Row],[TIPO OPERACIÓN]]="INDUSTRIA",Tabla1[[#This Row],[SUBTOTAL]]*0.21,IF(Tabla1[[#This Row],[TIPO OPERACIÓN]]="GDES CUENTAS",Tabla1[[#This Row],[SUBTOTAL]]*0.21,IF(Tabla1[[#This Row],[TIPO OPERACIÓN]]="TUC CTADO 2","",IF(Tabla1[[#This Row],[TIPO OPERACIÓN]]="EXPO CHILE","",IF(Tabla1[[#This Row],[TIPO OPERACIÓN]]="TUC CTADO 1",Tabla1[[#This Row],[SUBTOTAL]]*0.21,""))))) -> 3439437.6 | M17: =SUM(K17:L17) -> 19817712 | O17: 0 | P17: 0 | Q17: =+Tabla1[[#This Row],[VENTA TOTAL $ (IVA INC) ]]-Tabla1[[#This Row],[PENDIENTE DE COBRO]] -> 19817712 | R17: =+Tabla1[[#This Row],[FECHA FC]]+Tabla1[[#This Row],[PLAZO ENTREGA VALORES]] -> 46051 | S17: =+Tabla1[[#This Row],[FECHA FC]]+Tabla1[[#This Row],[PLAZO PAGO (DIAS)]] -> 46175.831 | T17: =+S17-$U$2 -> -5.16875 | U17: =+Tabla1[[#This Row],[FECHA OC]]-Tabla1[[#This Row],[FECHA Entrega]] -> -124.83125 | W17: =+Tabla1[[#This Row],[FECHA VTO VALORES]]+7 -> 46182.831 | Y17: 46051 | Z17: =Tabla1[[#This Row],[KGS]]/50 -> 719 | AA17: =IFERROR((IF(Tabla1[[#This Row],[TIPO OPERACIÓN]]="INDUSTRIA",Tabla1[[#This Row],[PRECIO $/ KG A PLAZO EN CLIENTE ( SIN IVA)]]*50*1.21,IF(Tabla1[[#This Row],[TIPO OPERACIÓN]]="TUC CTADO 2",Tabla1[[#This Row],[PRECIO $/ KG A PLAZO EN CLIENTE ( SIN IVA)]]*50,IF(Tabla1[[#This Row],[TIPO OPERACIÓN]]="EXPO CHILE",Tabla1[[#This Row],[PRECIO $/ KG A PLAZO EN CLIENTE ( SIN IVA)]]*50*1,IF(Tabla1[[#This Row],[TIPO OPERACIÓN]]="GDES CUENTAS",Tabla1[[#This Row],[PRECIO $/ KG A PLAZO EN CLIENTE ( SIN IVA)]]*50*1.21,IF(Tabla1[[#This Row],[TIPO OPERACIÓN]]="TUC CTADO 1",Tabla1[[#This Row],[PRECIO $/ KG A PLAZO EN CLIENTE ( SIN IVA)]]*50*1.21,"")))))),"") -> 27562.881 | AB17: =-Tabla1[[#This Row],[COSTO FLETE $ POR BOLSA 5O KG (SIN IVA)]]*1.21-Tabla1[[#This Row],[PRECIO $/ KG A PLAZO EN CLIENTE ( SIN IVA)]]*0.003*1.21*50 -> -0.40864392 | AC17: =SUM(Tabla1[[#This Row],[PRECIO $ BOLSA 50 KG (IVA INC) ]]+Tabla1[[#This Row],[COSTO FLETE $ BOLSA 50 KG (IVA INC)]]) -> 27562.473 | AD17: =-Tabla1[[#This Row],[PRECIO $ BOLSA 50 KG (IVA INC) ]]*(Tabla1[[#This Row],[TASA FINANCIACION MENSUAL]]/365)*Tabla1[[#This Row],[PLAZO ENTREGA VALORES]] -> 273.37139 | AE17: =SUM(Tabla1[[#This Row],[PRECIO $ BOLSA50 KG FOB TUCUMAN A PLAZO (IVA INC)]]+Tabla1[[#This Row],[GASTOS FINANCIEROS $ BOLSA 50 KG (IVA INC)]]) -> 27835.844 | AF17: GRANEL | AG17: RETIRA DE INGENIO | AH17: TUCUMAN | AI17: GDES CUENTAS | AJ17: =IFERROR(IF(Tabla1[[#This Row],[TIPO OPERACIÓN]]="INDUSTRIA",VLOOKUP(Tabla1[[#This Row],[FECHA OC]],'PRECIO CACTU'!A:B,2,FALSE),IF(Tabla1[[#This Row],[TIPO OPERACIÓN]]="GDES CUENTAS",VLOOKUP(Tabla1[[#This Row],[FECHA OC]],'PRECIO CACTU'!A:B,2,FALSE),IF(Tabla1[[#This Row],[TIPO OPERACIÓN]]="EXPO CHILE",VLOOKUP(Tabla1[[#This Row],[FECHA OC]],'PRECIO CACTU'!A:B,2,FALSE)/1.21,IF(Tabla1[[#This Row],[TIPO OPERACIÓN]]="TUC CTADO 2",VLOOKUP(Tabla1[[#This Row],[FECHA OC]],'PRECIO CACTU'!A:B,2,FALSE)/1.21,IF(Tabla1[[#This Row],[TIPO OPERACIÓN]]="TUC CTADO 1",VLOOKUP(Tabla1[[#This Row],[FECHA OC]],'PRECIO CACTU'!A:B,2,FALSE),""))))),"") -> 32515 | AK17: =SUM(Tabla1[[#This Row],[PRECIO $ BOLSA 50KG FOB CDO TUC (IVA INC)]]-Tabla1[[#This Row],[PRECIO REF $ BOLSA 50 KG CACTU (IVA INC)]]) -> -4679.1559 | AL17: =IFERROR(Tabla1[[#This Row],[PRECIO $ BOLSA 50KG FOB CDO TUC (IVA INC)]]/Tabla1[[#This Row],[PRECIO REF $ BOLSA 50 KG CACTU (IVA INC)]]-1,"") -> -0.14390761 | AM17: =+Tabla1[[#This Row],[DIF $ PRECIO NETO INDUSTRIA vs Neto TUCUMAN (IVA INC)]]*Tabla1[[#This Row],[Q Bolsas Equivalentes 50kg]] -> -3364313.1 | AN17: =Tabla1[[#This Row],[PRECIO REF $ BOLSA 50 KG CACTU (IVA INC)]]*Tabla1[[#This Row],[Q Bolsas Equivalentes 50kg]] -> 23378285 | AO17: =+Tabla1[[#This Row],[PRECIO $ BOLSA 50KG FOB CDO TUC (IVA INC)]]*Tabla1[[#This Row],[Q Bolsas Equivalentes 50kg]] -> 20013972 | AP17: 0.029 | AQ17: -68 | AS17: 0008-00005575 | AT17: =+Tabla1[[#This Row],[VENTA TOTAL $ (IVA INC) ]]-(SUM(Tabla1[[#This Row],[PENDIENTE DE ENTREGA]:[VALORES COBRADOS]])) -> 0 | AU17: =VLOOKUP(Tabla1[[#This Row],[FECHA OC]],'TIPO DE CAMBIO'!A:B,2,TRUE) -> 1446.301 | AV17: =+Tabla1[[#This Row],[SUBTOTAL]]/Tabla1[[#This Row],[TIPO DE CAMBIO]] -> 11324.25 | AX17: =IFERROR(Tabla1[[#This Row],[VENTA TOTAL USD A PLAZO EN CLIENTE (SIN IVA)]]*(1+Tabla1[[#This Row],[% IVA ]]),"") -> 11324.25 | AY17: =+Tabla1[[#This Row],[VENTA TOTAL USD A PLAZO EN CLIENTE (SIN IVA)]]/Tabla1[[#This Row],[KGS]]*1000 -> 315 | AZ17: 0 | BA17: =+Tabla1[[#This Row],[GASTOS FINANCIEROS $ BOLSA 50 KG (IVA INC)]]*20/Tabla1[[#This Row],[TIPO DE CAMBIO]] -> 3.7802836 | BB17: =+Tabla1[[#This Row],[PRECIO POR TN USD EN CLIENTE A PLAZO (SIN IVA)]]+Tabla1[[#This Row],[COSTO USD FLETE /TN (SIN IVA)]]+Tabla1[[#This Row],[COSTO FINANCIERO USD POR BOLSA 50KG (IVA INC)]] -> 318.78028 | BC17: 5
A18: 46143 | B18: 1 | C18: LEDESMA SAAI | D18: =+Tabla1[[#This Row],[FECHA Entrega]] -> 46175.833 | E18: 700000869 | F18: AZÚCAR CRUDO | G18: ENTREGADO | H18: 46175.833 | I18: =573*50 -> 28650 | J18: =0.315*Tabla1[[#This Row],[TIPO DE CAMBIO]] -> 455.58481 | K18: =+J18*I18 -> 13052505 | L18: =IF(Tabla1[[#This Row],[TIPO OPERACIÓN]]="INDUSTRIA",Tabla1[[#This Row],[SUBTOTAL]]*0.21,IF(Tabla1[[#This Row],[TIPO OPERACIÓN]]="GDES CUENTAS",Tabla1[[#This Row],[SUBTOTAL]]*0.21,IF(Tabla1[[#This Row],[TIPO OPERACIÓN]]="TUC CTADO 2","",IF(Tabla1[[#This Row],[TIPO OPERACIÓN]]="EXPO CHILE","",IF(Tabla1[[#This Row],[TIPO OPERACIÓN]]="TUC CTADO 1",Tabla1[[#This Row],[SUBTOTAL]]*0.21,""))))) -> 2741026 | M18: =SUM(K18:L18) -> 15793531 | O18: 0 | P18: 0 | Q18: =+Tabla1[[#This Row],[VENTA TOTAL $ (IVA INC) ]]-Tabla1[[#This Row],[PENDIENTE DE COBRO]] -> 15793531 | R18: =+Tabla1[[#This Row],[FECHA FC]]+Tabla1[[#This Row],[PLAZO ENTREGA VALORES]] -> 46051 | S18: =+Tabla1[[#This Row],[FECHA FC]]+Tabla1[[#This Row],[PLAZO PAGO (DIAS)]] -> 46175.833 | T18: =+S18-$U$2 -> -5.1666667 | U18: =+Tabla1[[#This Row],[FECHA OC]]-Tabla1[[#This Row],[FECHA Entrega]] -> -124.83333 | W18: =+Tabla1[[#This Row],[FECHA VTO VALORES]]+7 -> 46182.833 | Y18: 46051 | Z18: =Tabla1[[#This Row],[KGS]]/50 -> 573 | AA18: =IFERROR((IF(Tabla1[[#This Row],[TIPO OPERACIÓN]]="INDUSTRIA",Tabla1[[#This Row],[PRECIO $/ KG A PLAZO EN CLIENTE ( SIN IVA)]]*50*1.21,IF(Tabla1[[#This Row],[TIPO OPERACIÓN]]="TUC CTADO 2",Tabla1[[#This Row],[PRECIO $/ KG A PLAZO EN CLIENTE ( SIN IVA)]]*50,IF(Tabla1[[#This Row],[TIPO OPERACIÓN]]="EXPO CHILE",Tabla1[[#This Row],[PRECIO $/ KG A PLAZO EN CLIENTE ( SIN IVA)]]*50*1,IF(Tabla1[[#This Row],[TIPO OPERACIÓN]]="GDES CUENTAS",Tabla1[[#This Row],[PRECIO $/ KG A PLAZO EN CLIENTE ( SIN IVA)]]*50*1.21,IF(Tabla1[[#This Row],[TIPO OPERACIÓN]]="TUC CTADO 1",Tabla1[[#This Row],[PRECIO $/ KG A PLAZO EN CLIENTE ( SIN IVA)]]*50*1.21,"")))))),"") -> 27562.881 | AB18: =-Tabla1[[#This Row],[COSTO FLETE $ POR BOLSA 5O KG (SIN IVA)]]*1.21-Tabla1[[#This Row],[PRECIO $/ KG A PLAZO EN CLIENTE ( SIN IVA)]]*0.003*1.21*50 -> -0.40864392 | AC18: =SUM(Tabla1[[#This Row],[PRECIO $ BOLSA 50 KG (IVA INC) ]]+Tabla1[[#This Row],[COSTO FLETE $ BOLSA 50 KG (IVA INC)]]) -> 27562.473 | AD18: =-Tabla1[[#This Row],[PRECIO $ BOLSA 50 KG (IVA INC) ]]*(Tabla1[[#This Row],[TASA FINANCIACION MENSUAL]]/365)*Tabla1[[#This Row],[PLAZO ENTREGA VALORES]] -> 273.37596 | AE18: =SUM(Tabla1[[#This Row],[PRECIO $ BOLSA50 KG FOB TUCUMAN A PLAZO (IVA INC)]]+Tabla1[[#This Row],[GASTOS FINANCIEROS $ BOLSA 50 KG (IVA INC)]]) -> 27835.849 | AF18: GRANEL | AG18: RETIRA DE INGENIO | AH18: TUCUMAN | AI18: GDES CUENTAS | AJ18: =IFERROR(IF(Tabla1[[#This Row],[TIPO OPERACIÓN]]="INDUSTRIA",VLOOKUP(Tabla1[[#This Row],[FECHA OC]],'PRECIO CACTU'!A:B,2,FALSE),IF(Tabla1[[#This Row],[TIPO OPERACIÓN]]="GDES CUENTAS",VLOOKUP(Tabla1[[#This Row],[FECHA OC]],'PRECIO CACTU'!A:B,2,FALSE),IF(Tabla1[[#This Row],[TIPO OPERACIÓN]]="EXPO CHILE",VLOOKUP(Tabla1[[#This Row],[FECHA OC]],'PRECIO CACTU'!A:B,2,FALSE)/1.21,IF(Tabla1[[#This Row],[TIPO OPERACIÓN]]="TUC CTADO 2",VLOOKUP(Tabla1[[#This Row],[FECHA OC]],'PRECIO CACTU'!A:B,2,FALSE)/1.21,IF(Tabla1[[#This Row],[TIPO OPERACIÓN]]="TUC CTADO 1",VLOOKUP(Tabla1[[#This Row],[FECHA OC]],'PRECIO CACTU'!A:B,2,FALSE),""))))),"") -> 32515 | AK18: =SUM(Tabla1[[#This Row],[PRECIO $ BOLSA 50KG FOB CDO TUC (IVA INC)]]-Tabla1[[#This Row],[PRECIO REF $ BOLSA 50 KG CACTU (IVA INC)]]) -> -4679.1514 | AL18: =IFERROR(Tabla1[[#This Row],[PRECIO $ BOLSA 50KG FOB CDO TUC (IVA INC)]]/Tabla1[[#This Row],[PRECIO REF $ BOLSA 50 KG CACTU (IVA INC)]]-1,"") -> -0.14390747 | AM18: =+Tabla1[[#This Row],[DIF $ PRECIO NETO INDUSTRIA vs Neto TUCUMAN (IVA INC)]]*Tabla1[[#This Row],[Q Bolsas Equivalentes 50kg]] -> -2681153.7 | AN18: =Tabla1[[#This Row],[PRECIO REF $ BOLSA 50 KG CACTU (IVA INC)]]*Tabla1[[#This Row],[Q Bolsas Equivalentes 50kg]] -> 18631095 | AO18: =+Tabla1[[#This Row],[PRECIO $ BOLSA 50KG FOB CDO TUC (IVA INC)]]*Tabla1[[#This Row],[Q Bolsas Equivalentes 50kg]] -> 15949941 | AP18: 0.029 | AQ18: -68 | AS18: 0008-00005578 | AT18: =+Tabla1[[#This Row],[VENTA TOTAL $ (IVA INC) ]]-(SUM(Tabla1[[#This Row],[PENDIENTE DE ENTREGA]:[VALORES COBRADOS]])) -> 0 | AU18: =VLOOKUP(Tabla1[[#This Row],[FECHA OC]],'TIPO DE CAMBIO'!A:B,2,TRUE) -> 1446.301 | AV18: =+Tabla1[[#This Row],[SUBTOTAL]]/Tabla1[[#This Row],[TIPO DE CAMBIO]] -> 9024.75 | AX18: =IFERROR(Tabla1[[#This Row],[VENTA TOTAL USD A PLAZO EN CLIENTE (SIN IVA)]]*(1+Tabla1[[#This Row],[% IVA ]]),"") -> 9024.75 | AY18: =+Tabla1[[#This Row],[VENTA TOTAL USD A PLAZO EN CLIENTE (SIN IVA)]]/Tabla1[[#This Row],[KGS]]*1000 -> 315 | AZ18: 0 | BA18: =+Tabla1[[#This Row],[GASTOS FINANCIEROS $ BOLSA 50 KG (IVA INC)]]*20/Tabla1[[#This Row],[TIPO DE CAMBIO]] -> 3.7803466 | BB18: =+Tabla1[[#This Row],[PRECIO POR TN USD EN CLIENTE A PLAZO (SIN IVA)]]+Tabla1[[#This Row],[COSTO USD FLETE /TN (SIN IVA)]]+Tabla1[[#This Row],[COSTO FINANCIERO USD POR BOLSA 50KG (IVA INC)]] -> 318.78035 | BC18: 5
A19: 46143 | B19: 1 | C19: LEDESMA SAAI | D19: =+Tabla1[[#This Row],[FECHA Entrega]] -> 46175.835 | E19: 700000869 | F19: AZÚCAR CRUDO | G19: ENTREGADO | H19: 46175.835 | I19: =586*50 -> 29300 | J19: =0.315*Tabla1[[#This Row],[TIPO DE CAMBIO]] -> 455.58481 | K19: =+J19*I19 -> 13348635 | L19: =IF(Tabla1[[#This Row],[TIPO OPERACIÓN]]="INDUSTRIA",Tabla1[[#This Row],[SUBTOTAL]]*0.21,IF(Tabla1[[#This Row],[TIPO OPERACIÓN]]="GDES CUENTAS",Tabla1[[#This Row],[SUBTOTAL]]*0.21,IF(Tabla1[[#This Row],[TIPO OPERACIÓN]]="TUC CTADO 2","",IF(Tabla1[[#This Row],[TIPO OPERACIÓN]]="EXPO CHILE","",IF(Tabla1[[#This Row],[TIPO OPERACIÓN]]="TUC CTADO 1",Tabla1[[#This Row],[SUBTOTAL]]*0.21,""))))) -> 2803213.4 | M19: =SUM(K19:L19) -> 16151848 | O19: 0 | P19: 0 | Q19: =+Tabla1[[#This Row],[VENTA TOTAL $ (IVA INC) ]]-Tabla1[[#This Row],[PENDIENTE DE COBRO]] -> 16151848 | R19: =+Tabla1[[#This Row],[FECHA FC]]+Tabla1[[#This Row],[PLAZO ENTREGA VALORES]] -> 46051 | S19: =+Tabla1[[#This Row],[FECHA FC]]+Tabla1[[#This Row],[PLAZO PAGO (DIAS)]] -> 46175.835 | T19: =+S19-$U$2 -> -5.1652778 | U19: =+Tabla1[[#This Row],[FECHA OC]]-Tabla1[[#This Row],[FECHA Entrega]] -> -124.83472 | W19: =+Tabla1[[#This Row],[FECHA VTO VALORES]]+7 -> 46182.835 | Y19: 46051 | Z19: =Tabla1[[#This Row],[KGS]]/50 -> 586 | AA19: =IFERROR((IF(Tabla1[[#This Row],[TIPO OPERACIÓN]]="INDUSTRIA",Tabla1[[#This Row],[PRECIO $/ KG A PLAZO EN CLIENTE ( SIN IVA)]]*50*1.21,IF(Tabla1[[#This Row],[TIPO OPERACIÓN]]="TUC CTADO 2",Tabla1[[#This Row],[PRECIO $/ KG A PLAZO EN CLIENTE ( SIN IVA)]]*50,IF(Tabla1[[#This Row],[TIPO OPERACIÓN]]="EXPO CHILE",Tabla1[[#This Row],[PRECIO $/ KG A PLAZO EN CLIENTE ( SIN IVA)]]*50*1,IF(Tabla1[[#This Row],[TIPO OPERACIÓN]]="GDES CUENTAS",Tabla1[[#This Row],[PRECIO $/ KG A PLAZO EN CLIENTE ( SIN IVA)]]*50*1.21,IF(Tabla1[[#This Row],[TIPO OPERACIÓN]]="TUC CTADO 1",Tabla1[[#This Row],[PRECIO $/ KG A PLAZO EN CLIENTE ( SIN IVA)]]*50*1.21,"")))))),"") -> 27562.881 | AB19: =-Tabla1[[#This Row],[COSTO FLETE $ POR BOLSA 5O KG (SIN IVA)]]*1.21-Tabla1[[#This Row],[PRECIO $/ KG A PLAZO EN CLIENTE ( SIN IVA)]]*0.003*1.21*50 -> -0.40864392 | AC19: =SUM(Tabla1[[#This Row],[PRECIO $ BOLSA 50 KG (IVA INC) ]]+Tabla1[[#This Row],[COSTO FLETE $ BOLSA 50 KG (IVA INC)]]) -> 27562.473 | AD19: =-Tabla1[[#This Row],[PRECIO $ BOLSA 50 KG (IVA INC) ]]*(Tabla1[[#This Row],[TASA FINANCIACION MENSUAL]]/365)*Tabla1[[#This Row],[PLAZO ENTREGA VALORES]] -> 273.379 | AE19: =SUM(Tabla1[[#This Row],[PRECIO $ BOLSA50 KG FOB TUCUMAN A PLAZO (IVA INC)]]+Tabla1[[#This Row],[GASTOS FINANCIEROS $ BOLSA 50 KG (IVA INC)]]) -> 27835.852 | AF19: GRANEL | AG19: RETIRA DE INGENIO | AH19: TUCUMAN | AI19: GDES CUENTAS | AJ19: =IFERROR(IF(Tabla1[[#This Row],[TIPO OPERACIÓN]]="INDUSTRIA",VLOOKUP(Tabla1[[#This Row],[FECHA OC]],'PRECIO CACTU'!A:B,2,FALSE),IF(Tabla1[[#This Row],[TIPO OPERACIÓN]]="GDES CUENTAS",VLOOKUP(Tabla1[[#This Row],[FECHA OC]],'PRECIO CACTU'!A:B,2,FALSE),IF(Tabla1[[#This Row],[TIPO OPERACIÓN]]="EXPO CHILE",VLOOKUP(Tabla1[[#This Row],[FECHA OC]],'PRECIO CACTU'!A:B,2,FALSE)/1.21,IF(Tabla1[[#This Row],[TIPO OPERACIÓN]]="TUC CTADO 2",VLOOKUP(Tabla1[[#This Row],[FECHA OC]],'PRECIO CACTU'!A:B,2,FALSE)/1.21,IF(Tabla1[[#This Row],[TIPO OPERACIÓN]]="TUC CTADO 1",VLOOKUP(Tabla1[[#This Row],[FECHA OC]],'PRECIO CACTU'!A:B,2,FALSE),""))))),"") -> 32515 | AK19: =SUM(Tabla1[[#This Row],[PRECIO $ BOLSA 50KG FOB CDO TUC (IVA INC)]]-Tabla1[[#This Row],[PRECIO REF $ BOLSA 50 KG CACTU (IVA INC)]]) -> -4679.1483 | AL19: =IFERROR(Tabla1[[#This Row],[PRECIO $ BOLSA 50KG FOB CDO TUC (IVA INC)]]/Tabla1[[#This Row],[PRECIO REF $ BOLSA 50 KG CACTU (IVA INC)]]-1,"") -> -0.14390738 | AM19: =+Tabla1[[#This Row],[DIF $ PRECIO NETO INDUSTRIA vs Neto TUCUMAN (IVA INC)]]*Tabla1[[#This Row],[Q Bolsas Equivalentes 50kg]] -> -2741980.9 | AN19: =Tabla1[[#This Row],[PRECIO REF $ BOLSA 50 KG CACTU (IVA INC)]]*Tabla1[[#This Row],[Q Bolsas Equivalentes 50kg]] -> 19053790 | AO19: =+Tabla1[[#This Row],[PRECIO $ BOLSA 50KG FOB CDO TUC (IVA INC)]]*Tabla1[[#This Row],[Q Bolsas Equivalentes 50kg]] -> 16311809 | AP19: 0.029 | AQ19: -68 | AS19: 0008-00005581 | AT19: =+Tabla1[[#This Row],[VENTA TOTAL $ (IVA INC) ]]-(SUM(Tabla1[[#This Row],[PENDIENTE DE ENTREGA]:[VALORES COBRADOS]])) -> 0 | AU19: =VLOOKUP(Tabla1[[#This Row],[FECHA OC]],'TIPO DE CAMBIO'!A:B,2,TRUE) -> 1446.301 | AV19: =+Tabla1[[#This Row],[SUBTOTAL]]/Tabla1[[#This Row],[TIPO DE CAMBIO]] -> 9229.5 | AX19: =IFERROR(Tabla1[[#This Row],[VENTA TOTAL USD A PLAZO EN CLIENTE (SIN IVA)]]*(1+Tabla1[[#This Row],[% IVA ]]),"") -> 9229.5 | AY19: =+Tabla1[[#This Row],[VENTA TOTAL USD A PLAZO EN CLIENTE (SIN IVA)]]/Tabla1[[#This Row],[KGS]]*1000 -> 315 | AZ19: 0 | BA19: =+Tabla1[[#This Row],[GASTOS FINANCIEROS $ BOLSA 50 KG (IVA INC)]]*20/Tabla1[[#This Row],[TIPO DE CAMBIO]] -> 3.7803887 | BB19: =+Tabla1[[#This Row],[PRECIO POR TN USD EN CLIENTE A PLAZO (SIN IVA)]]+Tabla1[[#This Row],[COSTO USD FLETE /TN (SIN IVA)]]+Tabla1[[#This Row],[COSTO FINANCIERO USD POR BOLSA 50KG (IVA INC)]] -> 318.78039 | BC19: 5
A20: 46143 | B20: 1 | C20: LEDESMA SAAI | D20: =+Tabla1[[#This Row],[FECHA Entrega]] -> 46177 | E20: 700000869 | F20: AZÚCAR CRUDO | G20: PENDIENTE | H20: 46177 | I20: =700*50 -> 35000 | J20: =0.315*Tabla1[[#This Row],[TIPO DE CAMBIO]] -> 455.58481 | K20: =+J20*I20 -> 15945469 | L20: =IF(Tabla1[[#This Row],[TIPO OPERACIÓN]]="INDUSTRIA",Tabla1[[#This Row],[SUBTOTAL]]*0.21,IF(Tabla1[[#This Row],[TIPO OPERACIÓN]]="GDES CUENTAS",Tabla1[[#This Row],[SUBTOTAL]]*0.21,IF(Tabla1[[#This Row],[TIPO OPERACIÓN]]="TUC CTADO 2","",IF(Tabla1[[#This Row],[TIPO OPERACIÓN]]="EXPO CHILE","",IF(Tabla1[[#This Row],[TIPO OPERACIÓN]]="TUC CTADO 1",Tabla1[[#This Row],[SUBTOTAL]]*0.21,""))))) -> 3348548.4 | M20: =SUM(K20:L20) -> 19294017 | O20: 0 | P20: 0 | Q20: =+Tabla1[[#This Row],[VENTA TOTAL $ (IVA INC) ]]-Tabla1[[#This Row],[PENDIENTE DE COBRO]] -> 19294017 | R20: =+Tabla1[[#This Row],[FECHA FC]]+Tabla1[[#This Row],[PLAZO ENTREGA VALORES]] -> 46051 | S20: =+Tabla1[[#This Row],[FECHA FC]]+Tabla1[[#This Row],[PLAZO PAGO (DIAS)]] -> 46177 | T20: =+S20-$U$2 -> -4 | U20: =+Tabla1[[#This Row],[FECHA OC]]-Tabla1[[#This Row],[FECHA Entrega]] -> -126 | W20: =+Tabla1[[#This Row],[FECHA VTO VALORES]]+7 -> 46184 | Y20: 46051 | Z20: =Tabla1[[#This Row],[KGS]]/50 -> 700 | AA20: =IFERROR((IF(Tabla1[[#This Row],[TIPO OPERACIÓN]]="INDUSTRIA",Tabla1[[#This Row],[PRECIO $/ KG A PLAZO EN CLIENTE ( SIN IVA)]]*50*1.21,IF(Tabla1[[#This Row],[TIPO OPERACIÓN]]="TUC CTADO 2",Tabla1[[#This Row],[PRECIO $/ KG A PLAZO EN CLIENTE ( SIN IVA)]]*50,IF(Tabla1[[#This Row],[TIPO OPERACIÓN]]="EXPO CHILE",Tabla1[[#This Row],[PRECIO $/ KG A PLAZO EN CLIENTE ( SIN IVA)]]*50*1,IF(Tabla1[[#This Row],[TIPO OPERACIÓN]]="GDES CUENTAS",Tabla1[[#This Row],[PRECIO $/ KG A PLAZO EN CLIENTE ( SIN IVA)]]*50*1.21,IF(Tabla1[[#This Row],[TIPO OPERACIÓN]]="TUC CTADO 1",Tabla1[[#This Row],[PRECIO $/ KG A PLAZO EN CLIENTE ( SIN IVA)]]*50*1.21,"")))))),"") -> 27562.881 | AB20: =-Tabla1[[#This Row],[COSTO FLETE $ POR BOLSA 5O KG (SIN IVA)]]*1.21-Tabla1[[#This Row],[PRECIO $/ KG A PLAZO EN CLIENTE ( SIN IVA)]]*0.003*1.21*50 -> -0.40864392 | AC20: =SUM(Tabla1[[#This Row],[PRECIO $ BOLSA 50 KG (IVA INC) ]]+Tabla1[[#This Row],[COSTO FLETE $ BOLSA 50 KG (IVA INC)]]) -> 27562.473 | AD20: =-Tabla1[[#This Row],[PRECIO $ BOLSA 50 KG (IVA INC) ]]*(Tabla1[[#This Row],[TASA FINANCIACION MENSUAL]]/365)*Tabla1[[#This Row],[PLAZO ENTREGA VALORES]] -> 275.93087 | AE20: =SUM(Tabla1[[#This Row],[PRECIO $ BOLSA50 KG FOB TUCUMAN A PLAZO (IVA INC)]]+Tabla1[[#This Row],[GASTOS FINANCIEROS $ BOLSA 50 KG (IVA INC)]]) -> 27838.404 | AF20: GRANEL | AG20: RETIRA DE INGENIO | AH20: TUCUMAN | AI20: GDES CUENTAS | AJ20: =IFERROR(IF(Tabla1[[#This Row],[TIPO OPERACIÓN]]="INDUSTRIA",VLOOKUP(Tabla1[[#This Row],[FECHA OC]],'PRECIO CACTU'!A:B,2,FALSE),IF(Tabla1[[#This Row],[TIPO OPERACIÓN]]="GDES CUENTAS",VLOOKUP(Tabla1[[#This Row],[FECHA OC]],'PRECIO CACTU'!A:B,2,FALSE),IF(Tabla1[[#This Row],[TIPO OPERACIÓN]]="EXPO CHILE",VLOOKUP(Tabla1[[#This Row],[FECHA OC]],'PRECIO CACTU'!A:B,2,FALSE)/1.21,IF(Tabla1[[#This Row],[TIPO OPERACIÓN]]="TUC CTADO 2",VLOOKUP(Tabla1[[#This Row],[FECHA OC]],'PRECIO CACTU'!A:B,2,FALSE)/1.21,IF(Tabla1[[#This Row],[TIPO OPERACIÓN]]="TUC CTADO 1",VLOOKUP(Tabla1[[#This Row],[FECHA OC]],'PRECIO CACTU'!A:B,2,FALSE),""))))),"") -> 32515 | AK20: =SUM(Tabla1[[#This Row],[PRECIO $ BOLSA 50KG FOB CDO TUC (IVA INC)]]-Tabla1[[#This Row],[PRECIO REF $ BOLSA 50 KG CACTU (IVA INC)]]) -> -4676.5965 | AL20: =IFERROR(Tabla1[[#This Row],[PRECIO $ BOLSA 50KG FOB CDO TUC (IVA INC)]]/Tabla1[[#This Row],[PRECIO REF $ BOLSA 50 KG CACTU (IVA INC)]]-1,"") -> -0.14382889 | AM20: =+Tabla1[[#This Row],[DIF $ PRECIO NETO INDUSTRIA vs Neto TUCUMAN (IVA INC)]]*Tabla1[[#This Row],[Q Bolsas Equivalentes 50kg]] -> -3273617.5 | AN20: =Tabla1[[#This Row],[PRECIO REF $ BOLSA 50 KG CACTU (IVA INC)]]*Tabla1[[#This Row],[Q Bolsas Equivalentes 50kg]] -> 22760500 | AO20: =+Tabla1[[#This Row],[PRECIO $ BOLSA 50KG FOB CDO TUC (IVA INC)]]*Tabla1[[#This Row],[Q Bolsas Equivalentes 50kg]] -> 19486882 | AP20: 0.029 | AQ20: -68 | AT20: =+Tabla1[[#This Row],[VENTA TOTAL $ (IVA INC) ]]-(SUM(Tabla1[[#This Row],[PENDIENTE DE ENTREGA]:[VALORES COBRADOS]])) -> 0 | AU20: =VLOOKUP(Tabla1[[#This Row],[FECHA OC]],'TIPO DE CAMBIO'!A:B,2,TRUE) -> 1446.301 | AV20: =+Tabla1[[#This Row],[SUBTOTAL]]/Tabla1[[#This Row],[TIPO DE CAMBIO]] -> 11025 | AX20: =IFERROR(Tabla1[[#This Row],[VENTA TOTAL USD A PLAZO EN CLIENTE (SIN IVA)]]*(1+Tabla1[[#This Row],[% IVA ]]),"") -> 11025 | AY20: =+Tabla1[[#This Row],[VENTA TOTAL USD A PLAZO EN CLIENTE (SIN IVA)]]/Tabla1[[#This Row],[KGS]]*1000 -> 315 | AZ20: 0 | BA20: =+Tabla1[[#This Row],[GASTOS FINANCIEROS $ BOLSA 50 KG (IVA INC)]]*20/Tabla1[[#This Row],[TIPO DE CAMBIO]] -> 3.815677 | BB20: =+Tabla1[[#This Row],[PRECIO POR TN USD EN CLIENTE A PLAZO (SIN IVA)]]+Tabla1[[#This Row],[COSTO USD FLETE /TN (SIN IVA)]]+Tabla1[[#This Row],[COSTO FINANCIERO USD POR BOLSA 50KG (IVA INC)]] -> 318.81568 | BC20: 5
A21: 46143 | B21: 1 | C21: LEDESMA SAAI | D21: =+Tabla1[[#This Row],[FECHA Entrega]] -> 46178 | E21: 700000869 | F21: AZÚCAR CRUDO | G21: PENDIENTE | H21: 46178 | I21: =700*50 -> 35000 | J21: =0.315*Tabla1[[#This Row],[TIPO DE CAMBIO]] -> 455.58481 | K21: =+J21*I21 -> 15945469 | L21: =IF(Tabla1[[#This Row],[TIPO OPERACIÓN]]="INDUSTRIA",Tabla1[[#This Row],[SUBTOTAL]]*0.21,IF(Tabla1[[#This Row],[TIPO OPERACIÓN]]="GDES CUENTAS",Tabla1[[#This Row],[SUBTOTAL]]*0.21,IF(Tabla1[[#This Row],[TIPO OPERACIÓN]]="TUC CTADO 2","",IF(Tabla1[[#This Row],[TIPO OPERACIÓN]]="EXPO CHILE","",IF(Tabla1[[#This Row],[TIPO OPERACIÓN]]="TUC CTADO 1",Tabla1[[#This Row],[SUBTOTAL]]*0.21,""))))) -> 3348548.4 | M21: =SUM(K21:L21) -> 19294017 | O21: 0 | P21: 0 | Q21: =+Tabla1[[#This Row],[VENTA TOTAL $ (IVA INC) ]]-Tabla1[[#This Row],[PENDIENTE DE COBRO]] -> 19294017 | R21: =+Tabla1[[#This Row],[FECHA FC]]+Tabla1[[#This Row],[PLAZO ENTREGA VALORES]] -> 46051 | S21: =+Tabla1[[#This Row],[FECHA FC]]+Tabla1[[#This Row],[PLAZO PAGO (DIAS)]] -> 46178 | T21: =+S21-$U$2 -> -3 | U21: =+Tabla1[[#This Row],[FECHA OC]]-Tabla1[[#This Row],[FECHA Entrega]] -> -127 | W21: =+Tabla1[[#This Row],[FECHA VTO VALORES]]+7 -> 46185 | Y21: 46051 | Z21: =Tabla1[[#This Row],[KGS]]/50 -> 700 | AA21: =IFERROR((IF(Tabla1[[#This Row],[TIPO OPERACIÓN]]="INDUSTRIA",Tabla1[[#This Row],[PRECIO $/ KG A PLAZO EN CLIENTE ( SIN IVA)]]*50*1.21,IF(Tabla1[[#This Row],[TIPO OPERACIÓN]]="TUC CTADO 2",Tabla1[[#This Row],[PRECIO $/ KG A PLAZO EN CLIENTE ( SIN IVA)]]*50,IF(Tabla1[[#This Row],[TIPO OPERACIÓN]]="EXPO CHILE",Tabla1[[#This Row],[PRECIO $/ KG A PLAZO EN CLIENTE ( SIN IVA)]]*50*1,IF(Tabla1[[#This Row],[TIPO OPERACIÓN]]="GDES CUENTAS",Tabla1[[#This Row],[PRECIO $/ KG A PLAZO EN CLIENTE ( SIN IVA)]]*50*1.21,IF(Tabla1[[#This Row],[TIPO OPERACIÓN]]="TUC CTADO 1",Tabla1[[#This Row],[PRECIO $/ KG A PLAZO EN CLIENTE ( SIN IVA)]]*50*1.21,"")))))),"") -> 27562.881 | AB21: =-Tabla1[[#This Row],[COSTO FLETE $ POR BOLSA 5O KG (SIN IVA)]]*1.21-Tabla1[[#This Row],[PRECIO $/ KG A PLAZO EN CLIENTE ( SIN IVA)]]*0.003*1.21*50 -> -0.40864392 | AC21: =SUM(Tabla1[[#This Row],[PRECIO $ BOLSA 50 KG (IVA INC) ]]+Tabla1[[#This Row],[COSTO FLETE $ BOLSA 50 KG (IVA INC)]]) -> 27562.473 | AD21: =-Tabla1[[#This Row],[PRECIO $ BOLSA 50 KG (IVA INC) ]]*(Tabla1[[#This Row],[TASA FINANCIACION MENSUAL]]/365)*Tabla1[[#This Row],[PLAZO ENTREGA VALORES]] -> 278.1208 | AE21: =SUM(Tabla1[[#This Row],[PRECIO $ BOLSA50 KG FOB TUCUMAN A PLAZO (IVA INC)]]+Tabla1[[#This Row],[GASTOS FINANCIEROS $ BOLSA 50 KG (IVA INC)]]) -> 27840.593 | AF21: GRANEL | AG21: RETIRA DE INGENIO | AH21: TUCUMAN | AI21: GDES CUENTAS | AJ21: =IFERROR(IF(Tabla1[[#This Row],[TIPO OPERACIÓN]]="INDUSTRIA",VLOOKUP(Tabla1[[#This Row],[FECHA OC]],'PRECIO CACTU'!A:B,2,FALSE),IF(Tabla1[[#This Row],[TIPO OPERACIÓN]]="GDES CUENTAS",VLOOKUP(Tabla1[[#This Row],[FECHA OC]],'PRECIO CACTU'!A:B,2,FALSE),IF(Tabla1[[#This Row],[TIPO OPERACIÓN]]="EXPO CHILE",VLOOKUP(Tabla1[[#This Row],[FECHA OC]],'PRECIO CACTU'!A:B,2,FALSE)/1.21,IF(Tabla1[[#This Row],[TIPO OPERACIÓN]]="TUC CTADO 2",VLOOKUP(Tabla1[[#This Row],[FECHA OC]],'PRECIO CACTU'!A:B,2,FALSE)/1.21,IF(Tabla1[[#This Row],[TIPO OPERACIÓN]]="TUC CTADO 1",VLOOKUP(Tabla1[[#This Row],[FECHA OC]],'PRECIO CACTU'!A:B,2,FALSE),""))))),"") -> 32515 | AK21: =SUM(Tabla1[[#This Row],[PRECIO $ BOLSA 50KG FOB CDO TUC (IVA INC)]]-Tabla1[[#This Row],[PRECIO REF $ BOLSA 50 KG CACTU (IVA INC)]]) -> -4674.4065 | AL21: =IFERROR(Tabla1[[#This Row],[PRECIO $ BOLSA 50KG FOB CDO TUC (IVA INC)]]/Tabla1[[#This Row],[PRECIO REF $ BOLSA 50 KG CACTU (IVA INC)]]-1,"") -> -0.14376154 | AM21: =+Tabla1[[#This Row],[DIF $ PRECIO NETO INDUSTRIA vs Neto TUCUMAN (IVA INC)]]*Tabla1[[#This Row],[Q Bolsas Equivalentes 50kg]] -> -3272084.6 | AN21: =Tabla1[[#This Row],[PRECIO REF $ BOLSA 50 KG CACTU (IVA INC)]]*Tabla1[[#This Row],[Q Bolsas Equivalentes 50kg]] -> 22760500 | AO21: =+Tabla1[[#This Row],[PRECIO $ BOLSA 50KG FOB CDO TUC (IVA INC)]]*Tabla1[[#This Row],[Q Bolsas Equivalentes 50kg]] -> 19488415 | AP21: 0.029 | AQ21: -68 | AT21: =+Tabla1[[#This Row],[VENTA TOTAL $ (IVA INC) ]]-(SUM(Tabla1[[#This Row],[PENDIENTE DE ENTREGA]:[VALORES COBRADOS]])) -> 0 | AU21: =VLOOKUP(Tabla1[[#This Row],[FECHA OC]],'TIPO DE CAMBIO'!A:B,2,TRUE) -> 1446.301 | AV21: =+Tabla1[[#This Row],[SUBTOTAL]]/Tabla1[[#This Row],[TIPO DE CAMBIO]] -> 11025 | AX21: =IFERROR(Tabla1[[#This Row],[VENTA TOTAL USD A PLAZO EN CLIENTE (SIN IVA)]]*(1+Tabla1[[#This Row],[% IVA ]]),"") -> 11025 | AY21: =+Tabla1[[#This Row],[VENTA TOTAL USD A PLAZO EN CLIENTE (SIN IVA)]]/Tabla1[[#This Row],[KGS]]*1000 -> 315 | AZ21: 0 | BA21: =+Tabla1[[#This Row],[GASTOS FINANCIEROS $ BOLSA 50 KG (IVA INC)]]*20/Tabla1[[#This Row],[TIPO DE CAMBIO]] -> 3.8459601 | BB21: =+Tabla1[[#This Row],[PRECIO POR TN USD EN CLIENTE A PLAZO (SIN IVA)]]+Tabla1[[#This Row],[COSTO USD FLETE /TN (SIN IVA)]]+Tabla1[[#This Row],[COSTO FINANCIERO USD POR BOLSA 50KG (IVA INC)]] -> 318.84596 | BC21: 5
A22: 46143 | B22: 1 | C22: LEDESMA SAAI | D22: =+Tabla1[[#This Row],[FECHA Entrega]] -> 46178 | E22: 700000869 | F22: AZÚCAR CRUDO | G22: PENDIENTE | H22: 46178 | I22: =700*50 -> 35000 | J22: =0.315*Tabla1[[#This Row],[TIPO DE CAMBIO]] -> 455.58481 | K22: =+J22*I22 -> 15945469 | L22: =IF(Tabla1[[#This Row],[TIPO OPERACIÓN]]="INDUSTRIA",Tabla1[[#This Row],[SUBTOTAL]]*0.21,IF(Tabla1[[#This Row],[TIPO OPERACIÓN]]="GDES CUENTAS",Tabla1[[#This Row],[SUBTOTAL]]*0.21,IF(Tabla1[[#This Row],[TIPO OPERACIÓN]]="TUC CTADO 2","",IF(Tabla1[[#This Row],[TIPO OPERACIÓN]]="EXPO CHILE","",IF(Tabla1[[#This Row],[TIPO OPERACIÓN]]="TUC CTADO 1",Tabla1[[#This Row],[SUBTOTAL]]*0.21,""))))) -> 3348548.4 | M22: =SUM(K22:L22) -> 19294017 | O22: 0 | P22: 0 | Q22: =+Tabla1[[#This Row],[VENTA TOTAL $ (IVA INC) ]]-Tabla1[[#This Row],[PENDIENTE DE COBRO]] -> 19294017 | R22: =+Tabla1[[#This Row],[FECHA FC]]+Tabla1[[#This Row],[PLAZO ENTREGA VALORES]] -> 46051 | S22: =+Tabla1[[#This Row],[FECHA FC]]+Tabla1[[#This Row],[PLAZO PAGO (DIAS)]] -> 46178 | T22: =+S22-$U$2 -> -3 | U22: =+Tabla1[[#This Row],[FECHA OC]]-Tabla1[[#This Row],[FECHA Entrega]] -> -127 | W22: =+Tabla1[[#This Row],[FECHA VTO VALORES]]+7 -> 46185 | Y22: 46051 | Z22: =Tabla1[[#This Row],[KGS]]/50 -> 700 | AA22: =IFERROR((IF(Tabla1[[#This Row],[TIPO OPERACIÓN]]="INDUSTRIA",Tabla1[[#This Row],[PRECIO $/ KG A PLAZO EN CLIENTE ( SIN IVA)]]*50*1.21,IF(Tabla1[[#This Row],[TIPO OPERACIÓN]]="TUC CTADO 2",Tabla1[[#This Row],[PRECIO $/ KG A PLAZO EN CLIENTE ( SIN IVA)]]*50,IF(Tabla1[[#This Row],[TIPO OPERACIÓN]]="EXPO CHILE",Tabla1[[#This Row],[PRECIO $/ KG A PLAZO EN CLIENTE ( SIN IVA)]]*50*1,IF(Tabla1[[#This Row],[TIPO OPERACIÓN]]="GDES CUENTAS",Tabla1[[#This Row],[PRECIO $/ KG A PLAZO EN CLIENTE ( SIN IVA)]]*50*1.21,IF(Tabla1[[#This Row],[TIPO OPERACIÓN]]="TUC CTADO 1",Tabla1[[#This Row],[PRECIO $/ KG A PLAZO EN CLIENTE ( SIN IVA)]]*50*1.21,"")))))),"") -> 27562.881 | AB22: =-Tabla1[[#This Row],[COSTO FLETE $ POR BOLSA 5O KG (SIN IVA)]]*1.21-Tabla1[[#This Row],[PRECIO $/ KG A PLAZO EN CLIENTE ( SIN IVA)]]*0.003*1.21*50 -> -0.40864392 | AC22: =SUM(Tabla1[[#This Row],[PRECIO $ BOLSA 50 KG (IVA INC) ]]+Tabla1[[#This Row],[COSTO FLETE $ BOLSA 50 KG (IVA INC)]]) -> 27562.473 | AD22: =-Tabla1[[#This Row],[PRECIO $ BOLSA 50 KG (IVA INC) ]]*(Tabla1[[#This Row],[TASA FINANCIACION MENSUAL]]/365)*Tabla1[[#This Row],[PLAZO ENTREGA VALORES]] -> 278.1208 | AE22: =SUM(Tabla1[[#This Row],[PRECIO $ BOLSA50 KG FOB TUCUMAN A PLAZO (IVA INC)]]+Tabla1[[#This Row],[GASTOS FINANCIEROS $ BOLSA 50 KG (IVA INC)]]) -> 27840.593 | AF22: GRANEL | AG22: RETIRA DE INGENIO | AH22: TUCUMAN | AI22: GDES CUENTAS | AJ22: =IFERROR(IF(Tabla1[[#This Row],[TIPO OPERACIÓN]]="INDUSTRIA",VLOOKUP(Tabla1[[#This Row],[FECHA OC]],'PRECIO CACTU'!A:B,2,FALSE),IF(Tabla1[[#This Row],[TIPO OPERACIÓN]]="GDES CUENTAS",VLOOKUP(Tabla1[[#This Row],[FECHA OC]],'PRECIO CACTU'!A:B,2,FALSE),IF(Tabla1[[#This Row],[TIPO OPERACIÓN]]="EXPO CHILE",VLOOKUP(Tabla1[[#This Row],[FECHA OC]],'PRECIO CACTU'!A:B,2,FALSE)/1.21,IF(Tabla1[[#This Row],[TIPO OPERACIÓN]]="TUC CTADO 2",VLOOKUP(Tabla1[[#This Row],[FECHA OC]],'PRECIO CACTU'!A:B,2,FALSE)/1.21,IF(Tabla1[[#This Row],[TIPO OPERACIÓN]]="TUC CTADO 1",VLOOKUP(Tabla1[[#This Row],[FECHA OC]],'PRECIO CACTU'!A:B,2,FALSE),""))))),"") -> 32515 | AK22: =SUM(Tabla1[[#This Row],[PRECIO $ BOLSA 50KG FOB CDO TUC (IVA INC)]]-Tabla1[[#This Row],[PRECIO REF $ BOLSA 50 KG CACTU (IVA INC)]]) -> -4674.4065 | AL22: =IFERROR(Tabla1[[#This Row],[PRECIO $ BOLSA 50KG FOB CDO TUC (IVA INC)]]/Tabla1[[#This Row],[PRECIO REF $ BOLSA 50 KG CACTU (IVA INC)]]-1,"") -> -0.14376154 | AM22: =+Tabla1[[#This Row],[DIF $ PRECIO NETO INDUSTRIA vs Neto TUCUMAN (IVA INC)]]*Tabla1[[#This Row],[Q Bolsas Equivalentes 50kg]] -> -3272084.6 | AN22: =Tabla1[[#This Row],[PRECIO REF $ BOLSA 50 KG CACTU (IVA INC)]]*Tabla1[[#This Row],[Q Bolsas Equivalentes 50kg]] -> 22760500 | AO22: =+Tabla1[[#This Row],[PRECIO $ BOLSA 50KG FOB CDO TUC (IVA INC)]]*Tabla1[[#This Row],[Q Bolsas Equivalentes 50kg]] -> 19488415 | AP22: 0.029 | AQ22: -68 | AT22: =+Tabla1[[#This Row],[VENTA TOTAL $ (IVA INC) ]]-(SUM(Tabla1[[#This Row],[PENDIENTE DE ENTREGA]:[VALORES COBRADOS]])) -> 0 | AU22: =VLOOKUP(Tabla1[[#This Row],[FECHA OC]],'TIPO DE CAMBIO'!A:B,2,TRUE) -> 1446.301 | AV22: =+Tabla1[[#This Row],[SUBTOTAL]]/Tabla1[[#This Row],[TIPO DE CAMBIO]] -> 11025 | AX22: =IFERROR(Tabla1[[#This Row],[VENTA TOTAL USD A PLAZO EN CLIENTE (SIN IVA)]]*(1+Tabla1[[#This Row],[% IVA ]]),"") -> 11025 | AY22: =+Tabla1[[#This Row],[VENTA TOTAL USD A PLAZO EN CLIENTE (SIN IVA)]]/Tabla1[[#This Row],[KGS]]*1000 -> 315 | AZ22: 0 | BA22: =+Tabla1[[#This Row],[GASTOS FINANCIEROS $ BOLSA 50 KG (IVA INC)]]*20/Tabla1[[#This Row],[TIPO DE CAMBIO]] -> 3.8459601 | BB22: =+Tabla1[[#This Row],[PRECIO POR TN USD EN CLIENTE A PLAZO (SIN IVA)]]+Tabla1[[#This Row],[COSTO USD FLETE /TN (SIN IVA)]]+Tabla1[[#This Row],[COSTO FINANCIERO USD POR BOLSA 50KG (IVA INC)]] -> 318.84596 | BC22: 5
A23: 46143 | B23: 1 | C23: LEDESMA SAAI | D23: =+Tabla1[[#This Row],[FECHA Entrega]] -> 46059 | E23: 700000869 | F23: AZÚCAR CRUDO | G23: PENDIENTE | H23: 46059 | I23: =700*50 -> 35000 | J23: =0.315*Tabla1[[#This Row],[TIPO DE CAMBIO]] -> 455.58481 | K23: =+J23*I23 -> 15945469 | L23: =IF(Tabla1[[#This Row],[TIPO OPERACIÓN]]="INDUSTRIA",Tabla1[[#This Row],[SUBTOTAL]]*0.21,IF(Tabla1[[#This Row],[TIPO OPERACIÓN]]="GDES CUENTAS",Tabla1[[#This Row],[SUBTOTAL]]*0.21,IF(Tabla1[[#This Row],[TIPO OPERACIÓN]]="TUC CTADO 2","",IF(Tabla1[[#This Row],[TIPO OPERACIÓN]]="EXPO CHILE","",IF(Tabla1[[#This Row],[TIPO OPERACIÓN]]="TUC CTADO 1",Tabla1[[#This Row],[SUBTOTAL]]*0.21,""))))) -> 3348548.4 | M23: =SUM(K23:L23) -> 19294017 | O23: 0 | P23: 0 | Q23: =+Tabla1[[#This Row],[VENTA TOTAL $ (IVA INC) ]]-Tabla1[[#This Row],[PENDIENTE DE COBRO]] -> 19294017 | R23: =+Tabla1[[#This Row],[FECHA FC]]+Tabla1[[#This Row],[PLAZO ENTREGA VALORES]] -> 46051 | S23: =+Tabla1[[#This Row],[FECHA FC]]+Tabla1[[#This Row],[PLAZO PAGO (DIAS)]] -> 46059 | T23: =+S23-$U$2 -> -122 | U23: =+Tabla1[[#This Row],[FECHA OC]]-Tabla1[[#This Row],[FECHA Entrega]] -> -8 | W23: =+Tabla1[[#This Row],[FECHA VTO VALORES]]+7 -> 46066 | Y23: 46051 | Z23: =Tabla1[[#This Row],[KGS]]/50 -> 700 | AA23: =IFERROR((IF(Tabla1[[#This Row],[TIPO OPERACIÓN]]="INDUSTRIA",Tabla1[[#This Row],[PRECIO $/ KG A PLAZO EN CLIENTE ( SIN IVA)]]*50*1.21,IF(Tabla1[[#This Row],[TIPO OPERACIÓN]]="TUC CTADO 2",Tabla1[[#This Row],[PRECIO $/ KG A PLAZO EN CLIENTE ( SIN IVA)]]*50,IF(Tabla1[[#This Row],[TIPO OPERACIÓN]]="EXPO CHILE",Tabla1[[#This Row],[PRECIO $/ KG A PLAZO EN CLIENTE ( SIN IVA)]]*50*1,IF(Tabla1[[#This Row],[TIPO OPERACIÓN]]="GDES CUENTAS",Tabla1[[#This Row],[PRECIO $/ KG A PLAZO EN CLIENTE ( SIN IVA)]]*50*1.21,IF(Tabla1[[#This Row],[TIPO OPERACIÓN]]="TUC CTADO 1",Tabla1[[#This Row],[PRECIO $/ KG A PLAZO EN CLIENTE ( SIN IVA)]]*50*1.21,"")))))),"") -> 27562.881 | AB23: =-Tabla1[[#This Row],[COSTO FLETE $ POR BOLSA 5O KG (SIN IVA)]]*1.21-Tabla1[[#This Row],[PRECIO $/ KG A PLAZO EN CLIENTE ( SIN IVA)]]*0.003*1.21*50 -> -0.40864392 | AC23: =SUM(Tabla1[[#This Row],[PRECIO $ BOLSA 50 KG (IVA INC) ]]+Tabla1[[#This Row],[COSTO FLETE $ BOLSA 50 KG (IVA INC)]]) -> 27562.473 | AD23: =-Tabla1[[#This Row],[PRECIO $ BOLSA 50 KG (IVA INC) ]]*(Tabla1[[#This Row],[TASA FINANCIACION MENSUAL]]/365)*Tabla1[[#This Row],[PLAZO ENTREGA VALORES]] -> 17.51942 | AE23: =SUM(Tabla1[[#This Row],[PRECIO $ BOLSA50 KG FOB TUCUMAN A PLAZO (IVA INC)]]+Tabla1[[#This Row],[GASTOS FINANCIEROS $ BOLSA 50 KG (IVA INC)]]) -> 27579.992 | AF23: GRANEL | AG23: RETIRA DE INGENIO | AH23: TUCUMAN | AI23: GDES CUENTAS | AJ23: =IFERROR(IF(Tabla1[[#This Row],[TIPO OPERACIÓN]]="INDUSTRIA",VLOOKUP(Tabla1[[#This Row],[FECHA OC]],'PRECIO CACTU'!A:B,2,FALSE),IF(Tabla1[[#This Row],[TIPO OPERACIÓN]]="GDES CUENTAS",VLOOKUP(Tabla1[[#This Row],[FECHA OC]],'PRECIO CACTU'!A:B,2,FALSE),IF(Tabla1[[#This Row],[TIPO OPERACIÓN]]="EXPO CHILE",VLOOKUP(Tabla1[[#This Row],[FECHA OC]],'PRECIO CACTU'!A:B,2,FALSE)/1.21,IF(Tabla1[[#This Row],[TIPO OPERACIÓN]]="TUC CTADO 2",VLOOKUP(Tabla1[[#This Row],[FECHA OC]],'PRECIO CACTU'!A:B,2,FALSE)/1.21,IF(Tabla1[[#This Row],[TIPO OPERACIÓN]]="TUC CTADO 1",VLOOKUP(Tabla1[[#This Row],[FECHA OC]],'PRECIO CACTU'!A:B,2,FALSE),""))))),"") -> 32515 | AK23: =SUM(Tabla1[[#This Row],[PRECIO $ BOLSA 50KG FOB CDO TUC (IVA INC)]]-Tabla1[[#This Row],[PRECIO REF $ BOLSA 50 KG CACTU (IVA INC)]]) -> -4935.0079 | AL23: =IFERROR(Tabla1[[#This Row],[PRECIO $ BOLSA 50KG FOB CDO TUC (IVA INC)]]/Tabla1[[#This Row],[PRECIO REF $ BOLSA 50 KG CACTU (IVA INC)]]-1,"") -> -0.15177635 | AM23: =+Tabla1[[#This Row],[DIF $ PRECIO NETO INDUSTRIA vs Neto TUCUMAN (IVA INC)]]*Tabla1[[#This Row],[Q Bolsas Equivalentes 50kg]] -> -3454505.5 | AN23: =Tabla1[[#This Row],[PRECIO REF $ BOLSA 50 KG CACTU (IVA INC)]]*Tabla1[[#This Row],[Q Bolsas Equivalentes 50kg]] -> 22760500 | AO23: =+Tabla1[[#This Row],[PRECIO $ BOLSA 50KG FOB CDO TUC (IVA INC)]]*Tabla1[[#This Row],[Q Bolsas Equivalentes 50kg]] -> 19305994 | AP23: 0.029 | AQ23: -68 | AT23: =+Tabla1[[#This Row],[VENTA TOTAL $ (IVA INC) ]]-(SUM(Tabla1[[#This Row],[PENDIENTE DE ENTREGA]:[VALORES COBRADOS]])) -> 0 | AU23: =VLOOKUP(Tabla1[[#This Row],[FECHA OC]],'TIPO DE CAMBIO'!A:B,2,TRUE) -> 1446.301 | AV23: =+Tabla1[[#This Row],[SUBTOTAL]]/Tabla1[[#This Row],[TIPO DE CAMBIO]] -> 11025 | AX23: =IFERROR(Tabla1[[#This Row],[VENTA TOTAL USD A PLAZO EN CLIENTE (SIN IVA)]]*(1+Tabla1[[#This Row],[% IVA ]]),"") -> 11025 | AY23: =+Tabla1[[#This Row],[VENTA TOTAL USD A PLAZO EN CLIENTE (SIN IVA)]]/Tabla1[[#This Row],[KGS]]*1000 -> 315 | AZ23: 0 | BA23: =+Tabla1[[#This Row],[GASTOS FINANCIEROS $ BOLSA 50 KG (IVA INC)]]*20/Tabla1[[#This Row],[TIPO DE CAMBIO]] -> 0.24226521 | BB23: =+Tabla1[[#This Row],[PRECIO POR TN USD EN CLIENTE A PLAZO (SIN IVA)]]+Tabla1[[#This Row],[COSTO USD FLETE /TN (SIN IVA)]]+Tabla1[[#This Row],[COSTO FINANCIERO USD POR BOLSA 50KG (IVA INC)]] -> 315.24227 | BC23: 5
A24: 46143 | B24: 1 | C24: LEDESMA SAAI | D24: =+Tabla1[[#This Row],[FECHA Entrega]] -> 46059 | E24: 700000869 | F24: AZÚCAR CRUDO | G24: PENDIENTE | H24: 46059 | I24: =700*50 -> 35000 | J24: =0.315*Tabla1[[#This Row],[TIPO DE CAMBIO]] -> 455.58481 | K24: =+J24*I24 -> 15945469 | L24: =IF(Tabla1[[#This Row],[TIPO OPERACIÓN]]="INDUSTRIA",Tabla1[[#This Row],[SUBTOTAL]]*0.21,IF(Tabla1[[#This Row],[TIPO OPERACIÓN]]="GDES CUENTAS",Tabla1[[#This Row],[SUBTOTAL]]*0.21,IF(Tabla1[[#This Row],[TIPO OPERACIÓN]]="TUC CTADO 2","",IF(Tabla1[[#This Row],[TIPO OPERACIÓN]]="EXPO CHILE","",IF(Tabla1[[#This Row],[TIPO OPERACIÓN]]="TUC CTADO 1",Tabla1[[#This Row],[SUBTOTAL]]*0.21,""))))) -> 3348548.4 | M24: =SUM(K24:L24) -> 19294017 | O24: 0 | P24: 0 | Q24: =+Tabla1[[#This Row],[VENTA TOTAL $ (IVA INC) ]]-Tabla1[[#This Row],[PENDIENTE DE COBRO]] -> 19294017 | R24: =+Tabla1[[#This Row],[FECHA FC]]+Tabla1[[#This Row],[PLAZO ENTREGA VALORES]] -> 46051 | S24: =+Tabla1[[#This Row],[FECHA FC]]+Tabla1[[#This Row],[PLAZO PAGO (DIAS)]] -> 46059 | T24: =+S24-$U$2 -> -122 | U24: =+Tabla1[[#This Row],[FECHA OC]]-Tabla1[[#This Row],[FECHA Entrega]] -> -8 | W24: =+Tabla1[[#This Row],[FECHA VTO VALORES]]+7 -> 46066 | Y24: 46051 | Z24: =Tabla1[[#This Row],[KGS]]/50 -> 700 | AA24: =IFERROR((IF(Tabla1[[#This Row],[TIPO OPERACIÓN]]="INDUSTRIA",Tabla1[[#This Row],[PRECIO $/ KG A PLAZO EN CLIENTE ( SIN IVA)]]*50*1.21,IF(Tabla1[[#This Row],[TIPO OPERACIÓN]]="TUC CTADO 2",Tabla1[[#This Row],[PRECIO $/ KG A PLAZO EN CLIENTE ( SIN IVA)]]*50,IF(Tabla1[[#This Row],[TIPO OPERACIÓN]]="EXPO CHILE",Tabla1[[#This Row],[PRECIO $/ KG A PLAZO EN CLIENTE ( SIN IVA)]]*50*1,IF(Tabla1[[#This Row],[TIPO OPERACIÓN]]="GDES CUENTAS",Tabla1[[#This Row],[PRECIO $/ KG A PLAZO EN CLIENTE ( SIN IVA)]]*50*1.21,IF(Tabla1[[#This Row],[TIPO OPERACIÓN]]="TUC CTADO 1",Tabla1[[#This Row],[PRECIO $/ KG A PLAZO EN CLIENTE ( SIN IVA)]]*50*1.21,"")))))),"") -> 27562.881 | AB24: =-Tabla1[[#This Row],[COSTO FLETE $ POR BOLSA 5O KG (SIN IVA)]]*1.21-Tabla1[[#This Row],[PRECIO $/ KG A PLAZO EN CLIENTE ( SIN IVA)]]*0.003*1.21*50 -> -0.40864392 | AC24: =SUM(Tabla1[[#This Row],[PRECIO $ BOLSA 50 KG (IVA INC) ]]+Tabla1[[#This Row],[COSTO FLETE $ BOLSA 50 KG (IVA INC)]]) -> 27562.473 | AD24: =-Tabla1[[#This Row],[PRECIO $ BOLSA 50 KG (IVA INC) ]]*(Tabla1[[#This Row],[TASA FINANCIACION MENSUAL]]/365)*Tabla1[[#This Row],[PLAZO ENTREGA VALORES]] -> 17.51942 | AE24: =SUM(Tabla1[[#This Row],[PRECIO $ BOLSA50 KG FOB TUCUMAN A PLAZO (IVA INC)]]+Tabla1[[#This Row],[GASTOS FINANCIEROS $ BOLSA 50 KG (IVA INC)]]) -> 27579.992 | AF24: GRANEL | AG24: RETIRA DE INGENIO | AH24: TUCUMAN | AI24: GDES CUENTAS | AJ24: =IFERROR(IF(Tabla1[[#This Row],[TIPO OPERACIÓN]]="INDUSTRIA",VLOOKUP(Tabla1[[#This Row],[FECHA OC]],'PRECIO CACTU'!A:B,2,FALSE),IF(Tabla1[[#This Row],[TIPO OPERACIÓN]]="GDES CUENTAS",VLOOKUP(Tabla1[[#This Row],[FECHA OC]],'PRECIO CACTU'!A:B,2,FALSE),IF(Tabla1[[#This Row],[TIPO OPERACIÓN]]="EXPO CHILE",VLOOKUP(Tabla1[[#This Row],[FECHA OC]],'PRECIO CACTU'!A:B,2,FALSE)/1.21,IF(Tabla1[[#This Row],[TIPO OPERACIÓN]]="TUC CTADO 2",VLOOKUP(Tabla1[[#This Row],[FECHA OC]],'PRECIO CACTU'!A:B,2,FALSE)/1.21,IF(Tabla1[[#This Row],[TIPO OPERACIÓN]]="TUC CTADO 1",VLOOKUP(Tabla1[[#This Row],[FECHA OC]],'PRECIO CACTU'!A:B,2,FALSE),""))))),"") -> 32515 | AK24: =SUM(Tabla1[[#This Row],[PRECIO $ BOLSA 50KG FOB CDO TUC (IVA INC)]]-Tabla1[[#This Row],[PRECIO REF $ BOLSA 50 KG CACTU (IVA INC)]]) -> -4935.0079 | AL24: =IFERROR(Tabla1[[#This Row],[PRECIO $ BOLSA 50KG FOB CDO TUC (IVA INC)]]/Tabla1[[#This Row],[PRECIO REF $ BOLSA 50 KG CACTU (IVA INC)]]-1,"") -> -0.15177635 | AM24: =+Tabla1[[#This Row],[DIF $ PRECIO NETO INDUSTRIA vs Neto TUCUMAN (IVA INC)]]*Tabla1[[#This Row],[Q Bolsas Equivalentes 50kg]] -> -3454505.5 | AN24: =Tabla1[[#This Row],[PRECIO REF $ BOLSA 50 KG CACTU (IVA INC)]]*Tabla1[[#This Row],[Q Bolsas Equivalentes 50kg]] -> 22760500 | AO24: =+Tabla1[[#This Row],[PRECIO $ BOLSA 50KG FOB CDO TUC (IVA INC)]]*Tabla1[[#This Row],[Q Bolsas Equivalentes 50kg]] -> 19305994 | AP24: 0.029 | AQ24: -68 | AT24: =+Tabla1[[#This Row],[VENTA TOTAL $ (IVA INC) ]]-(SUM(Tabla1[[#This Row],[PENDIENTE DE ENTREGA]:[VALORES COBRADOS]])) -> 0 | AU24: =VLOOKUP(Tabla1[[#This Row],[FECHA OC]],'TIPO DE CAMBIO'!A:B,2,TRUE) -> 1446.301 | AV24: =+Tabla1[[#This Row],[SUBTOTAL]]/Tabla1[[#This Row],[TIPO DE CAMBIO]] -> 11025 | AX24: =IFERROR(Tabla1[[#This Row],[VENTA TOTAL USD A PLAZO EN CLIENTE (SIN IVA)]]*(1+Tabla1[[#This Row],[% IVA ]]),"") -> 11025 | AY24: =+Tabla1[[#This Row],[VENTA TOTAL USD A PLAZO EN CLIENTE (SIN IVA)]]/Tabla1[[#This Row],[KGS]]*1000 -> 315 | AZ24: 0 | BA24: =+Tabla1[[#This Row],[GASTOS FINANCIEROS $ BOLSA 50 KG (IVA INC)]]*20/Tabla1[[#This Row],[TIPO DE CAMBIO]] -> 0.24226521 | BB24: =+Tabla1[[#This Row],[PRECIO POR TN USD EN CLIENTE A PLAZO (SIN IVA)]]+Tabla1[[#This Row],[COSTO USD FLETE /TN (SIN IVA)]]+Tabla1[[#This Row],[COSTO FINANCIERO USD POR BOLSA 50KG (IVA INC)]] -> 315.24227 | BC24: 5
A25: 46143 | B25: 1 | C25: LEDESMA SAAI | D25: =+Tabla1[[#This Row],[FECHA Entrega]] -> 46180 | E25: 700000869 | F25: AZÚCAR CRUDO | G25: PENDIENTE | H25: 46180 | I25: =700*50 -> 35000 | J25: =0.315*Tabla1[[#This Row],[TIPO DE CAMBIO]] -> 455.58481 | K25: =+J25*I25 -> 15945469 | L25: =IF(Tabla1[[#This Row],[TIPO OPERACIÓN]]="INDUSTRIA",Tabla1[[#This Row],[SUBTOTAL]]*0.21,IF(Tabla1[[#This Row],[TIPO OPERACIÓN]]="GDES CUENTAS",Tabla1[[#This Row],[SUBTOTAL]]*0.21,IF(Tabla1[[#This Row],[TIPO OPERACIÓN]]="TUC CTADO 2","",IF(Tabla1[[#This Row],[TIPO OPERACIÓN]]="EXPO CHILE","",IF(Tabla1[[#This Row],[TIPO OPERACIÓN]]="TUC CTADO 1",Tabla1[[#This Row],[SUBTOTAL]]*0.21,""))))) -> 3348548.4 | M25: =SUM(K25:L25) -> 19294017 | O25: 0 | P25: 0 | Q25: =+Tabla1[[#This Row],[VENTA TOTAL $ (IVA INC) ]]-Tabla1[[#This Row],[PENDIENTE DE COBRO]] -> 19294017 | R25: =+Tabla1[[#This Row],[FECHA FC]]+Tabla1[[#This Row],[PLAZO ENTREGA VALORES]] -> 46051 | S25: =+Tabla1[[#This Row],[FECHA FC]]+Tabla1[[#This Row],[PLAZO PAGO (DIAS)]] -> 46180 | T25: =+S25-$U$2 -> -1 | U25: =+Tabla1[[#This Row],[FECHA OC]]-Tabla1[[#This Row],[FECHA Entrega]] -> -129 | W25: =+Tabla1[[#This Row],[FECHA VTO VALORES]]+7 -> 46187 | Y25: 46051 | Z25: =Tabla1[[#This Row],[KGS]]/50 -> 700 | AA25: =IFERROR((IF(Tabla1[[#This Row],[TIPO OPERACIÓN]]="INDUSTRIA",Tabla1[[#This Row],[PRECIO $/ KG A PLAZO EN CLIENTE ( SIN IVA)]]*50*1.21,IF(Tabla1[[#This Row],[TIPO OPERACIÓN]]="TUC CTADO 2",Tabla1[[#This Row],[PRECIO $/ KG A PLAZO EN CLIENTE ( SIN IVA)]]*50,IF(Tabla1[[#This Row],[TIPO OPERACIÓN]]="EXPO CHILE",Tabla1[[#This Row],[PRECIO $/ KG A PLAZO EN CLIENTE ( SIN IVA)]]*50*1,IF(Tabla1[[#This Row],[TIPO OPERACIÓN]]="GDES CUENTAS",Tabla1[[#This Row],[PRECIO $/ KG A PLAZO EN CLIENTE ( SIN IVA)]]*50*1.21,IF(Tabla1[[#This Row],[TIPO OPERACIÓN]]="TUC CTADO 1",Tabla1[[#This Row],[PRECIO $/ KG A PLAZO EN CLIENTE ( SIN IVA)]]*50*1.21,"")))))),"") -> 27562.881 | AB25: =-Tabla1[[#This Row],[COSTO FLETE $ POR BOLSA 5O KG (SIN IVA)]]*1.21-Tabla1[[#This Row],[PRECIO $/ KG A PLAZO EN CLIENTE ( SIN IVA)]]*0.003*1.21*50 -> -0.40864392 | AC25: =SUM(Tabla1[[#This Row],[PRECIO $ BOLSA 50 KG (IVA INC) ]]+Tabla1[[#This Row],[COSTO FLETE $ BOLSA 50 KG (IVA INC)]]) -> 27562.473 | AD25: =-Tabla1[[#This Row],[PRECIO $ BOLSA 50 KG (IVA INC) ]]*(Tabla1[[#This Row],[TASA FINANCIACION MENSUAL]]/365)*Tabla1[[#This Row],[PLAZO ENTREGA VALORES]] -> 282.50065 | AE25: =SUM(Tabla1[[#This Row],[PRECIO $ BOLSA50 KG FOB TUCUMAN A PLAZO (IVA INC)]]+Tabla1[[#This Row],[GASTOS FINANCIEROS $ BOLSA 50 KG (IVA INC)]]) -> 27844.973 | AF25: GRANEL | AG25: RETIRA DE INGENIO | AH25: TUCUMAN | AI25: GDES CUENTAS | AJ25: =IFERROR(IF(Tabla1[[#This Row],[TIPO OPERACIÓN]]="INDUSTRIA",VLOOKUP(Tabla1[[#This Row],[FECHA OC]],'PRECIO CACTU'!A:B,2,FALSE),IF(Tabla1[[#This Row],[TIPO OPERACIÓN]]="GDES CUENTAS",VLOOKUP(Tabla1[[#This Row],[FECHA OC]],'PRECIO CACTU'!A:B,2,FALSE),IF(Tabla1[[#This Row],[TIPO OPERACIÓN]]="EXPO CHILE",VLOOKUP(Tabla1[[#This Row],[FECHA OC]],'PRECIO CACTU'!A:B,2,FALSE)/1.21,IF(Tabla1[[#This Row],[TIPO OPERACIÓN]]="TUC CTADO 2",VLOOKUP(Tabla1[[#This Row],[FECHA OC]],'PRECIO CACTU'!A:B,2,FALSE)/1.21,IF(Tabla1[[#This Row],[TIPO OPERACIÓN]]="TUC CTADO 1",VLOOKUP(Tabla1[[#This Row],[FECHA OC]],'PRECIO CACTU'!A:B,2,FALSE),""))))),"") -> 32515 | AK25: =SUM(Tabla1[[#This Row],[PRECIO $ BOLSA 50KG FOB CDO TUC (IVA INC)]]-Tabla1[[#This Row],[PRECIO REF $ BOLSA 50 KG CACTU (IVA INC)]]) -> -4670.0267 | AL25: =IFERROR(Tabla1[[#This Row],[PRECIO $ BOLSA 50KG FOB CDO TUC (IVA INC)]]/Tabla1[[#This Row],[PRECIO REF $ BOLSA 50 KG CACTU (IVA INC)]]-1,"") -> -0.14362684 | AM25: =+Tabla1[[#This Row],[DIF $ PRECIO NETO INDUSTRIA vs Neto TUCUMAN (IVA INC)]]*Tabla1[[#This Row],[Q Bolsas Equivalentes 50kg]] -> -3269018.7 | AN25: =Tabla1[[#This Row],[PRECIO REF $ BOLSA 50 KG CACTU (IVA INC)]]*Tabla1[[#This Row],[Q Bolsas Equivalentes 50kg]] -> 22760500 | AO25: =+Tabla1[[#This Row],[PRECIO $ BOLSA 50KG FOB CDO TUC (IVA INC)]]*Tabla1[[#This Row],[Q Bolsas Equivalentes 50kg]] -> 19491481 | AP25: 0.029 | AQ25: -68 | AT25: =+Tabla1[[#This Row],[VENTA TOTAL $ (IVA INC) ]]-(SUM(Tabla1[[#This Row],[PENDIENTE DE ENTREGA]:[VALORES COBRADOS]])) -> 0 | AU25: =VLOOKUP(Tabla1[[#This Row],[FECHA OC]],'TIPO DE CAMBIO'!A:B,2,TRUE) -> 1446.301 | AV25: =+Tabla1[[#This Row],[SUBTOTAL]]/Tabla1[[#This Row],[TIPO DE CAMBIO]] -> 11025 | AX25: =IFERROR(Tabla1[[#This Row],[VENTA TOTAL USD A PLAZO EN CLIENTE (SIN IVA)]]*(1+Tabla1[[#This Row],[% IVA ]]),"") -> 11025 | AY25: =+Tabla1[[#This Row],[VENTA TOTAL USD A PLAZO EN CLIENTE (SIN IVA)]]/Tabla1[[#This Row],[KGS]]*1000 -> 315 | AZ25: 0 | BA25: =+Tabla1[[#This Row],[GASTOS FINANCIEROS $ BOLSA 50 KG (IVA INC)]]*20/Tabla1[[#This Row],[TIPO DE CAMBIO]] -> 3.9065264 | BB25: =+Tabla1[[#This Row],[PRECIO POR TN USD EN CLIENTE A PLAZO (SIN IVA)]]+Tabla1[[#This Row],[COSTO USD FLETE /TN (SIN IVA)]]+Tabla1[[#This Row],[COSTO FINANCIERO USD POR BOLSA 50KG (IVA INC)]] -> 318.90653 | BC25: 5
A26: 46143 | B26: 1 | C26: AGROCOMMERCE SPA (CHILE) | D26: =+Tabla1[[#This Row],[FECHA Entrega]] -> 46171 | E26: PROFORMA 17 | F26: AZUCAR GRADO 4 | G26: PENDIENTE | H26: 46171 | I26: 28006 | J26: =439.5/1000*Tabla1[[#This Row],[TIPO DE CAMBIO]] -> 647.26694 | K26: =+J26*I26 -> 18127358 | L26: =IF(Tabla1[[#This Row],[TIPO OPERACIÓN]]="INDUSTRIA",Tabla1[[#This Row],[SUBTOTAL]]*0.21,IF(Tabla1[[#This Row],[TIPO OPERACIÓN]]="GDES CUENTAS",Tabla1[[#This Row],[SUBTOTAL]]*0.21,IF(Tabla1[[#This Row],[TIPO OPERACIÓN]]="TUC CTADO 2","",IF(Tabla1[[#This Row],[TIPO OPERACIÓN]]="EXPO CHILE","",IF(Tabla1[[#This Row],[TIPO OPERACIÓN]]="TUC CTADO 1",Tabla1[[#This Row],[SUBTOTAL]]*0.21,""))))) | M26: =SUM(K26:L26) -> 18127358 | N26: =+Tabla1[[#This Row],[VENTA TOTAL $ (IVA INC) ]] -> 18127358 | O26: 0 | P26: 0 | Q26: =+Tabla1[[#This Row],[VENTA TOTAL $ (IVA INC) ]]-Tabla1[[#This Row],[PENDIENTE DE ENTREGA]]-Tabla1[[#This Row],[PENDIENTE DE COBRO]]+Tabla1[[#This Row],[VALORES EN CARTERA]] -> 0 | R26: =+Tabla1[[#This Row],[FECHA FC]]+Tabla1[[#This Row],[PLAZO ENTREGA VALORES]] -> 46171 | S26: =+Tabla1[[#This Row],[FECHA FC]]+Tabla1[[#This Row],[PLAZO PAGO (DIAS)]] -> 46174 | T26: =+S26-$U$2 -> -7 | U26: 0 | W26: =+Tabla1[[#This Row],[FECHA VTO VALORES]]+7 -> 46181 | X26: PROFORMA 17 | Y26: 46027 | Z26: =Tabla1[[#This Row],[KGS]]/50 -> 560.12 | AA26: =IFERROR((IF(Tabla1[[#This Row],[TIPO OPERACIÓN]]="INDUSTRIA",Tabla1[[#This Row],[PRECIO $/ KG A PLAZO EN CLIENTE ( SIN IVA)]]*50*1.21,IF(Tabla1[[#This Row],[TIPO OPERACIÓN]]="TUC CTADO 2",Tabla1[[#This Row],[PRECIO $/ KG A PLAZO EN CLIENTE ( SIN IVA)]]*50,IF(Tabla1[[#This Row],[TIPO OPERACIÓN]]="EXPO CHILE",Tabla1[[#This Row],[PRECIO $/ KG A PLAZO EN CLIENTE ( SIN IVA)]]*50*1,IF(Tabla1[[#This Row],[TIPO OPERACIÓN]]="GDES CUENTAS",Tabla1[[#This Row],[PRECIO $/ KG A PLAZO EN CLIENTE ( SIN IVA)]]*50*1.21,IF(Tabla1[[#This Row],[TIPO OPERACIÓN]]="TUC CTADO 1",Tabla1[[#This Row],[PRECIO $/ KG A PLAZO EN CLIENTE ( SIN IVA)]]*50*1.21,"")))))),"") -> 32363.347 | AB26: -6627 | AC26: =SUM(Tabla1[[#This Row],[PRECIO $ BOLSA 50 KG (IVA INC) ]]+Tabla1[[#This Row],[COSTO FLETE $ BOLSA 50 KG (IVA INC)]]) -> 25736.347 | AD26: =-Tabla1[[#This Row],[PRECIO $ BOLSA 50 KG (IVA INC) ]]*(Tabla1[[#This Row],[TASA FINANCIACION MENSUAL]]/365)*Tabla1[[#This Row],[PLAZO ENTREGA VALORES]] -> 0 | AE26: =SUM(Tabla1[[#This Row],[PRECIO $ BOLSA50 KG FOB TUCUMAN A PLAZO (IVA INC)]]+Tabla1[[#This Row],[GASTOS FINANCIEROS $ BOLSA 50 KG (IVA INC)]]) -> 25736.347 | AF26: BIG BAG 1273 | AG26: SANTIAGO DE CHILE | AH26: CHILE | AI26: EXPO CHILE | AJ26: =IFERROR(IF(Tabla1[[#This Row],[TIPO OPERACIÓN]]="INDUSTRIA",VLOOKUP(Tabla1[[#This Row],[FECHA OC]],'PRECIO CACTU'!A:B,2,FALSE),IF(Tabla1[[#This Row],[TIPO OPERACIÓN]]="GDES CUENTAS",VLOOKUP(Tabla1[[#This Row],[FECHA OC]],'PRECIO CACTU'!A:B,2,FALSE),IF(Tabla1[[#This Row],[TIPO OPERACIÓN]]="EXPO CHILE",VLOOKUP(Tabla1[[#This Row],[FECHA OC]],'PRECIO CACTU'!A:B,2,FALSE)/1.21,IF(Tabla1[[#This Row],[TIPO OPERACIÓN]]="TUC CTADO 2",VLOOKUP(Tabla1[[#This Row],[FECHA OC]],'PRECIO CACTU'!A:B,2,FALSE)/1.21,IF(Tabla1[[#This Row],[TIPO OPERACIÓN]]="TUC CTADO 1",VLOOKUP(Tabla1[[#This Row],[FECHA OC]],'PRECIO CACTU'!A:B,2,FALSE),""))))),"") -> 25502.479 | AK26: =SUM(Tabla1[[#This Row],[PRECIO $ BOLSA 50KG FOB CDO TUC (IVA INC)]]-Tabla1[[#This Row],[PRECIO REF $ BOLSA 50 KG CACTU (IVA INC)]]) -> 233.86789 | AL26: =IFERROR(Tabla1[[#This Row],[PRECIO $ BOLSA 50KG FOB CDO TUC (IVA INC)]]/Tabla1[[#This Row],[PRECIO REF $ BOLSA 50 KG CACTU (IVA INC)]]-1,"") -> 0.0091703982 | AM26: =+Tabla1[[#This Row],[DIF $ PRECIO NETO INDUSTRIA vs Neto TUCUMAN (IVA INC)]]*Tabla1[[#This Row],[Q Bolsas Equivalentes 50kg]] -> 130994.08 | AN26: =Tabla1[[#This Row],[PRECIO REF $ BOLSA 50 KG CACTU (IVA INC)]]*Tabla1[[#This Row],[Q Bolsas Equivalentes 50kg]] -> 14284449 | AO26: =+Tabla1[[#This Row],[PRECIO $ BOLSA 50KG FOB CDO TUC (IVA INC)]]*Tabla1[[#This Row],[Q Bolsas Equivalentes 50kg]] -> 14415443 | AP26: 0.029 | AQ26: =90/20*Tabla1[[#This Row],[TIPO DE CAMBIO]] -> 6627.3066 | AR26: 3 | AT26: =+Tabla1[[#This Row],[VENTA TOTAL $ (IVA INC) ]]-(SUM(Tabla1[[#This Row],[PENDIENTE DE ENTREGA]:[VALORES COBRADOS]])) -> 0 | AU26: =VLOOKUP(Tabla1[[#This Row],[FECHA OC]],'TIPO DE CAMBIO'!A:B,2,TRUE) -> 1472.7348 | AV26: =+Tabla1[[#This Row],[SUBTOTAL]]/Tabla1[[#This Row],[TIPO DE CAMBIO]] -> 12308.637 | AX26: =IFERROR(Tabla1[[#This Row],[VENTA TOTAL USD A PLAZO EN CLIENTE (SIN IVA)]]*(1+Tabla1[[#This Row],[% IVA ]]),"") -> 12308.637 | AY26: =+Tabla1[[#This Row],[VENTA TOTAL USD A PLAZO EN CLIENTE (SIN IVA)]]/Tabla1[[#This Row],[KGS]]*1000 -> 439.5 | AZ26: =-Tabla1[[#This Row],[COSTO FLETE $ POR BOLSA 5O KG (SIN IVA)]]*20/Tabla1[[#This Row],[TIPO DE CAMBIO]] -> -90 | BA26: =+Tabla1[[#This Row],[GASTOS FINANCIEROS $ BOLSA 50 KG (IVA INC)]]*20/Tabla1[[#This Row],[TIPO DE CAMBIO]] -> 0 | BB26: =+Tabla1[[#This Row],[PRECIO POR TN USD EN CLIENTE A PLAZO (SIN IVA)]]+Tabla1[[#This Row],[COSTO USD FLETE /TN (SIN IVA)]]+Tabla1[[#This Row],[COSTO FINANCIERO USD POR BOLSA 50KG (IVA INC)]] -> 349.5 | BC26: 1
A27: 46143 | B27: 1 | C27: AGROCOMMERCE SPA (CHILE) | D27: =+Tabla1[[#This Row],[FECHA Entrega]] -> 46175 | E27: PROFORMA 17 | F27: AZUCAR GRADO 4 | G27: PENDIENTE | H27: 46175 | I27: 28006 | J27: =439.5/1000*Tabla1[[#This Row],[TIPO DE CAMBIO]] -> 647.26694 | K27: =+J27*I27 -> 18127358 | L27: =IF(Tabla1[[#This Row],[TIPO OPERACIÓN]]="INDUSTRIA",Tabla1[[#This Row],[SUBTOTAL]]*0.21,IF(Tabla1[[#This Row],[TIPO OPERACIÓN]]="GDES CUENTAS",Tabla1[[#This Row],[SUBTOTAL]]*0.21,IF(Tabla1[[#This Row],[TIPO OPERACIÓN]]="TUC CTADO 2","",IF(Tabla1[[#This Row],[TIPO OPERACIÓN]]="EXPO CHILE","",IF(Tabla1[[#This Row],[TIPO OPERACIÓN]]="TUC CTADO 1",Tabla1[[#This Row],[SUBTOTAL]]*0.21,""))))) | M27: =SUM(K27:L27) -> 18127358 | N27: =+Tabla1[[#This Row],[VENTA TOTAL $ (IVA INC) ]] -> 18127358 | O27: 0 | P27: 0 | Q27: =+Tabla1[[#This Row],[VENTA TOTAL $ (IVA INC) ]]-Tabla1[[#This Row],[PENDIENTE DE ENTREGA]]-Tabla1[[#This Row],[PENDIENTE DE COBRO]]+Tabla1[[#This Row],[VALORES EN CARTERA]] -> 0 | R27: =+Tabla1[[#This Row],[FECHA FC]]+Tabla1[[#This Row],[PLAZO ENTREGA VALORES]] -> 46175 | S27: =+Tabla1[[#This Row],[FECHA FC]]+Tabla1[[#This Row],[PLAZO PAGO (DIAS)]] -> 46178 | T27: =+S27-$U$2 -> -3 | U27: 0 | W27: =+Tabla1[[#This Row],[FECHA VTO VALORES]]+7 -> 46185 | X27: PROFORMA 17 | Y27: 46027 | Z27: =Tabla1[[#This Row],[KGS]]/50 -> 560.12 | AA27: =IFERROR((IF(Tabla1[[#This Row],[TIPO OPERACIÓN]]="INDUSTRIA",Tabla1[[#This Row],[PRECIO $/ KG A PLAZO EN CLIENTE ( SIN IVA)]]*50*1.21,IF(Tabla1[[#This Row],[TIPO OPERACIÓN]]="TUC CTADO 2",Tabla1[[#This Row],[PRECIO $/ KG A PLAZO EN CLIENTE ( SIN IVA)]]*50,IF(Tabla1[[#This Row],[TIPO OPERACIÓN]]="EXPO CHILE",Tabla1[[#This Row],[PRECIO $/ KG A PLAZO EN CLIENTE ( SIN IVA)]]*50*1,IF(Tabla1[[#This Row],[TIPO OPERACIÓN]]="GDES CUENTAS",Tabla1[[#This Row],[PRECIO $/ KG A PLAZO EN CLIENTE ( SIN IVA)]]*50*1.21,IF(Tabla1[[#This Row],[TIPO OPERACIÓN]]="TUC CTADO 1",Tabla1[[#This Row],[PRECIO $/ KG A PLAZO EN CLIENTE ( SIN IVA)]]*50*1.21,"")))))),"") -> 32363.347 | AB27: -6627 | AC27: =SUM(Tabla1[[#This Row],[PRECIO $ BOLSA 50 KG (IVA INC) ]]+Tabla1[[#This Row],[COSTO FLETE $ BOLSA 50 KG (IVA INC)]]) -> 25736.347 | AD27: =-Tabla1[[#This Row],[PRECIO $ BOLSA 50 KG (IVA INC) ]]*(Tabla1[[#This Row],[TASA FINANCIACION MENSUAL]]/365)*Tabla1[[#This Row],[PLAZO ENTREGA VALORES]] -> 0 | AE27: =SUM(Tabla1[[#This Row],[PRECIO $ BOLSA50 KG FOB TUCUMAN A PLAZO (IVA INC)]]+Tabla1[[#This Row],[GASTOS FINANCIEROS $ BOLSA 50 KG (IVA INC)]]) -> 25736.347 | AF27: BIG BAG 1273 | AG27: SANTIAGO DE CHILE | AH27: CHILE | AI27: EXPO CHILE | AJ27: =IFERROR(IF(Tabla1[[#This Row],[TIPO OPERACIÓN]]="INDUSTRIA",VLOOKUP(Tabla1[[#This Row],[FECHA OC]],'PRECIO CACTU'!A:B,2,FALSE),IF(Tabla1[[#This Row],[TIPO OPERACIÓN]]="GDES CUENTAS",VLOOKUP(Tabla1[[#This Row],[FECHA OC]],'PRECIO CACTU'!A:B,2,FALSE),IF(Tabla1[[#This Row],[TIPO OPERACIÓN]]="EXPO CHILE",VLOOKUP(Tabla1[[#This Row],[FECHA OC]],'PRECIO CACTU'!A:B,2,FALSE)/1.21,IF(Tabla1[[#This Row],[TIPO OPERACIÓN]]="TUC CTADO 2",VLOOKUP(Tabla1[[#This Row],[FECHA OC]],'PRECIO CACTU'!A:B,2,FALSE)/1.21,IF(Tabla1[[#This Row],[TIPO OPERACIÓN]]="TUC CTADO 1",VLOOKUP(Tabla1[[#This Row],[FECHA OC]],'PRECIO CACTU'!A:B,2,FALSE),""))))),"") -> 25502.479 | AK27: =SUM(Tabla1[[#This Row],[PRECIO $ BOLSA 50KG FOB CDO TUC (IVA INC)]]-Tabla1[[#This Row],[PRECIO REF $ BOLSA 50 KG CACTU (IVA INC)]]) -> 233.86789 | AL27: =IFERROR(Tabla1[[#This Row],[PRECIO $ BOLSA 50KG FOB CDO TUC (IVA INC)]]/Tabla1[[#This Row],[PRECIO REF $ BOLSA 50 KG CACTU (IVA INC)]]-1,"") -> 0.0091703982 | AM27: =+Tabla1[[#This Row],[DIF $ PRECIO NETO INDUSTRIA vs Neto TUCUMAN (IVA INC)]]*Tabla1[[#This Row],[Q Bolsas Equivalentes 50kg]] -> 130994.08 | AN27: =Tabla1[[#This Row],[PRECIO REF $ BOLSA 50 KG CACTU (IVA INC)]]*Tabla1[[#This Row],[Q Bolsas Equivalentes 50kg]] -> 14284449 | AO27: =+Tabla1[[#This Row],[PRECIO $ BOLSA 50KG FOB CDO TUC (IVA INC)]]*Tabla1[[#This Row],[Q Bolsas Equivalentes 50kg]] -> 14415443 | AP27: 0.029 | AQ27: =90/20*Tabla1[[#This Row],[TIPO DE CAMBIO]] -> 6627.3066 | AR27: 3 | AT27: =+Tabla1[[#This Row],[VENTA TOTAL $ (IVA INC) ]]-(SUM(Tabla1[[#This Row],[PENDIENTE DE ENTREGA]:[VALORES COBRADOS]])) -> 0 | AU27: =VLOOKUP(Tabla1[[#This Row],[FECHA OC]],'TIPO DE CAMBIO'!A:B,2,TRUE) -> 1472.7348 | AV27: =+Tabla1[[#This Row],[SUBTOTAL]]/Tabla1[[#This Row],[TIPO DE CAMBIO]] -> 12308.637 | AX27: =IFERROR(Tabla1[[#This Row],[VENTA TOTAL USD A PLAZO EN CLIENTE (SIN IVA)]]*(1+Tabla1[[#This Row],[% IVA ]]),"") -> 12308.637 | AY27: =+Tabla1[[#This Row],[VENTA TOTAL USD A PLAZO EN CLIENTE (SIN IVA)]]/Tabla1[[#This Row],[KGS]]*1000 -> 439.5 | AZ27: =-Tabla1[[#This Row],[COSTO FLETE $ POR BOLSA 5O KG (SIN IVA)]]*20/Tabla1[[#This Row],[TIPO DE CAMBIO]] -> -90 | BA27: =+Tabla1[[#This Row],[GASTOS FINANCIEROS $ BOLSA 50 KG (IVA INC)]]*20/Tabla1[[#This Row],[TIPO DE CAMBIO]] -> 0 | BB27: =+Tabla1[[#This Row],[PRECIO POR TN USD EN CLIENTE A PLAZO (SIN IVA)]]+Tabla1[[#This Row],[COSTO USD FLETE /TN (SIN IVA)]]+Tabla1[[#This Row],[COSTO FINANCIERO USD POR BOLSA 50KG (IVA INC)]] -> 349.5 | BC27: 1
A28: 46143 | B28: 1 | C28: AGROCOMMERCE SPA (CHILE) | D28: =+Tabla1[[#This Row],[FECHA Entrega]] -> 46175 | E28: PROFORMA 17 | F28: AZUCAR GRADO 4 | G28: PENDIENTE | H28: 46175 | I28: 28006 | J28: =439.5/1000*Tabla1[[#This Row],[TIPO DE CAMBIO]] -> 647.26694 | K28: =+J28*I28 -> 18127358 | L28: =IF(Tabla1[[#This Row],[TIPO OPERACIÓN]]="INDUSTRIA",Tabla1[[#This Row],[SUBTOTAL]]*0.21,IF(Tabla1[[#This Row],[TIPO OPERACIÓN]]="GDES CUENTAS",Tabla1[[#This Row],[SUBTOTAL]]*0.21,IF(Tabla1[[#This Row],[TIPO OPERACIÓN]]="TUC CTADO 2","",IF(Tabla1[[#This Row],[TIPO OPERACIÓN]]="EXPO CHILE","",IF(Tabla1[[#This Row],[TIPO OPERACIÓN]]="TUC CTADO 1",Tabla1[[#This Row],[SUBTOTAL]]*0.21,""))))) | M28: =SUM(K28:L28) -> 18127358 | N28: =+Tabla1[[#This Row],[VENTA TOTAL $ (IVA INC) ]] -> 18127358 | O28: 0 | P28: 0 | Q28: =+Tabla1[[#This Row],[VENTA TOTAL $ (IVA INC) ]]-Tabla1[[#This Row],[PENDIENTE DE ENTREGA]]-Tabla1[[#This Row],[PENDIENTE DE COBRO]]+Tabla1[[#This Row],[VALORES EN CARTERA]] -> 0 | R28: =+Tabla1[[#This Row],[FECHA FC]]+Tabla1[[#This Row],[PLAZO ENTREGA VALORES]] -> 46175 | S28: =+Tabla1[[#This Row],[FECHA FC]]+Tabla1[[#This Row],[PLAZO PAGO (DIAS)]] -> 46178 | T28: =+S28-$U$2 -> -3 | U28: 0 | W28: =+Tabla1[[#This Row],[FECHA VTO VALORES]]+7 -> 46185 | X28: PROFORMA 17 | Y28: 46027 | Z28: =Tabla1[[#This Row],[KGS]]/50 -> 560.12 | AA28: =IFERROR((IF(Tabla1[[#This Row],[TIPO OPERACIÓN]]="INDUSTRIA",Tabla1[[#This Row],[PRECIO $/ KG A PLAZO EN CLIENTE ( SIN IVA)]]*50*1.21,IF(Tabla1[[#This Row],[TIPO OPERACIÓN]]="TUC CTADO 2",Tabla1[[#This Row],[PRECIO $/ KG A PLAZO EN CLIENTE ( SIN IVA)]]*50,IF(Tabla1[[#This Row],[TIPO OPERACIÓN]]="EXPO CHILE",Tabla1[[#This Row],[PRECIO $/ KG A PLAZO EN CLIENTE ( SIN IVA)]]*50*1,IF(Tabla1[[#This Row],[TIPO OPERACIÓN]]="GDES CUENTAS",Tabla1[[#This Row],[PRECIO $/ KG A PLAZO EN CLIENTE ( SIN IVA)]]*50*1.21,IF(Tabla1[[#This Row],[TIPO OPERACIÓN]]="TUC CTADO 1",Tabla1[[#This Row],[PRECIO $/ KG A PLAZO EN CLIENTE ( SIN IVA)]]*50*1.21,"")))))),"") -> 32363.347 | AB28: -6627 | AC28: =SUM(Tabla1[[#This Row],[PRECIO $ BOLSA 50 KG (IVA INC) ]]+Tabla1[[#This Row],[COSTO FLETE $ BOLSA 50 KG (IVA INC)]]) -> 25736.347 | AD28: =-Tabla1[[#This Row],[PRECIO $ BOLSA 50 KG (IVA INC) ]]*(Tabla1[[#This Row],[TASA FINANCIACION MENSUAL]]/365)*Tabla1[[#This Row],[PLAZO ENTREGA VALORES]] -> 0 | AE28: =SUM(Tabla1[[#This Row],[PRECIO $ BOLSA50 KG FOB TUCUMAN A PLAZO (IVA INC)]]+Tabla1[[#This Row],[GASTOS FINANCIEROS $ BOLSA 50 KG (IVA INC)]]) -> 25736.347 | AF28: BIG BAG 1273 | AG28: SANTIAGO DE CHILE | AH28: CHILE | AI28: EXPO CHILE | AJ28: =IFERROR(IF(Tabla1[[#This Row],[TIPO OPERACIÓN]]="INDUSTRIA",VLOOKUP(Tabla1[[#This Row],[FECHA OC]],'PRECIO CACTU'!A:B,2,FALSE),IF(Tabla1[[#This Row],[TIPO OPERACIÓN]]="GDES CUENTAS",VLOOKUP(Tabla1[[#This Row],[FECHA OC]],'PRECIO CACTU'!A:B,2,FALSE),IF(Tabla1[[#This Row],[TIPO OPERACIÓN]]="EXPO CHILE",VLOOKUP(Tabla1[[#This Row],[FECHA OC]],'PRECIO CACTU'!A:B,2,FALSE)/1.21,IF(Tabla1[[#This Row],[TIPO OPERACIÓN]]="TUC CTADO 2",VLOOKUP(Tabla1[[#This Row],[FECHA OC]],'PRECIO CACTU'!A:B,2,FALSE)/1.21,IF(Tabla1[[#This Row],[TIPO OPERACIÓN]]="TUC CTADO 1",VLOOKUP(Tabla1[[#This Row],[FECHA OC]],'PRECIO CACTU'!A:B,2,FALSE),""))))),"") -> 25502.479 | AK28: =SUM(Tabla1[[#This Row],[PRECIO $ BOLSA 50KG FOB CDO TUC (IVA INC)]]-Tabla1[[#This Row],[PRECIO REF $ BOLSA 50 KG CACTU (IVA INC)]]) -> 233.86789 | AL28: =IFERROR(Tabla1[[#This Row],[PRECIO $ BOLSA 50KG FOB CDO TUC (IVA INC)]]/Tabla1[[#This Row],[PRECIO REF $ BOLSA 50 KG CACTU (IVA INC)]]-1,"") -> 0.0091703982 | AM28: =+Tabla1[[#This Row],[DIF $ PRECIO NETO INDUSTRIA vs Neto TUCUMAN (IVA INC)]]*Tabla1[[#This Row],[Q Bolsas Equivalentes 50kg]] -> 130994.08 | AN28: =Tabla1[[#This Row],[PRECIO REF $ BOLSA 50 KG CACTU (IVA INC)]]*Tabla1[[#This Row],[Q Bolsas Equivalentes 50kg]] -> 14284449 | AO28: =+Tabla1[[#This Row],[PRECIO $ BOLSA 50KG FOB CDO TUC (IVA INC)]]*Tabla1[[#This Row],[Q Bolsas Equivalentes 50kg]] -> 14415443 | AP28: 0.029 | AQ28: =90/20*Tabla1[[#This Row],[TIPO DE CAMBIO]] -> 6627.3066 | AR28: 3 | AT28: =+Tabla1[[#This Row],[VENTA TOTAL $ (IVA INC) ]]-(SUM(Tabla1[[#This Row],[PENDIENTE DE ENTREGA]:[VALORES COBRADOS]])) -> 0 | AU28: =VLOOKUP(Tabla1[[#This Row],[FECHA OC]],'TIPO DE CAMBIO'!A:B,2,TRUE) -> 1472.7348 | AV28: =+Tabla1[[#This Row],[SUBTOTAL]]/Tabla1[[#This Row],[TIPO DE CAMBIO]] -> 12308.637 | AX28: =IFERROR(Tabla1[[#This Row],[VENTA TOTAL USD A PLAZO EN CLIENTE (SIN IVA)]]*(1+Tabla1[[#This Row],[% IVA ]]),"") -> 12308.637 | AY28: =+Tabla1[[#This Row],[VENTA TOTAL USD A PLAZO EN CLIENTE (SIN IVA)]]/Tabla1[[#This Row],[KGS]]*1000 -> 439.5 | AZ28: =-Tabla1[[#This Row],[COSTO FLETE $ POR BOLSA 5O KG (SIN IVA)]]*20/Tabla1[[#This Row],[TIPO DE CAMBIO]] -> -90 | BA28: =+Tabla1[[#This Row],[GASTOS FINANCIEROS $ BOLSA 50 KG (IVA INC)]]*20/Tabla1[[#This Row],[TIPO DE CAMBIO]] -> 0 | BB28: =+Tabla1[[#This Row],[PRECIO POR TN USD EN CLIENTE A PLAZO (SIN IVA)]]+Tabla1[[#This Row],[COSTO USD FLETE /TN (SIN IVA)]]+Tabla1[[#This Row],[COSTO FINANCIERO USD POR BOLSA 50KG (IVA INC)]] -> 349.5 | BC28: 1
A29: 46143 | B29: 1 | C29: AGROCOMMERCE SPA (CHILE) | D29: =+Tabla1[[#This Row],[FECHA Entrega]] -> 46178 | E29: PROFORMA 17 | F29: AZUCAR GRADO 4 | G29: PENDIENTE | H29: 46178 | I29: 28006 | J29: =439.5/1000*Tabla1[[#This Row],[TIPO DE CAMBIO]] -> 647.26694 | K29: =+J29*I29 -> 18127358 | L29: =IF(Tabla1[[#This Row],[TIPO OPERACIÓN]]="INDUSTRIA",Tabla1[[#This Row],[SUBTOTAL]]*0.21,IF(Tabla1[[#This Row],[TIPO OPERACIÓN]]="GDES CUENTAS",Tabla1[[#This Row],[SUBTOTAL]]*0.21,IF(Tabla1[[#This Row],[TIPO OPERACIÓN]]="TUC CTADO 2","",IF(Tabla1[[#This Row],[TIPO OPERACIÓN]]="EXPO CHILE","",IF(Tabla1[[#This Row],[TIPO OPERACIÓN]]="TUC CTADO 1",Tabla1[[#This Row],[SUBTOTAL]]*0.21,""))))) | M29: =SUM(K29:L29) -> 18127358 | N29: =+Tabla1[[#This Row],[VENTA TOTAL $ (IVA INC) ]] -> 18127358 | O29: 0 | P29: 0 | Q29: =+Tabla1[[#This Row],[VENTA TOTAL $ (IVA INC) ]]-Tabla1[[#This Row],[PENDIENTE DE ENTREGA]]-Tabla1[[#This Row],[PENDIENTE DE COBRO]]+Tabla1[[#This Row],[VALORES EN CARTERA]] -> 0 | R29: =+Tabla1[[#This Row],[FECHA FC]]+Tabla1[[#This Row],[PLAZO ENTREGA VALORES]] -> 46178 | S29: =+Tabla1[[#This Row],[FECHA FC]]+Tabla1[[#This Row],[PLAZO PAGO (DIAS)]] -> 46181 | T29: =+S29-$U$2 -> 0 | U29: 0 | W29: =+Tabla1[[#This Row],[FECHA VTO VALORES]]+7 -> 46188 | X29: PROFORMA 17 | Y29: 46027 | Z29: =Tabla1[[#This Row],[KGS]]/50 -> 560.12 | AA29: =IFERROR((IF(Tabla1[[#This Row],[TIPO OPERACIÓN]]="INDUSTRIA",Tabla1[[#This Row],[PRECIO $/ KG A PLAZO EN CLIENTE ( SIN IVA)]]*50*1.21,IF(Tabla1[[#This Row],[TIPO OPERACIÓN]]="TUC CTADO 2",Tabla1[[#This Row],[PRECIO $/ KG A PLAZO EN CLIENTE ( SIN IVA)]]*50,IF(Tabla1[[#This Row],[TIPO OPERACIÓN]]="EXPO CHILE",Tabla1[[#This Row],[PRECIO $/ KG A PLAZO EN CLIENTE ( SIN IVA)]]*50*1,IF(Tabla1[[#This Row],[TIPO OPERACIÓN]]="GDES CUENTAS",Tabla1[[#This Row],[PRECIO $/ KG A PLAZO EN CLIENTE ( SIN IVA)]]*50*1.21,IF(Tabla1[[#This Row],[TIPO OPERACIÓN]]="TUC CTADO 1",Tabla1[[#This Row],[PRECIO $/ KG A PLAZO EN CLIENTE ( SIN IVA)]]*50*1.21,"")))))),"") -> 32363.347 | AB29: =-6627 -> -6627 | AC29: =SUM(Tabla1[[#This Row],[PRECIO $ BOLSA 50 KG (IVA INC) ]]+Tabla1[[#This Row],[COSTO FLETE $ BOLSA 50 KG (IVA INC)]]) -> 25736.347 | AD29: =-Tabla1[[#This Row],[PRECIO $ BOLSA 50 KG (IVA INC) ]]*(Tabla1[[#This Row],[TASA FINANCIACION MENSUAL]]/365)*Tabla1[[#This Row],[PLAZO ENTREGA VALORES]] -> 0 | AE29: =SUM(Tabla1[[#This Row],[PRECIO $ BOLSA50 KG FOB TUCUMAN A PLAZO (IVA INC)]]+Tabla1[[#This Row],[GASTOS FINANCIEROS $ BOLSA 50 KG (IVA INC)]]) -> 25736.347 | AF29: BIG BAG 1273 | AG29: SANTIAGO DE CHILE | AH29: CHILE | AI29: EXPO CHILE | AJ29: =IFERROR(IF(Tabla1[[#This Row],[TIPO OPERACIÓN]]="INDUSTRIA",VLOOKUP(Tabla1[[#This Row],[FECHA OC]],'PRECIO CACTU'!A:B,2,FALSE),IF(Tabla1[[#This Row],[TIPO OPERACIÓN]]="GDES CUENTAS",VLOOKUP(Tabla1[[#This Row],[FECHA OC]],'PRECIO CACTU'!A:B,2,FALSE),IF(Tabla1[[#This Row],[TIPO OPERACIÓN]]="EXPO CHILE",VLOOKUP(Tabla1[[#This Row],[FECHA OC]],'PRECIO CACTU'!A:B,2,FALSE)/1.21,IF(Tabla1[[#This Row],[TIPO OPERACIÓN]]="TUC CTADO 2",VLOOKUP(Tabla1[[#This Row],[FECHA OC]],'PRECIO CACTU'!A:B,2,FALSE)/1.21,IF(Tabla1[[#This Row],[TIPO OPERACIÓN]]="TUC CTADO 1",VLOOKUP(Tabla1[[#This Row],[FECHA OC]],'PRECIO CACTU'!A:B,2,FALSE),""))))),"") -> 25502.479 | AK29: =SUM(Tabla1[[#This Row],[PRECIO $ BOLSA 50KG FOB CDO TUC (IVA INC)]]-Tabla1[[#This Row],[PRECIO REF $ BOLSA 50 KG CACTU (IVA INC)]]) -> 233.86789 | AL29: =IFERROR(Tabla1[[#This Row],[PRECIO $ BOLSA 50KG FOB CDO TUC (IVA INC)]]/Tabla1[[#This Row],[PRECIO REF $ BOLSA 50 KG CACTU (IVA INC)]]-1,"") -> 0.0091703982 | AM29: =+Tabla1[[#This Row],[DIF $ PRECIO NETO INDUSTRIA vs Neto TUCUMAN (IVA INC)]]*Tabla1[[#This Row],[Q Bolsas Equivalentes 50kg]] -> 130994.08 | AN29: =Tabla1[[#This Row],[PRECIO REF $ BOLSA 50 KG CACTU (IVA INC)]]*Tabla1[[#This Row],[Q Bolsas Equivalentes 50kg]] -> 14284449 | AO29: =+Tabla1[[#This Row],[PRECIO $ BOLSA 50KG FOB CDO TUC (IVA INC)]]*Tabla1[[#This Row],[Q Bolsas Equivalentes 50kg]] -> 14415443 | AP29: 0.029 | AQ29: =90/20*Tabla1[[#This Row],[TIPO DE CAMBIO]] -> 6627.3066 | AR29: 3 | AT29: =+Tabla1[[#This Row],[VENTA TOTAL $ (IVA INC) ]]-(SUM(Tabla1[[#This Row],[PENDIENTE DE ENTREGA]:[VALORES COBRADOS]])) -> 0 | AU29: =VLOOKUP(Tabla1[[#This Row],[FECHA OC]],'TIPO DE CAMBIO'!A:B,2,TRUE) -> 1472.7348 | AV29: =+Tabla1[[#This Row],[SUBTOTAL]]/Tabla1[[#This Row],[TIPO DE CAMBIO]] -> 12308.637 | AX29: =IFERROR(Tabla1[[#This Row],[VENTA TOTAL USD A PLAZO EN CLIENTE (SIN IVA)]]*(1+Tabla1[[#This Row],[% IVA ]]),"") -> 12308.637 | AY29: =+Tabla1[[#This Row],[VENTA TOTAL USD A PLAZO EN CLIENTE (SIN IVA)]]/Tabla1[[#This Row],[KGS]]*1000 -> 439.5 | AZ29: =-Tabla1[[#This Row],[COSTO FLETE $ POR BOLSA 5O KG (SIN IVA)]]*20/Tabla1[[#This Row],[TIPO DE CAMBIO]] -> -90 | BA29: =+Tabla1[[#This Row],[GASTOS FINANCIEROS $ BOLSA 50 KG (IVA INC)]]*20/Tabla1[[#This Row],[TIPO DE CAMBIO]] -> 0 | BB29: =+Tabla1[[#This Row],[PRECIO POR TN USD EN CLIENTE A PLAZO (SIN IVA)]]+Tabla1[[#This Row],[COSTO USD FLETE /TN (SIN IVA)]]+Tabla1[[#This Row],[COSTO FINANCIERO USD POR BOLSA 50KG (IVA INC)]] -> 349.5 | BC29: 1
A30: 46143 | B30: 1 | C30: AGROCOMMERCE SPA (CHILE) | D30: =+Tabla1[[#This Row],[FECHA Entrega]] -> 46178 | E30: PROFORMA 17 | F30: AZUCAR GRADO 4 | G30: PENDIENTE | H30: 46178 | I30: 28006 | J30: =439.5/1000*Tabla1[[#This Row],[TIPO DE CAMBIO]] -> 647.26694 | K30: =+J30*I30 -> 18127358 | L30: =IF(Tabla1[[#This Row],[TIPO OPERACIÓN]]="INDUSTRIA",Tabla1[[#This Row],[SUBTOTAL]]*0.21,IF(Tabla1[[#This Row],[TIPO OPERACIÓN]]="GDES CUENTAS",Tabla1[[#This Row],[SUBTOTAL]]*0.21,IF(Tabla1[[#This Row],[TIPO OPERACIÓN]]="TUC CTADO 2","",IF(Tabla1[[#This Row],[TIPO OPERACIÓN]]="EXPO CHILE","",IF(Tabla1[[#This Row],[TIPO OPERACIÓN]]="TUC CTADO 1",Tabla1[[#This Row],[SUBTOTAL]]*0.21,""))))) | M30: =SUM(K30:L30) -> 18127358 | N30: =+Tabla1[[#This Row],[VENTA TOTAL $ (IVA INC) ]] -> 18127358 | O30: 0 | P30: 0 | Q30: =+Tabla1[[#This Row],[VENTA TOTAL $ (IVA INC) ]]-Tabla1[[#This Row],[PENDIENTE DE ENTREGA]]-Tabla1[[#This Row],[PENDIENTE DE COBRO]]+Tabla1[[#This Row],[VALORES EN CARTERA]] -> 0 | R30: =+Tabla1[[#This Row],[FECHA FC]]+Tabla1[[#This Row],[PLAZO ENTREGA VALORES]] -> 46178 | S30: =+Tabla1[[#This Row],[FECHA FC]]+Tabla1[[#This Row],[PLAZO PAGO (DIAS)]] -> 46181 | T30: =+S30-$U$2 -> 0 | U30: 0 | W30: =+Tabla1[[#This Row],[FECHA VTO VALORES]]+7 -> 46188 | X30: PROFORMA 17 | Y30: 46027 | Z30: =Tabla1[[#This Row],[KGS]]/50 -> 560.12 | AA30: =IFERROR((IF(Tabla1[[#This Row],[TIPO OPERACIÓN]]="INDUSTRIA",Tabla1[[#This Row],[PRECIO $/ KG A PLAZO EN CLIENTE ( SIN IVA)]]*50*1.21,IF(Tabla1[[#This Row],[TIPO OPERACIÓN]]="TUC CTADO 2",Tabla1[[#This Row],[PRECIO $/ KG A PLAZO EN CLIENTE ( SIN IVA)]]*50,IF(Tabla1[[#This Row],[TIPO OPERACIÓN]]="EXPO CHILE",Tabla1[[#This Row],[PRECIO $/ KG A PLAZO EN CLIENTE ( SIN IVA)]]*50*1,IF(Tabla1[[#This Row],[TIPO OPERACIÓN]]="GDES CUENTAS",Tabla1[[#This Row],[PRECIO $/ KG A PLAZO EN CLIENTE ( SIN IVA)]]*50*1.21,IF(Tabla1[[#This Row],[TIPO OPERACIÓN]]="TUC CTADO 1",Tabla1[[#This Row],[PRECIO $/ KG A PLAZO EN CLIENTE ( SIN IVA)]]*50*1.21,"")))))),"") -> 32363.347 | AB30: =-6627 -> -6627 | AC30: =SUM(Tabla1[[#This Row],[PRECIO $ BOLSA 50 KG (IVA INC) ]]+Tabla1[[#This Row],[COSTO FLETE $ BOLSA 50 KG (IVA INC)]]) -> 25736.347 | AD30: =-Tabla1[[#This Row],[PRECIO $ BOLSA 50 KG (IVA INC) ]]*(Tabla1[[#This Row],[TASA FINANCIACION MENSUAL]]/365)*Tabla1[[#This Row],[PLAZO ENTREGA VALORES]] -> 0 | AE30: =SUM(Tabla1[[#This Row],[PRECIO $ BOLSA50 KG FOB TUCUMAN A PLAZO (IVA INC)]]+Tabla1[[#This Row],[GASTOS FINANCIEROS $ BOLSA 50 KG (IVA INC)]]) -> 25736.347 | AF30: BIG BAG 1273 | AG30: SANTIAGO DE CHILE | AH30: CHILE | AI30: EXPO CHILE | AJ30: =IFERROR(IF(Tabla1[[#This Row],[TIPO OPERACIÓN]]="INDUSTRIA",VLOOKUP(Tabla1[[#This Row],[FECHA OC]],'PRECIO CACTU'!A:B,2,FALSE),IF(Tabla1[[#This Row],[TIPO OPERACIÓN]]="GDES CUENTAS",VLOOKUP(Tabla1[[#This Row],[FECHA OC]],'PRECIO CACTU'!A:B,2,FALSE),IF(Tabla1[[#This Row],[TIPO OPERACIÓN]]="EXPO CHILE",VLOOKUP(Tabla1[[#This Row],[FECHA OC]],'PRECIO CACTU'!A:B,2,FALSE)/1.21,IF(Tabla1[[#This Row],[TIPO OPERACIÓN]]="TUC CTADO 2",VLOOKUP(Tabla1[[#This Row],[FECHA OC]],'PRECIO CACTU'!A:B,2,FALSE)/1.21,IF(Tabla1[[#This Row],[TIPO OPERACIÓN]]="TUC CTADO 1",VLOOKUP(Tabla1[[#This Row],[FECHA OC]],'PRECIO CACTU'!A:B,2,FALSE),""))))),"") -> 25502.479 | AK30: =SUM(Tabla1[[#This Row],[PRECIO $ BOLSA 50KG FOB CDO TUC (IVA INC)]]-Tabla1[[#This Row],[PRECIO REF $ BOLSA 50 KG CACTU (IVA INC)]]) -> 233.86789 | AL30: =IFERROR(Tabla1[[#This Row],[PRECIO $ BOLSA 50KG FOB CDO TUC (IVA INC)]]/Tabla1[[#This Row],[PRECIO REF $ BOLSA 50 KG CACTU (IVA INC)]]-1,"") -> 0.0091703982 | AM30: =+Tabla1[[#This Row],[DIF $ PRECIO NETO INDUSTRIA vs Neto TUCUMAN (IVA INC)]]*Tabla1[[#This Row],[Q Bolsas Equivalentes 50kg]] -> 130994.08 | AN30: =Tabla1[[#This Row],[PRECIO REF $ BOLSA 50 KG CACTU (IVA INC)]]*Tabla1[[#This Row],[Q Bolsas Equivalentes 50kg]] -> 14284449 | AO30: =+Tabla1[[#This Row],[PRECIO $ BOLSA 50KG FOB CDO TUC (IVA INC)]]*Tabla1[[#This Row],[Q Bolsas Equivalentes 50kg]] -> 14415443 | AP30: 0.029 | AQ30: =90/20*Tabla1[[#This Row],[TIPO DE CAMBIO]] -> 6627.3066 | AR30: 3 | AT30: =+Tabla1[[#This Row],[VENTA TOTAL $ (IVA INC) ]]-(SUM(Tabla1[[#This Row],[PENDIENTE DE ENTREGA]:[VALORES COBRADOS]])) -> 0 | AU30: =VLOOKUP(Tabla1[[#This Row],[FECHA OC]],'TIPO DE CAMBIO'!A:B,2,TRUE) -> 1472.7348 | AV30: =+Tabla1[[#This Row],[SUBTOTAL]]/Tabla1[[#This Row],[TIPO DE CAMBIO]] -> 12308.637 | AX30: =IFERROR(Tabla1[[#This Row],[VENTA TOTAL USD A PLAZO EN CLIENTE (SIN IVA)]]*(1+Tabla1[[#This Row],[% IVA ]]),"") -> 12308.637 | AY30: =+Tabla1[[#This Row],[VENTA TOTAL USD A PLAZO EN CLIENTE (SIN IVA)]]/Tabla1[[#This Row],[KGS]]*1000 -> 439.5 | AZ30: =-Tabla1[[#This Row],[COSTO FLETE $ POR BOLSA 5O KG (SIN IVA)]]*20/Tabla1[[#This Row],[TIPO DE CAMBIO]] -> -90 | BA30: =+Tabla1[[#This Row],[GASTOS FINANCIEROS $ BOLSA 50 KG (IVA INC)]]*20/Tabla1[[#This Row],[TIPO DE CAMBIO]] -> 0 | BB30: =+Tabla1[[#This Row],[PRECIO POR TN USD EN CLIENTE A PLAZO (SIN IVA)]]+Tabla1[[#This Row],[COSTO USD FLETE /TN (SIN IVA)]]+Tabla1[[#This Row],[COSTO FINANCIERO USD POR BOLSA 50KG (IVA INC)]] -> 349.5 | BC30: 1
A31: 46143 | B31: 1 | C31: AGROCOMMERCE SPA (CHILE) | D31: =+Tabla1[[#This Row],[FECHA Entrega]] -> 46182 | E31: PROFORMA 17 | F31: AZUCAR GRADO 4 | G31: PENDIENTE | H31: 46182 | I31: 28006 | J31: =439.5/1000*Tabla1[[#This Row],[TIPO DE CAMBIO]] -> 647.26694 | K31: =+J31*I31 -> 18127358 | L31: =IF(Tabla1[[#This Row],[TIPO OPERACIÓN]]="INDUSTRIA",Tabla1[[#This Row],[SUBTOTAL]]*0.21,IF(Tabla1[[#This Row],[TIPO OPERACIÓN]]="GDES CUENTAS",Tabla1[[#This Row],[SUBTOTAL]]*0.21,IF(Tabla1[[#This Row],[TIPO OPERACIÓN]]="TUC CTADO 2","",IF(Tabla1[[#This Row],[TIPO OPERACIÓN]]="EXPO CHILE","",IF(Tabla1[[#This Row],[TIPO OPERACIÓN]]="TUC CTADO 1",Tabla1[[#This Row],[SUBTOTAL]]*0.21,""))))) | M31: =SUM(K31:L31) -> 18127358 | N31: =+Tabla1[[#This Row],[VENTA TOTAL $ (IVA INC) ]] -> 18127358 | O31: 0 | P31: 0 | Q31: =+Tabla1[[#This Row],[VENTA TOTAL $ (IVA INC) ]]-Tabla1[[#This Row],[PENDIENTE DE ENTREGA]]-Tabla1[[#This Row],[PENDIENTE DE COBRO]]+Tabla1[[#This Row],[VALORES EN CARTERA]] -> 0 | R31: =+Tabla1[[#This Row],[FECHA FC]]+Tabla1[[#This Row],[PLAZO ENTREGA VALORES]] -> 46182 | S31: =+Tabla1[[#This Row],[FECHA FC]]+Tabla1[[#This Row],[PLAZO PAGO (DIAS)]] -> 46185 | T31: =+S31-$U$2 -> 4 | U31: 0 | W31: =+Tabla1[[#This Row],[FECHA VTO VALORES]]+7 -> 46192 | X31: PROFORMA 17 | Y31: 46027 | Z31: =Tabla1[[#This Row],[KGS]]/50 -> 560.12 | AA31: =IFERROR((IF(Tabla1[[#This Row],[TIPO OPERACIÓN]]="INDUSTRIA",Tabla1[[#This Row],[PRECIO $/ KG A PLAZO EN CLIENTE ( SIN IVA)]]*50*1.21,IF(Tabla1[[#This Row],[TIPO OPERACIÓN]]="TUC CTADO 2",Tabla1[[#This Row],[PRECIO $/ KG A PLAZO EN CLIENTE ( SIN IVA)]]*50,IF(Tabla1[[#This Row],[TIPO OPERACIÓN]]="EXPO CHILE",Tabla1[[#This Row],[PRECIO $/ KG A PLAZO EN CLIENTE ( SIN IVA)]]*50*1,IF(Tabla1[[#This Row],[TIPO OPERACIÓN]]="GDES CUENTAS",Tabla1[[#This Row],[PRECIO $/ KG A PLAZO EN CLIENTE ( SIN IVA)]]*50*1.21,IF(Tabla1[[#This Row],[TIPO OPERACIÓN]]="TUC CTADO 1",Tabla1[[#This Row],[PRECIO $/ KG A PLAZO EN CLIENTE ( SIN IVA)]]*50*1.21,"")))))),"") -> 32363.347 | AB31: =-6627 -> -6627 | AC31: =SUM(Tabla1[[#This Row],[PRECIO $ BOLSA 50 KG (IVA INC) ]]+Tabla1[[#This Row],[COSTO FLETE $ BOLSA 50 KG (IVA INC)]]) -> 25736.347 | AD31: =-Tabla1[[#This Row],[PRECIO $ BOLSA 50 KG (IVA INC) ]]*(Tabla1[[#This Row],[TASA FINANCIACION MENSUAL]]/365)*Tabla1[[#This Row],[PLAZO ENTREGA VALORES]] -> 0 | AE31: =SUM(Tabla1[[#This Row],[PRECIO $ BOLSA50 KG FOB TUCUMAN A PLAZO (IVA INC)]]+Tabla1[[#This Row],[GASTOS FINANCIEROS $ BOLSA 50 KG (IVA INC)]]) -> 25736.347 | AF31: BIG BAG 1273 | AG31: SANTIAGO DE CHILE | AH31: CHILE | AI31: EXPO CHILE | AJ31: =IFERROR(IF(Tabla1[[#This Row],[TIPO OPERACIÓN]]="INDUSTRIA",VLOOKUP(Tabla1[[#This Row],[FECHA OC]],'PRECIO CACTU'!A:B,2,FALSE),IF(Tabla1[[#This Row],[TIPO OPERACIÓN]]="GDES CUENTAS",VLOOKUP(Tabla1[[#This Row],[FECHA OC]],'PRECIO CACTU'!A:B,2,FALSE),IF(Tabla1[[#This Row],[TIPO OPERACIÓN]]="EXPO CHILE",VLOOKUP(Tabla1[[#This Row],[FECHA OC]],'PRECIO CACTU'!A:B,2,FALSE)/1.21,IF(Tabla1[[#This Row],[TIPO OPERACIÓN]]="TUC CTADO 2",VLOOKUP(Tabla1[[#This Row],[FECHA OC]],'PRECIO CACTU'!A:B,2,FALSE)/1.21,IF(Tabla1[[#This Row],[TIPO OPERACIÓN]]="TUC CTADO 1",VLOOKUP(Tabla1[[#This Row],[FECHA OC]],'PRECIO CACTU'!A:B,2,FALSE),""))))),"") -> 25502.479 | AK31: =SUM(Tabla1[[#This Row],[PRECIO $ BOLSA 50KG FOB CDO TUC (IVA INC)]]-Tabla1[[#This Row],[PRECIO REF $ BOLSA 50 KG CACTU (IVA INC)]]) -> 233.86789 | AL31: =IFERROR(Tabla1[[#This Row],[PRECIO $ BOLSA 50KG FOB CDO TUC (IVA INC)]]/Tabla1[[#This Row],[PRECIO REF $ BOLSA 50 KG CACTU (IVA INC)]]-1,"") -> 0.0091703982 | AM31: =+Tabla1[[#This Row],[DIF $ PRECIO NETO INDUSTRIA vs Neto TUCUMAN (IVA INC)]]*Tabla1[[#This Row],[Q Bolsas Equivalentes 50kg]] -> 130994.08 | AN31: =Tabla1[[#This Row],[PRECIO REF $ BOLSA 50 KG CACTU (IVA INC)]]*Tabla1[[#This Row],[Q Bolsas Equivalentes 50kg]] -> 14284449 | AO31: =+Tabla1[[#This Row],[PRECIO $ BOLSA 50KG FOB CDO TUC (IVA INC)]]*Tabla1[[#This Row],[Q Bolsas Equivalentes 50kg]] -> 14415443 | AP31: 0.029 | AQ31: =90/20*Tabla1[[#This Row],[TIPO DE CAMBIO]] -> 6627.3066 | AR31: 3 | AT31: =+Tabla1[[#This Row],[VENTA TOTAL $ (IVA INC) ]]-(SUM(Tabla1[[#This Row],[PENDIENTE DE ENTREGA]:[VALORES COBRADOS]])) -> 0 | AU31: =VLOOKUP(Tabla1[[#This Row],[FECHA OC]],'TIPO DE CAMBIO'!A:B,2,TRUE) -> 1472.7348 | AV31: =+Tabla1[[#This Row],[SUBTOTAL]]/Tabla1[[#This Row],[TIPO DE CAMBIO]] -> 12308.637 | AX31: =IFERROR(Tabla1[[#This Row],[VENTA TOTAL USD A PLAZO EN CLIENTE (SIN IVA)]]*(1+Tabla1[[#This Row],[% IVA ]]),"") -> 12308.637 | AY31: =+Tabla1[[#This Row],[VENTA TOTAL USD A PLAZO EN CLIENTE (SIN IVA)]]/Tabla1[[#This Row],[KGS]]*1000 -> 439.5 | AZ31: =-Tabla1[[#This Row],[COSTO FLETE $ POR BOLSA 5O KG (SIN IVA)]]*20/Tabla1[[#This Row],[TIPO DE CAMBIO]] -> -90 | BA31: =+Tabla1[[#This Row],[GASTOS FINANCIEROS $ BOLSA 50 KG (IVA INC)]]*20/Tabla1[[#This Row],[TIPO DE CAMBIO]] -> 0 | BB31: =+Tabla1[[#This Row],[PRECIO POR TN USD EN CLIENTE A PLAZO (SIN IVA)]]+Tabla1[[#This Row],[COSTO USD FLETE /TN (SIN IVA)]]+Tabla1[[#This Row],[COSTO FINANCIERO USD POR BOLSA 50KG (IVA INC)]] -> 349.5 | BC31: 1
A32: 46143 | B32: 1 | C32: AGROCOMMERCE SPA (CHILE) | D32: =+Tabla1[[#This Row],[FECHA Entrega]] -> 46182 | E32: PROFORMA 17 | F32: AZUCAR GRADO 4 | G32: PENDIENTE | H32: 46182 | I32: 28006 | J32: =439.5/1000*Tabla1[[#This Row],[TIPO DE CAMBIO]] -> 647.26694 | K32: =+J32*I32 -> 18127358 | L32: =IF(Tabla1[[#This Row],[TIPO OPERACIÓN]]="INDUSTRIA",Tabla1[[#This Row],[SUBTOTAL]]*0.21,IF(Tabla1[[#This Row],[TIPO OPERACIÓN]]="GDES CUENTAS",Tabla1[[#This Row],[SUBTOTAL]]*0.21,IF(Tabla1[[#This Row],[TIPO OPERACIÓN]]="TUC CTADO 2","",IF(Tabla1[[#This Row],[TIPO OPERACIÓN]]="EXPO CHILE","",IF(Tabla1[[#This Row],[TIPO OPERACIÓN]]="TUC CTADO 1",Tabla1[[#This Row],[SUBTOTAL]]*0.21,""))))) | M32: =SUM(K32:L32) -> 18127358 | N32: =+Tabla1[[#This Row],[VENTA TOTAL $ (IVA INC) ]] -> 18127358 | O32: 0 | P32: 0 | Q32: =+Tabla1[[#This Row],[VENTA TOTAL $ (IVA INC) ]]-Tabla1[[#This Row],[PENDIENTE DE ENTREGA]]-Tabla1[[#This Row],[PENDIENTE DE COBRO]]+Tabla1[[#This Row],[VALORES EN CARTERA]] -> 0 | R32: =+Tabla1[[#This Row],[FECHA FC]]+Tabla1[[#This Row],[PLAZO ENTREGA VALORES]] -> 46182 | S32: =+Tabla1[[#This Row],[FECHA FC]]+Tabla1[[#This Row],[PLAZO PAGO (DIAS)]] -> 46185 | T32: =+S32-$U$2 -> 4 | U32: 0 | W32: =+Tabla1[[#This Row],[FECHA VTO VALORES]]+7 -> 46192 | X32: PROFORMA 17 | Y32: 46027 | Z32: =Tabla1[[#This Row],[KGS]]/50 -> 560.12 | AA32: =IFERROR((IF(Tabla1[[#This Row],[TIPO OPERACIÓN]]="INDUSTRIA",Tabla1[[#This Row],[PRECIO $/ KG A PLAZO EN CLIENTE ( SIN IVA)]]*50*1.21,IF(Tabla1[[#This Row],[TIPO OPERACIÓN]]="TUC CTADO 2",Tabla1[[#This Row],[PRECIO $/ KG A PLAZO EN CLIENTE ( SIN IVA)]]*50,IF(Tabla1[[#This Row],[TIPO OPERACIÓN]]="EXPO CHILE",Tabla1[[#This Row],[PRECIO $/ KG A PLAZO EN CLIENTE ( SIN IVA)]]*50*1,IF(Tabla1[[#This Row],[TIPO OPERACIÓN]]="GDES CUENTAS",Tabla1[[#This Row],[PRECIO $/ KG A PLAZO EN CLIENTE ( SIN IVA)]]*50*1.21,IF(Tabla1[[#This Row],[TIPO OPERACIÓN]]="TUC CTADO 1",Tabla1[[#This Row],[PRECIO $/ KG A PLAZO EN CLIENTE ( SIN IVA)]]*50*1.21,"")))))),"") -> 32363.347 | AB32: =-6627 -> -6627 | AC32: =SUM(Tabla1[[#This Row],[PRECIO $ BOLSA 50 KG (IVA INC) ]]+Tabla1[[#This Row],[COSTO FLETE $ BOLSA 50 KG (IVA INC)]]) -> 25736.347 | AD32: =-Tabla1[[#This Row],[PRECIO $ BOLSA 50 KG (IVA INC) ]]*(Tabla1[[#This Row],[TASA FINANCIACION MENSUAL]]/365)*Tabla1[[#This Row],[PLAZO ENTREGA VALORES]] -> 0 | AE32: =SUM(Tabla1[[#This Row],[PRECIO $ BOLSA50 KG FOB TUCUMAN A PLAZO (IVA INC)]]+Tabla1[[#This Row],[GASTOS FINANCIEROS $ BOLSA 50 KG (IVA INC)]]) -> 25736.347 | AF32: BIG BAG 1273 | AG32: SANTIAGO DE CHILE | AH32: CHILE | AI32: EXPO CHILE | AJ32: =IFERROR(IF(Tabla1[[#This Row],[TIPO OPERACIÓN]]="INDUSTRIA",VLOOKUP(Tabla1[[#This Row],[FECHA OC]],'PRECIO CACTU'!A:B,2,FALSE),IF(Tabla1[[#This Row],[TIPO OPERACIÓN]]="GDES CUENTAS",VLOOKUP(Tabla1[[#This Row],[FECHA OC]],'PRECIO CACTU'!A:B,2,FALSE),IF(Tabla1[[#This Row],[TIPO OPERACIÓN]]="EXPO CHILE",VLOOKUP(Tabla1[[#This Row],[FECHA OC]],'PRECIO CACTU'!A:B,2,FALSE)/1.21,IF(Tabla1[[#This Row],[TIPO OPERACIÓN]]="TUC CTADO 2",VLOOKUP(Tabla1[[#This Row],[FECHA OC]],'PRECIO CACTU'!A:B,2,FALSE)/1.21,IF(Tabla1[[#This Row],[TIPO OPERACIÓN]]="TUC CTADO 1",VLOOKUP(Tabla1[[#This Row],[FECHA OC]],'PRECIO CACTU'!A:B,2,FALSE),""))))),"") -> 25502.479 | AK32: =SUM(Tabla1[[#This Row],[PRECIO $ BOLSA 50KG FOB CDO TUC (IVA INC)]]-Tabla1[[#This Row],[PRECIO REF $ BOLSA 50 KG CACTU (IVA INC)]]) -> 233.86789 | AL32: =IFERROR(Tabla1[[#This Row],[PRECIO $ BOLSA 50KG FOB CDO TUC (IVA INC)]]/Tabla1[[#This Row],[PRECIO REF $ BOLSA 50 KG CACTU (IVA INC)]]-1,"") -> 0.0091703982 | AM32: =+Tabla1[[#This Row],[DIF $ PRECIO NETO INDUSTRIA vs Neto TUCUMAN (IVA INC)]]*Tabla1[[#This Row],[Q Bolsas Equivalentes 50kg]] -> 130994.08 | AN32: =Tabla1[[#This Row],[PRECIO REF $ BOLSA 50 KG CACTU (IVA INC)]]*Tabla1[[#This Row],[Q Bolsas Equivalentes 50kg]] -> 14284449 | AO32: =+Tabla1[[#This Row],[PRECIO $ BOLSA 50KG FOB CDO TUC (IVA INC)]]*Tabla1[[#This Row],[Q Bolsas Equivalentes 50kg]] -> 14415443 | AP32: 0.029 | AQ32: =90/20*Tabla1[[#This Row],[TIPO DE CAMBIO]] -> 6627.3066 | AR32: 3 | AT32: =+Tabla1[[#This Row],[VENTA TOTAL $ (IVA INC) ]]-(SUM(Tabla1[[#This Row],[PENDIENTE DE ENTREGA]:[VALORES COBRADOS]])) -> 0 | AU32: =VLOOKUP(Tabla1[[#This Row],[FECHA OC]],'TIPO DE CAMBIO'!A:B,2,TRUE) -> 1472.7348 | AV32: =+Tabla1[[#This Row],[SUBTOTAL]]/Tabla1[[#This Row],[TIPO DE CAMBIO]] -> 12308.637 | AX32: =IFERROR(Tabla1[[#This Row],[VENTA TOTAL USD A PLAZO EN CLIENTE (SIN IVA)]]*(1+Tabla1[[#This Row],[% IVA ]]),"") -> 12308.637 | AY32: =+Tabla1[[#This Row],[VENTA TOTAL USD A PLAZO EN CLIENTE (SIN IVA)]]/Tabla1[[#This Row],[KGS]]*1000 -> 439.5 | AZ32: =-Tabla1[[#This Row],[COSTO FLETE $ POR BOLSA 5O KG (SIN IVA)]]*20/Tabla1[[#This Row],[TIPO DE CAMBIO]] -> -90 | BA32: =+Tabla1[[#This Row],[GASTOS FINANCIEROS $ BOLSA 50 KG (IVA INC)]]*20/Tabla1[[#This Row],[TIPO DE CAMBIO]] -> 0 | BB32: =+Tabla1[[#This Row],[PRECIO POR TN USD EN CLIENTE A PLAZO (SIN IVA)]]+Tabla1[[#This Row],[COSTO USD FLETE /TN (SIN IVA)]]+Tabla1[[#This Row],[COSTO FINANCIERO USD POR BOLSA 50KG (IVA INC)]] -> 349.5 | BC32: 1
A33: 46143 | B33: 1 | C33: AGROCOMMERCE SPA (CHILE) | D33: =+Tabla1[[#This Row],[FECHA Entrega]] -> 46182 | E33: PROFORMA 17 | F33: AZUCAR GRADO 4 | G33: PENDIENTE | H33: 46182 | I33: 28006 | J33: =439.5/1000*Tabla1[[#This Row],[TIPO DE CAMBIO]] -> 647.26694 | K33: =+J33*I33 -> 18127358 | L33: =IF(Tabla1[[#This Row],[TIPO OPERACIÓN]]="INDUSTRIA",Tabla1[[#This Row],[SUBTOTAL]]*0.21,IF(Tabla1[[#This Row],[TIPO OPERACIÓN]]="GDES CUENTAS",Tabla1[[#This Row],[SUBTOTAL]]*0.21,IF(Tabla1[[#This Row],[TIPO OPERACIÓN]]="TUC CTADO 2","",IF(Tabla1[[#This Row],[TIPO OPERACIÓN]]="EXPO CHILE","",IF(Tabla1[[#This Row],[TIPO OPERACIÓN]]="TUC CTADO 1",Tabla1[[#This Row],[SUBTOTAL]]*0.21,""))))) | M33: =SUM(K33:L33) -> 18127358 | N33: =+Tabla1[[#This Row],[VENTA TOTAL $ (IVA INC) ]] -> 18127358 | O33: 0 | P33: 0 | Q33: =+Tabla1[[#This Row],[VENTA TOTAL $ (IVA INC) ]]-Tabla1[[#This Row],[PENDIENTE DE ENTREGA]]-Tabla1[[#This Row],[PENDIENTE DE COBRO]]+Tabla1[[#This Row],[VALORES EN CARTERA]] -> 0 | R33: =+Tabla1[[#This Row],[FECHA FC]]+Tabla1[[#This Row],[PLAZO ENTREGA VALORES]] -> 46182 | S33: =+Tabla1[[#This Row],[FECHA FC]]+Tabla1[[#This Row],[PLAZO PAGO (DIAS)]] -> 46185 | T33: =+S33-$U$2 -> 4 | U33: 0 | W33: =+Tabla1[[#This Row],[FECHA VTO VALORES]]+7 -> 46192 | X33: PROFORMA 17 | Y33: 46027 | Z33: =Tabla1[[#This Row],[KGS]]/50 -> 560.12 | AA33: =IFERROR((IF(Tabla1[[#This Row],[TIPO OPERACIÓN]]="INDUSTRIA",Tabla1[[#This Row],[PRECIO $/ KG A PLAZO EN CLIENTE ( SIN IVA)]]*50*1.21,IF(Tabla1[[#This Row],[TIPO OPERACIÓN]]="TUC CTADO 2",Tabla1[[#This Row],[PRECIO $/ KG A PLAZO EN CLIENTE ( SIN IVA)]]*50,IF(Tabla1[[#This Row],[TIPO OPERACIÓN]]="EXPO CHILE",Tabla1[[#This Row],[PRECIO $/ KG A PLAZO EN CLIENTE ( SIN IVA)]]*50*1,IF(Tabla1[[#This Row],[TIPO OPERACIÓN]]="GDES CUENTAS",Tabla1[[#This Row],[PRECIO $/ KG A PLAZO EN CLIENTE ( SIN IVA)]]*50*1.21,IF(Tabla1[[#This Row],[TIPO OPERACIÓN]]="TUC CTADO 1",Tabla1[[#This Row],[PRECIO $/ KG A PLAZO EN CLIENTE ( SIN IVA)]]*50*1.21,"")))))),"") -> 32363.347 | AB33: -6627 | AC33: =SUM(Tabla1[[#This Row],[PRECIO $ BOLSA 50 KG (IVA INC) ]]+Tabla1[[#This Row],[COSTO FLETE $ BOLSA 50 KG (IVA INC)]]) -> 25736.347 | AD33: =-Tabla1[[#This Row],[PRECIO $ BOLSA 50 KG (IVA INC) ]]*(Tabla1[[#This Row],[TASA FINANCIACION MENSUAL]]/365)*Tabla1[[#This Row],[PLAZO ENTREGA VALORES]] -> 0 | AE33: =SUM(Tabla1[[#This Row],[PRECIO $ BOLSA50 KG FOB TUCUMAN A PLAZO (IVA INC)]]+Tabla1[[#This Row],[GASTOS FINANCIEROS $ BOLSA 50 KG (IVA INC)]]) -> 25736.347 | AF33: BIG BAG 1273 | AG33: SANTIAGO DE CHILE | AH33: CHILE | AI33: EXPO CHILE | AJ33: =IFERROR(IF(Tabla1[[#This Row],[TIPO OPERACIÓN]]="INDUSTRIA",VLOOKUP(Tabla1[[#This Row],[FECHA OC]],'PRECIO CACTU'!A:B,2,FALSE),IF(Tabla1[[#This Row],[TIPO OPERACIÓN]]="GDES CUENTAS",VLOOKUP(Tabla1[[#This Row],[FECHA OC]],'PRECIO CACTU'!A:B,2,FALSE),IF(Tabla1[[#This Row],[TIPO OPERACIÓN]]="EXPO CHILE",VLOOKUP(Tabla1[[#This Row],[FECHA OC]],'PRECIO CACTU'!A:B,2,FALSE)/1.21,IF(Tabla1[[#This Row],[TIPO OPERACIÓN]]="TUC CTADO 2",VLOOKUP(Tabla1[[#This Row],[FECHA OC]],'PRECIO CACTU'!A:B,2,FALSE)/1.21,IF(Tabla1[[#This Row],[TIPO OPERACIÓN]]="TUC CTADO 1",VLOOKUP(Tabla1[[#This Row],[FECHA OC]],'PRECIO CACTU'!A:B,2,FALSE),""))))),"") -> 25502.479 | AK33: =SUM(Tabla1[[#This Row],[PRECIO $ BOLSA 50KG FOB CDO TUC (IVA INC)]]-Tabla1[[#This Row],[PRECIO REF $ BOLSA 50 KG CACTU (IVA INC)]]) -> 233.86789 | AL33: =IFERROR(Tabla1[[#This Row],[PRECIO $ BOLSA 50KG FOB CDO TUC (IVA INC)]]/Tabla1[[#This Row],[PRECIO REF $ BOLSA 50 KG CACTU (IVA INC)]]-1,"") -> 0.0091703982 | AM33: =+Tabla1[[#This Row],[DIF $ PRECIO NETO INDUSTRIA vs Neto TUCUMAN (IVA INC)]]*Tabla1[[#This Row],[Q Bolsas Equivalentes 50kg]] -> 130994.08 | AN33: =Tabla1[[#This Row],[PRECIO REF $ BOLSA 50 KG CACTU (IVA INC)]]*Tabla1[[#This Row],[Q Bolsas Equivalentes 50kg]] -> 14284449 | AO33: =+Tabla1[[#This Row],[PRECIO $ BOLSA 50KG FOB CDO TUC (IVA INC)]]*Tabla1[[#This Row],[Q Bolsas Equivalentes 50kg]] -> 14415443 | AP33: 0.029 | AQ33: =90/20*Tabla1[[#This Row],[TIPO DE CAMBIO]] -> 6627.3066 | AR33: 3 | AT33: =+Tabla1[[#This Row],[VENTA TOTAL $ (IVA INC) ]]-(SUM(Tabla1[[#This Row],[PENDIENTE DE ENTREGA]:[VALORES COBRADOS]])) -> 0 | AU33: =VLOOKUP(Tabla1[[#This Row],[FECHA OC]],'TIPO DE CAMBIO'!A:B,2,TRUE) -> 1472.7348 | AV33: =+Tabla1[[#This Row],[SUBTOTAL]]/Tabla1[[#This Row],[TIPO DE CAMBIO]] -> 12308.637 | AX33: =IFERROR(Tabla1[[#This Row],[VENTA TOTAL USD A PLAZO EN CLIENTE (SIN IVA)]]*(1+Tabla1[[#This Row],[% IVA ]]),"") -> 12308.637 | AY33: =+Tabla1[[#This Row],[VENTA TOTAL USD A PLAZO EN CLIENTE (SIN IVA)]]/Tabla1[[#This Row],[KGS]]*1000 -> 439.5 | AZ33: =-Tabla1[[#This Row],[COSTO FLETE $ POR BOLSA 5O KG (SIN IVA)]]*20/Tabla1[[#This Row],[TIPO DE CAMBIO]] -> -90 | BA33: =+Tabla1[[#This Row],[GASTOS FINANCIEROS $ BOLSA 50 KG (IVA INC)]]*20/Tabla1[[#This Row],[TIPO DE CAMBIO]] -> 0 | BB33: =+Tabla1[[#This Row],[PRECIO POR TN USD EN CLIENTE A PLAZO (SIN IVA)]]+Tabla1[[#This Row],[COSTO USD FLETE /TN (SIN IVA)]]+Tabla1[[#This Row],[COSTO FINANCIERO USD POR BOLSA 50KG (IVA INC)]] -> 349.5 | BC33: 1
A34: 46143 | B34: 1 | C34: VERAMOR DE MARMOL S.R.L. | D34: =+Tabla1[[#This Row],[FECHA Entrega]] -> 46172.42 | F34: AZUCAR COMUN TIPO A | G34: ENTREGADO | H34: 46172.42 | I34: =600*50 -> 30000 | J34: 675 | K34: =+J34*I34 -> 20250000 | L34: =IF(Tabla1[[#This Row],[TIPO OPERACIÓN]]="INDUSTRIA",Tabla1[[#This Row],[SUBTOTAL]]*0.21,IF(Tabla1[[#This Row],[TIPO OPERACIÓN]]="GDES CUENTAS",Tabla1[[#This Row],[SUBTOTAL]]*0.21,IF(Tabla1[[#This Row],[TIPO OPERACIÓN]]="TUC CTADO 2","",IF(Tabla1[[#This Row],[TIPO OPERACIÓN]]="EXPO CHILE","",IF(Tabla1[[#This Row],[TIPO OPERACIÓN]]="TUC CTADO 1",Tabla1[[#This Row],[SUBTOTAL]]*0.21,""))))) -> 4252500 | M34: =SUM(K34:L34) -> 24502500 | N34: 0 | O34: 0 | P34: 0 | Q34: =+Tabla1[[#This Row],[VENTA TOTAL $ (IVA INC) ]] -> 24502500 | R34: =+Tabla1[[#This Row],[FECHA FC]]+Tabla1[[#This Row],[PLAZO ENTREGA VALORES]] -> 46163.42 | S34: =+Tabla1[[#This Row],[FECHA FC]]+Tabla1[[#This Row],[PLAZO PAGO (DIAS)]] -> 46202.42 | T34: =+S34-$U$2 -> 21.420139 | U34: =22-31 -> -9 | W34: =+Tabla1[[#This Row],[FECHA VTO VALORES]]+7 -> 46209.42 | X34: WS 07.05.26 | Y34: 46149 | Z34: =Tabla1[[#This Row],[KGS]]/50 -> 600 | AA34: =IFERROR((IF(Tabla1[[#This Row],[TIPO OPERACIÓN]]="INDUSTRIA",Tabla1[[#This Row],[PRECIO $/ KG A PLAZO EN CLIENTE ( SIN IVA)]]*50*1.21,IF(Tabla1[[#This Row],[TIPO OPERACIÓN]]="TUC CTADO 2",Tabla1[[#This Row],[PRECIO $/ KG A PLAZO EN CLIENTE ( SIN IVA)]]*50,IF(Tabla1[[#This Row],[TIPO OPERACIÓN]]="EXPO CHILE",Tabla1[[#This Row],[PRECIO $/ KG A PLAZO EN CLIENTE ( SIN IVA)]]*50*1,IF(Tabla1[[#This Row],[TIPO OPERACIÓN]]="GDES CUENTAS",Tabla1[[#This Row],[PRECIO $/ KG A PLAZO EN CLIENTE ( SIN IVA)]]*50*1.21,IF(Tabla1[[#This Row],[TIPO OPERACIÓN]]="TUC CTADO 1",Tabla1[[#This Row],[PRECIO $/ KG A PLAZO EN CLIENTE ( SIN IVA)]]*50*1.21,"")))))),"") -> 40837.5 | AB34: =-Tabla1[[#This Row],[COSTO FLETE $ POR BOLSA 5O KG (SIN IVA)]]*1.21-Tabla1[[#This Row],[PRECIO $/ KG A PLAZO EN CLIENTE ( SIN IVA)]]*0.003*1.21*50 -> -2784.5125 | AC34: =SUM(Tabla1[[#This Row],[PRECIO $ BOLSA 50 KG (IVA INC) ]]+Tabla1[[#This Row],[COSTO FLETE $ BOLSA 50 KG (IVA INC)]]) -> 38052.988 | AD34: =-Tabla1[[#This Row],[PRECIO $ BOLSA 50 KG (IVA INC) ]]*(Tabla1[[#This Row],[TASA FINANCIACION MENSUAL]]/365)*Tabla1[[#This Row],[PLAZO ENTREGA VALORES]] -> 29.20161 | AE34: =SUM(Tabla1[[#This Row],[PRECIO $ BOLSA50 KG FOB TUCUMAN A PLAZO (IVA INC)]]+Tabla1[[#This Row],[GASTOS FINANCIEROS $ BOLSA 50 KG (IVA INC)]]) -> 38082.189 | AF34: BOLSA 50 Kgs | AG34: CORDOBA | AH34: CORDOBA | AI34: INDUSTRIA | AJ34: =IFERROR(IF(Tabla1[[#This Row],[TIPO OPERACIÓN]]="INDUSTRIA",VLOOKUP(Tabla1[[#This Row],[FECHA OC]],'PRECIO CACTU'!A:B,2,FALSE),IF(Tabla1[[#This Row],[TIPO OPERACIÓN]]="GDES CUENTAS",VLOOKUP(Tabla1[[#This Row],[FECHA OC]],'PRECIO CACTU'!A:B,2,FALSE),IF(Tabla1[[#This Row],[TIPO OPERACIÓN]]="EXPO CHILE",VLOOKUP(Tabla1[[#This Row],[FECHA OC]],'PRECIO CACTU'!A:B,2,FALSE)/1.21,IF(Tabla1[[#This Row],[TIPO OPERACIÓN]]="TUC CTADO 2",VLOOKUP(Tabla1[[#This Row],[FECHA OC]],'PRECIO CACTU'!A:B,2,FALSE)/1.21,IF(Tabla1[[#This Row],[TIPO OPERACIÓN]]="TUC CTADO 1",VLOOKUP(Tabla1[[#This Row],[FECHA OC]],'PRECIO CACTU'!A:B,2,FALSE),""))))),"") -> 36780 | AK34: =SUM(Tabla1[[#This Row],[PRECIO $ BOLSA 50KG FOB CDO TUC (IVA INC)]]-Tabla1[[#This Row],[PRECIO REF $ BOLSA 50 KG CACTU (IVA INC)]]) -> 1302.1891 | AL34: =IFERROR(Tabla1[[#This Row],[PRECIO $ BOLSA 50KG FOB CDO TUC (IVA INC)]]/Tabla1[[#This Row],[PRECIO REF $ BOLSA 50 KG CACTU (IVA INC)]]-1,"") -> 0.035404815 | AM34: =+Tabla1[[#This Row],[DIF $ PRECIO NETO INDUSTRIA vs Neto TUCUMAN (IVA INC)]]*Tabla1[[#This Row],[Q Bolsas Equivalentes 50kg]] -> 781313.47 | AN34: =Tabla1[[#This Row],[PRECIO REF $ BOLSA 50 KG CACTU (IVA INC)]]*Tabla1[[#This Row],[Q Bolsas Equivalentes 50kg]] -> 22068000 | AO34: =+Tabla1[[#This Row],[PRECIO $ BOLSA 50KG FOB CDO TUC (IVA INC)]]*Tabla1[[#This Row],[Q Bolsas Equivalentes 50kg]] -> 22849313 | AP34: 0.029 | AQ34: =44000/20 -> 2200 | AR34: 30 | AS34: 0008-00005553 | AT34: =+Tabla1[[#This Row],[VENTA TOTAL $ (IVA INC) ]]-(SUM(Tabla1[[#This Row],[PENDIENTE DE ENTREGA]:[VALORES COBRADOS]])) -> 0 | AU34: =VLOOKUP(Tabla1[[#This Row],[FECHA OC]],'TIPO DE CAMBIO'!A:B,2,TRUE) -> 1390.637 | AV34: =+Tabla1[[#This Row],[SUBTOTAL]]/Tabla1[[#This Row],[TIPO DE CAMBIO]] -> 14561.672 | AX34: =IFERROR(Tabla1[[#This Row],[VENTA TOTAL USD A PLAZO EN CLIENTE (SIN IVA)]]*(1+Tabla1[[#This Row],[% IVA ]]),"") -> 14561.672 | AY34: =+Tabla1[[#This Row],[VENTA TOTAL USD A PLAZO EN CLIENTE (SIN IVA)]]/Tabla1[[#This Row],[KGS]]*1000 -> 485.38907 | AZ34: =-Tabla1[[#This Row],[COSTO FLETE $ POR BOLSA 5O KG (SIN IVA)]]*20/Tabla1[[#This Row],[TIPO DE CAMBIO]] -> -31.640176 | BA34: =+Tabla1[[#This Row],[GASTOS FINANCIEROS $ BOLSA 50 KG (IVA INC)]]*20/Tabla1[[#This Row],[TIPO DE CAMBIO]] -> 0.41997458 | BB34: =+Tabla1[[#This Row],[PRECIO POR TN USD EN CLIENTE A PLAZO (SIN IVA)]]+Tabla1[[#This Row],[COSTO USD FLETE /TN (SIN IVA)]]+Tabla1[[#This Row],[COSTO FINANCIERO USD POR BOLSA 50KG (IVA INC)]] -> 454.16887 | BC34: 3
A35: 46143 | B35: 1 | C35: EDRA S.R.L. | D35: =+Tabla1[[#This Row],[FECHA Entrega]] -> 46180 | F35: AZUCAR COMUN TIPO A | G35: PENDIENTE | H35: 46180 | I35: 28000 | J35: 710 | K35: =+J35*I35 -> 19880000 | L35: =IF(Tabla1[[#This Row],[TIPO OPERACIÓN]]="INDUSTRIA",Tabla1[[#This Row],[SUBTOTAL]]*0.21,IF(Tabla1[[#This Row],[TIPO OPERACIÓN]]="GDES CUENTAS",Tabla1[[#This Row],[SUBTOTAL]]*0.21,IF(Tabla1[[#This Row],[TIPO OPERACIÓN]]="TUC CTADO 2","",IF(Tabla1[[#This Row],[TIPO OPERACIÓN]]="EXPO CHILE","",IF(Tabla1[[#This Row],[TIPO OPERACIÓN]]="TUC CTADO 1",Tabla1[[#This Row],[SUBTOTAL]]*0.21,""))))) -> 4174800 | M35: =SUM(K35:L35) -> 24054800 | N35: =+Tabla1[[#This Row],[VENTA TOTAL $ (IVA INC) ]] -> 24054800 | O35: 0 | P35: 0 | Q35: 0 | R35: =+Tabla1[[#This Row],[FECHA FC]]+Tabla1[[#This Row],[PLAZO ENTREGA VALORES]] -> 46187 | S35: =+Tabla1[[#This Row],[FECHA FC]]+Tabla1[[#This Row],[PLAZO PAGO (DIAS)]] -> 46195 | T35: =+S35-$U$2 -> 14 | U35: 7 | W35: =+Tabla1[[#This Row],[FECHA VTO VALORES]]+7 -> 46202 | X35: WS 13.05.26 | Y35: 46155 | Z35: =Tabla1[[#This Row],[KGS]]/50 -> 560 | AA35: =IFERROR((IF(Tabla1[[#This Row],[TIPO OPERACIÓN]]="INDUSTRIA",Tabla1[[#This Row],[PRECIO $/ KG A PLAZO EN CLIENTE ( SIN IVA)]]*50*1.21,IF(Tabla1[[#This Row],[TIPO OPERACIÓN]]="TUC CTADO 2",Tabla1[[#This Row],[PRECIO $/ KG A PLAZO EN CLIENTE ( SIN IVA)]]*50,IF(Tabla1[[#This Row],[TIPO OPERACIÓN]]="EXPO CHILE",Tabla1[[#This Row],[PRECIO $/ KG A PLAZO EN CLIENTE ( SIN IVA)]]*50*1,IF(Tabla1[[#This Row],[TIPO OPERACIÓN]]="GDES CUENTAS",Tabla1[[#This Row],[PRECIO $/ KG A PLAZO EN CLIENTE ( SIN IVA)]]*50*1.21,IF(Tabla1[[#This Row],[TIPO OPERACIÓN]]="TUC CTADO 1",Tabla1[[#This Row],[PRECIO $/ KG A PLAZO EN CLIENTE ( SIN IVA)]]*50*1.21,"")))))),"") -> 42955 | AB35: =-Tabla1[[#This Row],[COSTO FLETE $ POR BOLSA 5O KG (SIN IVA)]]*1.21-Tabla1[[#This Row],[PRECIO $/ KG A PLAZO EN CLIENTE ( SIN IVA)]]*0.003*1.21*50 -> -5271.365 | AC35: =SUM(Tabla1[[#This Row],[PRECIO $ BOLSA 50 KG (IVA INC) ]]+Tabla1[[#This Row],[COSTO FLETE $ BOLSA 50 KG (IVA INC)]]) -> 37683.635 | AD35: =-Tabla1[[#This Row],[PRECIO $ BOLSA 50 KG (IVA INC) ]]*(Tabla1[[#This Row],[TASA FINANCIACION MENSUAL]]/365)*Tabla1[[#This Row],[PLAZO ENTREGA VALORES]] -> -23.890041 | AE35: =SUM(Tabla1[[#This Row],[PRECIO $ BOLSA50 KG FOB TUCUMAN A PLAZO (IVA INC)]]+Tabla1[[#This Row],[GASTOS FINANCIEROS $ BOLSA 50 KG (IVA INC)]]) -> 37659.745 | AF35: BOLSA 50 Kgs | AG35: LOMAS DEL MIRADOR | AH35: BUENOS AIRES | AI35: INDUSTRIA | AJ35: =IFERROR(IF(Tabla1[[#This Row],[TIPO OPERACIÓN]]="INDUSTRIA",VLOOKUP(Tabla1[[#This Row],[FECHA OC]],'PRECIO CACTU'!A:B,2,FALSE),IF(Tabla1[[#This Row],[TIPO OPERACIÓN]]="GDES CUENTAS",VLOOKUP(Tabla1[[#This Row],[FECHA OC]],'PRECIO CACTU'!A:B,2,FALSE),IF(Tabla1[[#This Row],[TIPO OPERACIÓN]]="EXPO CHILE",VLOOKUP(Tabla1[[#This Row],[FECHA OC]],'PRECIO CACTU'!A:B,2,FALSE)/1.21,IF(Tabla1[[#This Row],[TIPO OPERACIÓN]]="TUC CTADO 2",VLOOKUP(Tabla1[[#This Row],[FECHA OC]],'PRECIO CACTU'!A:B,2,FALSE)/1.21,IF(Tabla1[[#This Row],[TIPO OPERACIÓN]]="TUC CTADO 1",VLOOKUP(Tabla1[[#This Row],[FECHA OC]],'PRECIO CACTU'!A:B,2,FALSE),""))))),"") -> 37095 | AK35: =SUM(Tabla1[[#This Row],[PRECIO $ BOLSA 50KG FOB CDO TUC (IVA INC)]]-Tabla1[[#This Row],[PRECIO REF $ BOLSA 50 KG CACTU (IVA INC)]]) -> 564.74496 | AL35: =IFERROR(Tabla1[[#This Row],[PRECIO $ BOLSA 50KG FOB CDO TUC (IVA INC)]]/Tabla1[[#This Row],[PRECIO REF $ BOLSA 50 KG CACTU (IVA INC)]]-1,"") -> 0.015224288 | AM35: =+Tabla1[[#This Row],[DIF $ PRECIO NETO INDUSTRIA vs Neto TUCUMAN (IVA INC)]]*Tabla1[[#This Row],[Q Bolsas Equivalentes 50kg]] -> 316257.18 | AN35: =Tabla1[[#This Row],[PRECIO REF $ BOLSA 50 KG CACTU (IVA INC)]]*Tabla1[[#This Row],[Q Bolsas Equivalentes 50kg]] -> 20773200 | AO35: =+Tabla1[[#This Row],[PRECIO $ BOLSA 50KG FOB CDO TUC (IVA INC)]]*Tabla1[[#This Row],[Q Bolsas Equivalentes 50kg]] -> 21089457 | AP35: 0.029 | AQ35: =85000/20 -> 4250 | AR35: 15 | AT35: =+Tabla1[[#This Row],[VENTA TOTAL $ (IVA INC) ]]-(SUM(Tabla1[[#This Row],[PENDIENTE DE ENTREGA]:[VALORES COBRADOS]])) -> 0 | AU35: =VLOOKUP(Tabla1[[#This Row],[FECHA OC]],'TIPO DE CAMBIO'!A:B,2,TRUE) -> 1389.2073 | AV35: =+Tabla1[[#This Row],[SUBTOTAL]]/Tabla1[[#This Row],[TIPO DE CAMBIO]] -> 14310.319 | AX35: =IFERROR(Tabla1[[#This Row],[VENTA TOTAL USD A PLAZO EN CLIENTE (SIN IVA)]]*(1+Tabla1[[#This Row],[% IVA ]]),"") -> 14310.319 | AY35: =+Tabla1[[#This Row],[VENTA TOTAL USD A PLAZO EN CLIENTE (SIN IVA)]]/Tabla1[[#This Row],[KGS]]*1000 -> 511.08283 | AZ35: =-Tabla1[[#This Row],[COSTO FLETE $ POR BOLSA 5O KG (SIN IVA)]]*20/Tabla1[[#This Row],[TIPO DE CAMBIO]] -> -61.185973 | BA35: =+Tabla1[[#This Row],[GASTOS FINANCIEROS $ BOLSA 50 KG (IVA INC)]]*20/Tabla1[[#This Row],[TIPO DE CAMBIO]] -> -0.34393774 | BB35: =+Tabla1[[#This Row],[PRECIO POR TN USD EN CLIENTE A PLAZO (SIN IVA)]]+Tabla1[[#This Row],[COSTO USD FLETE /TN (SIN IVA)]]+Tabla1[[#This Row],[COSTO FINANCIERO USD POR BOLSA 50KG (IVA INC)]] -> 449.55292 | BC35: 3
A36: 46143 | B36: 1 | C36: BON MASE | D36: =+Tabla1[[#This Row],[FECHA Entrega]] -> 46177 | F36: AZUCAR COMUN TIPO A | G36: ENTREGADO | H36: 46177 | I36: 27500 | J36: 705 | K36: =+J36*I36 -> 19387500 | L36: =IF(Tabla1[[#This Row],[TIPO OPERACIÓN]]="INDUSTRIA",Tabla1[[#This Row],[SUBTOTAL]]*0.21,IF(Tabla1[[#This Row],[TIPO OPERACIÓN]]="GDES CUENTAS",Tabla1[[#This Row],[SUBTOTAL]]*0.21,IF(Tabla1[[#This Row],[TIPO OPERACIÓN]]="TUC CTADO 2","",IF(Tabla1[[#This Row],[TIPO OPERACIÓN]]="EXPO CHILE","",IF(Tabla1[[#This Row],[TIPO OPERACIÓN]]="TUC CTADO 1",Tabla1[[#This Row],[SUBTOTAL]]*0.21,""))))) -> 4071375 | M36: =SUM(K36:L36) -> 23458875 | N36: 0 | O36: =+Tabla1[[#This Row],[VENTA TOTAL $ (IVA INC) ]] -> 23458875 | P36: 0 | Q36: =+Tabla1[[#This Row],[VENTA TOTAL $ (IVA INC) ]]-Tabla1[[#This Row],[PENDIENTE DE ENTREGA]]-Tabla1[[#This Row],[PENDIENTE DE COBRO]]+Tabla1[[#This Row],[VALORES COBRADOS]] -> 0 | R36: =+Tabla1[[#This Row],[FECHA FC]]+Tabla1[[#This Row],[PLAZO ENTREGA VALORES]] -> 46207 | S36: =+Tabla1[[#This Row],[FECHA FC]]+Tabla1[[#This Row],[PLAZO PAGO (DIAS)]] -> 46207 | T36: =+S36-$U$2 -> 26 | U36: 30 | W36: =+Tabla1[[#This Row],[FECHA VTO VALORES]]+7 -> 46214 | X36: 48825 | Y36: 46136 | Z36: =Tabla1[[#This Row],[KGS]]/50 -> 550 | AA36: =IFERROR((IF(Tabla1[[#This Row],[TIPO OPERACIÓN]]="INDUSTRIA",Tabla1[[#This Row],[PRECIO $/ KG A PLAZO EN CLIENTE ( SIN IVA)]]*50*1.21,IF(Tabla1[[#This Row],[TIPO OPERACIÓN]]="TUC CTADO 2",Tabla1[[#This Row],[PRECIO $/ KG A PLAZO EN CLIENTE ( SIN IVA)]]*50,IF(Tabla1[[#This Row],[TIPO OPERACIÓN]]="EXPO CHILE",Tabla1[[#This Row],[PRECIO $/ KG A PLAZO EN CLIENTE ( SIN IVA)]]*50*1,IF(Tabla1[[#This Row],[TIPO OPERACIÓN]]="GDES CUENTAS",Tabla1[[#This Row],[PRECIO $/ KG A PLAZO EN CLIENTE ( SIN IVA)]]*50*1.21,IF(Tabla1[[#This Row],[TIPO OPERACIÓN]]="TUC CTADO 1",Tabla1[[#This Row],[PRECIO $/ KG A PLAZO EN CLIENTE ( SIN IVA)]]*50*1.21,"")))))),"") -> 42652.5 | AB36: =-Tabla1[[#This Row],[COSTO FLETE $ POR BOLSA 5O KG (SIN IVA)]]*1.21-Tabla1[[#This Row],[PRECIO $/ KG A PLAZO EN CLIENTE ( SIN IVA)]]*0.003*1.21*50 -> -3576.4575 | AC36: =SUM(Tabla1[[#This Row],[PRECIO $ BOLSA 50 KG (IVA INC) ]]+Tabla1[[#This Row],[COSTO FLETE $ BOLSA 50 KG (IVA INC)]]) -> 39076.043 | AD36: =-Tabla1[[#This Row],[PRECIO $ BOLSA 50 KG (IVA INC) ]]*(Tabla1[[#This Row],[TASA FINANCIACION MENSUAL]]/365)*Tabla1[[#This Row],[PLAZO ENTREGA VALORES]] -> -101.66486 | AE36: =SUM(Tabla1[[#This Row],[PRECIO $ BOLSA50 KG FOB TUCUMAN A PLAZO (IVA INC)]]+Tabla1[[#This Row],[GASTOS FINANCIEROS $ BOLSA 50 KG (IVA INC)]]) -> 38974.378 | AF36: BIG BAG 1250 | AG36: PILAR | AH36: BUENOS AIRES | AI36: INDUSTRIA | AJ36: =IFERROR(IF(Tabla1[[#This Row],[TIPO OPERACIÓN]]="INDUSTRIA",VLOOKUP(Tabla1[[#This Row],[FECHA OC]],'PRECIO CACTU'!A:B,2,FALSE),IF(Tabla1[[#This Row],[TIPO OPERACIÓN]]="GDES CUENTAS",VLOOKUP(Tabla1[[#This Row],[FECHA OC]],'PRECIO CACTU'!A:B,2,FALSE),IF(Tabla1[[#This Row],[TIPO OPERACIÓN]]="EXPO CHILE",VLOOKUP(Tabla1[[#This Row],[FECHA OC]],'PRECIO CACTU'!A:B,2,FALSE)/1.21,IF(Tabla1[[#This Row],[TIPO OPERACIÓN]]="TUC CTADO 2",VLOOKUP(Tabla1[[#This Row],[FECHA OC]],'PRECIO CACTU'!A:B,2,FALSE)/1.21,IF(Tabla1[[#This Row],[TIPO OPERACIÓN]]="TUC CTADO 1",VLOOKUP(Tabla1[[#This Row],[FECHA OC]],'PRECIO CACTU'!A:B,2,FALSE),""))))),"") -> 35460 | AK36: =SUM(Tabla1[[#This Row],[PRECIO $ BOLSA 50KG FOB CDO TUC (IVA INC)]]-Tabla1[[#This Row],[PRECIO REF $ BOLSA 50 KG CACTU (IVA INC)]]) -> 3514.3776 | AL36: =IFERROR(Tabla1[[#This Row],[PRECIO $ BOLSA 50KG FOB CDO TUC (IVA INC)]]/Tabla1[[#This Row],[PRECIO REF $ BOLSA 50 KG CACTU (IVA INC)]]-1,"") -> 0.099108224 | AM36: =+Tabla1[[#This Row],[DIF $ PRECIO NETO INDUSTRIA vs Neto TUCUMAN (IVA INC)]]*Tabla1[[#This Row],[Q Bolsas Equivalentes 50kg]] -> 1932907.7 | AN36: =Tabla1[[#This Row],[PRECIO REF $ BOLSA 50 KG CACTU (IVA INC)]]*Tabla1[[#This Row],[Q Bolsas Equivalentes 50kg]] -> 19503000 | AO36: =+Tabla1[[#This Row],[PRECIO $ BOLSA 50KG FOB CDO TUC (IVA INC)]]*Tabla1[[#This Row],[Q Bolsas Equivalentes 50kg]] -> 21435908 | AP36: 0.029 | AQ36: =57000/20 -> 2850 | AR36: 30 | AS36: 0008-00005590 | AT36: =+Tabla1[[#This Row],[VENTA TOTAL $ (IVA INC) ]]-(SUM(Tabla1[[#This Row],[PENDIENTE DE ENTREGA]:[VALORES COBRADOS]])) -> 0 | AU36: =VLOOKUP(Tabla1[[#This Row],[FECHA OC]],'TIPO DE CAMBIO'!A:B,2,TRUE) -> 1397.2063 | AV36: =+Tabla1[[#This Row],[SUBTOTAL]]/Tabla1[[#This Row],[TIPO DE CAMBIO]] -> 13875.904 | AX36: =IFERROR(Tabla1[[#This Row],[VENTA TOTAL USD A PLAZO EN CLIENTE (SIN IVA)]]*(1+Tabla1[[#This Row],[% IVA ]]),"") -> 13875.904 | AY36: =+Tabla1[[#This Row],[VENTA TOTAL USD A PLAZO EN CLIENTE (SIN IVA)]]/Tabla1[[#This Row],[KGS]]*1000 -> 504.57831 | AZ36: =-Tabla1[[#This Row],[COSTO FLETE $ POR BOLSA 5O KG (SIN IVA)]]*20/Tabla1[[#This Row],[TIPO DE CAMBIO]] -> -40.795694 | BA36: =+Tabla1[[#This Row],[GASTOS FINANCIEROS $ BOLSA 50 KG (IVA INC)]]*20/Tabla1[[#This Row],[TIPO DE CAMBIO]] -> -1.4552592 | BB36: =+Tabla1[[#This Row],[PRECIO POR TN USD EN CLIENTE A PLAZO (SIN IVA)]]+Tabla1[[#This Row],[COSTO USD FLETE /TN (SIN IVA)]]+Tabla1[[#This Row],[COSTO FINANCIERO USD POR BOLSA 50KG (IVA INC)]] -> 462.32736 | BC36: 3
A37: 46143 | B37: 1 | C37: BON MASE | D37: =+Tabla1[[#This Row],[FECHA Entrega]] -> 46177 | F37: AZUCAR COMUN TIPO A | G37: ENTREGADO | H37: 46177 | I37: =3*1250 -> 3750 | J37: 705 | K37: =+J37*I37 -> 2643750 | L37: =IF(Tabla1[[#This Row],[TIPO OPERACIÓN]]="INDUSTRIA",Tabla1[[#This Row],[SUBTOTAL]]*0.21,IF(Tabla1[[#This Row],[TIPO OPERACIÓN]]="GDES CUENTAS",Tabla1[[#This Row],[SUBTOTAL]]*0.21,IF(Tabla1[[#This Row],[TIPO OPERACIÓN]]="TUC CTADO 2","",IF(Tabla1[[#This Row],[TIPO OPERACIÓN]]="EXPO CHILE","",IF(Tabla1[[#This Row],[TIPO OPERACIÓN]]="TUC CTADO 1",Tabla1[[#This Row],[SUBTOTAL]]*0.21,""))))) -> 555187.5 | M37: =SUM(K37:L37) -> 3198937.5 | N37: 0 | O37: =+Tabla1[[#This Row],[VENTA TOTAL $ (IVA INC) ]] -> 3198937.5 | P37: 0 | Q37: =+Tabla1[[#This Row],[VENTA TOTAL $ (IVA INC) ]]-Tabla1[[#This Row],[PENDIENTE DE ENTREGA]]-Tabla1[[#This Row],[PENDIENTE DE COBRO]]+Tabla1[[#This Row],[VALORES COBRADOS]] -> 0 | R37: =+Tabla1[[#This Row],[FECHA FC]]+Tabla1[[#This Row],[PLAZO ENTREGA VALORES]] -> 46207 | S37: =+Tabla1[[#This Row],[FECHA FC]]+Tabla1[[#This Row],[PLAZO PAGO (DIAS)]] -> 46207 | T37: =+S37-$U$2 -> 26 | U37: 30 | W37: =+Tabla1[[#This Row],[FECHA VTO VALORES]]+7 -> 46214 | X37: 48825 | Y37: 46136 | Z37: =Tabla1[[#This Row],[KGS]]/50 -> 75 | AA37: =IFERROR((IF(Tabla1[[#This Row],[TIPO OPERACIÓN]]="INDUSTRIA",Tabla1[[#This Row],[PRECIO $/ KG A PLAZO EN CLIENTE ( SIN IVA)]]*50*1.21,IF(Tabla1[[#This Row],[TIPO OPERACIÓN]]="TUC CTADO 2",Tabla1[[#This Row],[PRECIO $/ KG A PLAZO EN CLIENTE ( SIN IVA)]]*50,IF(Tabla1[[#This Row],[TIPO OPERACIÓN]]="EXPO CHILE",Tabla1[[#This Row],[PRECIO $/ KG A PLAZO EN CLIENTE ( SIN IVA)]]*50*1,IF(Tabla1[[#This Row],[TIPO OPERACIÓN]]="GDES CUENTAS",Tabla1[[#This Row],[PRECIO $/ KG A PLAZO EN CLIENTE ( SIN IVA)]]*50*1.21,IF(Tabla1[[#This Row],[TIPO OPERACIÓN]]="TUC CTADO 1",Tabla1[[#This Row],[PRECIO $/ KG A PLAZO EN CLIENTE ( SIN IVA)]]*50*1.21,"")))))),"") -> 42652.5 | AB37: =-Tabla1[[#This Row],[COSTO FLETE $ POR BOLSA 5O KG (SIN IVA)]]*1.21-Tabla1[[#This Row],[PRECIO $/ KG A PLAZO EN CLIENTE ( SIN IVA)]]*0.003*1.21*50 -> -3576.4575 | AC37: =SUM(Tabla1[[#This Row],[PRECIO $ BOLSA 50 KG (IVA INC) ]]+Tabla1[[#This Row],[COSTO FLETE $ BOLSA 50 KG (IVA INC)]]) -> 39076.043 | AD37: =-Tabla1[[#This Row],[PRECIO $ BOLSA 50 KG (IVA INC) ]]*(Tabla1[[#This Row],[TASA FINANCIACION MENSUAL]]/365)*Tabla1[[#This Row],[PLAZO ENTREGA VALORES]] -> -101.66486 | AE37: =SUM(Tabla1[[#This Row],[PRECIO $ BOLSA50 KG FOB TUCUMAN A PLAZO (IVA INC)]]+Tabla1[[#This Row],[GASTOS FINANCIEROS $ BOLSA 50 KG (IVA INC)]]) -> 38974.378 | AF37: BIG BAG 1250 | AG37: PILAR | AH37: BUENOS AIRES | AI37: INDUSTRIA | AJ37: =IFERROR(IF(Tabla1[[#This Row],[TIPO OPERACIÓN]]="INDUSTRIA",VLOOKUP(Tabla1[[#This Row],[FECHA OC]],'PRECIO CACTU'!A:B,2,FALSE),IF(Tabla1[[#This Row],[TIPO OPERACIÓN]]="GDES CUENTAS",VLOOKUP(Tabla1[[#This Row],[FECHA OC]],'PRECIO CACTU'!A:B,2,FALSE),IF(Tabla1[[#This Row],[TIPO OPERACIÓN]]="EXPO CHILE",VLOOKUP(Tabla1[[#This Row],[FECHA OC]],'PRECIO CACTU'!A:B,2,FALSE)/1.21,IF(Tabla1[[#This Row],[TIPO OPERACIÓN]]="TUC CTADO 2",VLOOKUP(Tabla1[[#This Row],[FECHA OC]],'PRECIO CACTU'!A:B,2,FALSE)/1.21,IF(Tabla1[[#This Row],[TIPO OPERACIÓN]]="TUC CTADO 1",VLOOKUP(Tabla1[[#This Row],[FECHA OC]],'PRECIO CACTU'!A:B,2,FALSE),""))))),"") -> 35460 | AK37: =SUM(Tabla1[[#This Row],[PRECIO $ BOLSA 50KG FOB CDO TUC (IVA INC)]]-Tabla1[[#This Row],[PRECIO REF $ BOLSA 50 KG CACTU (IVA INC)]]) -> 3514.3776 | AL37: =IFERROR(Tabla1[[#This Row],[PRECIO $ BOLSA 50KG FOB CDO TUC (IVA INC)]]/Tabla1[[#This Row],[PRECIO REF $ BOLSA 50 KG CACTU (IVA INC)]]-1,"") -> 0.099108224 | AM37: =+Tabla1[[#This Row],[DIF $ PRECIO NETO INDUSTRIA vs Neto TUCUMAN (IVA INC)]]*Tabla1[[#This Row],[Q Bolsas Equivalentes 50kg]] -> 263578.32 | AN37: =Tabla1[[#This Row],[PRECIO REF $ BOLSA 50 KG CACTU (IVA INC)]]*Tabla1[[#This Row],[Q Bolsas Equivalentes 50kg]] -> 2659500 | AO37: =+Tabla1[[#This Row],[PRECIO $ BOLSA 50KG FOB CDO TUC (IVA INC)]]*Tabla1[[#This Row],[Q Bolsas Equivalentes 50kg]] -> 2923078.3 | AP37: 0.029 | AQ37: =57000/20 -> 2850 | AR37: 30 | AS37: 0008-00005591 | AT37: =+Tabla1[[#This Row],[VENTA TOTAL $ (IVA INC) ]]-(SUM(Tabla1[[#This Row],[PENDIENTE DE ENTREGA]:[VALORES COBRADOS]])) -> 0 | AU37: =VLOOKUP(Tabla1[[#This Row],[FECHA OC]],'TIPO DE CAMBIO'!A:B,2,TRUE) -> 1397.2063 | AV37: =+Tabla1[[#This Row],[SUBTOTAL]]/Tabla1[[#This Row],[TIPO DE CAMBIO]] -> 1892.1687 | AX37: =IFERROR(Tabla1[[#This Row],[VENTA TOTAL USD A PLAZO EN CLIENTE (SIN IVA)]]*(1+Tabla1[[#This Row],[% IVA ]]),"") -> 1892.1687 | AY37: =+Tabla1[[#This Row],[VENTA TOTAL USD A PLAZO EN CLIENTE (SIN IVA)]]/Tabla1[[#This Row],[KGS]]*1000 -> 504.57831 | AZ37: =-Tabla1[[#This Row],[COSTO FLETE $ POR BOLSA 5O KG (SIN IVA)]]*20/Tabla1[[#This Row],[TIPO DE CAMBIO]] -> -40.795694 | BA37: =+Tabla1[[#This Row],[GASTOS FINANCIEROS $ BOLSA 50 KG (IVA INC)]]*20/Tabla1[[#This Row],[TIPO DE CAMBIO]] -> -1.4552592 | BB37: =+Tabla1[[#This Row],[PRECIO POR TN USD EN CLIENTE A PLAZO (SIN IVA)]]+Tabla1[[#This Row],[COSTO USD FLETE /TN (SIN IVA)]]+Tabla1[[#This Row],[COSTO FINANCIERO USD POR BOLSA 50KG (IVA INC)]] -> 462.32736 | BC37: 3 | BD37: RECIBE RECHAZO 3 BB DE CALSA
